{"endOfGameResult":"GameComplete","gameCreation":1742145769851,"gameDuration":1432,"gameEndTimestamp":1742147261589,"gameId":216867,"gameMode":"CLASSIC","gameName":"scrim| m8 game 5","gameStartTimestamp":1742145829312,"gameType":"CUSTOM_GAME","gameVersion":"15.5.662.5311","mapId":11,"participants":[{"PlayerScore0":0.0,"PlayerScore1":0.0,"PlayerScore10":0.0,"PlayerScore11":0.0,"PlayerScore2":0.0,"PlayerScore3":0.0,"PlayerScore4":0.0,"PlayerScore5":0.0,"PlayerScore6":0.0,"PlayerScore7":0.0,"PlayerScore8":0.0,"PlayerScore9":0.0,"allInPings":2,"assistMePings":0,"assists":2,"baronKills":0,"basicPings":0,"bountyLevel":2,"challenges":{"12AssistStreakCount":0.0,"HealFromMapSources":0.0,"InfernalScalePickup":0.0,"SWARM_DefeatAatrox":0.0,"SWARM_DefeatBriar":0.0,"SWARM_DefeatMiniBosses":0.0,"SWARM_EvolveWeapon":0.0,"SWARM_Have3Passives":0.0,"SWARM_KillEnemy":0.0,"SWARM_PickupGold":0.0,"SWARM_ReachLevel50":0.0,"SWARM_Survive15Min":0.0,"SWARM_WinWith5EvolvedWeapons":0.0,"abilityUses":158.0,"acesBefore15Minutes":0.0,"alliedJungleMonsterKills":0.0,"baronTakedowns":0.0,"blastConeOppositeOpponentCount":0.0,"bountyGold":0.0,"buffsStolen":0.0,"completeSupportQuestInTime":0.0,"controlWardsPlaced":0.0,"damagePerMinute":540.3109093862205,"damageTakenOnTeamPercentage":0.2726030799992445,"dancedWithRiftHerald":0.0,"deathsByEnemyChamps":6.0,"dodgeSkillShotsSmallWindow":12.0,"doubleAces":0.0,"dragonTakedowns":0.0,"earlyLaningPhaseGoldExpAdvantage":0.0,"effectiveHealAndShielding":0.0,"elderDragonKillsWithOpposingSoul":0.0,"elderDragonMultikills":0.0,"enemyChampionImmobilizations":48.0,"enemyJungleMonsterKills":0.0,"epicMonsterKillsNearEnemyJungler":0.0,"epicMonsterKillsWithin30SecondsOfSpawn":0.0,"epicMonsterSteals":0.0,"epicMonsterStolenWithoutSmite":0.0,"firstTurretKilled":0.0,"fistBumpParticipation":0.0,"flawlessAces":0.0,"fullTeamTakedown":0.0,"gameLength":1432.588370054,"goldPerMinute":314.0475441372189,"hadOpenNexus":0.0,"immobilizeAndKillWithAlly":2.0,"initialBuffCount":0.0,"initialCrabCount":0.0,"jungleCsBefore10Minutes":0.0,"junglerTakedownsNearDamagedEpicMonster":0.0,"kTurretsDestroyedBeforePlatesFall":0.0,"kda":0.6666666666666666,"killAfterHiddenWithAlly":0.0,"killParticipation":0.4444444444444444,"killedChampTookFullTeamDamageSurvived":0.0,"killingSprees":0.0,"killsNearEnemyTurret":0.0,"killsOnRecentlyHealedByAramPack":0.0,"killsUnderOwnTurret":0.0,"killsWithHelpFromEpicMonster":0.0,"knockEnemyIntoTeamAndKill":1.0,"landSkillShotsEarlyGame":9.0,"laneMinionsFirst10Minutes":65.0,"laningPhaseGoldExpAdvantage":0.0,"legendaryCount":0.0,"legendaryItemUsed":[3068.0,3119.0,3121.0],"lostAnInhibitor":0.0,"maxCsAdvantageOnLaneOpponent":1.0,"maxKillDeficit":0.0,"maxLevelLeadLaneOpponent":1.0,"mejaisFullStackInTime":0.0,"moreEnemyJungleThanOpponent":0.0,"multiKillOneSpell":0.0,"multiTurretRiftHeraldCount":0.0,"multikills":0.0,"multikillsAfterAggressiveFlash":0.0,"outerTurretExecutesBefore10Minutes":0.0,"outnumberedKills":0.0,"outnumberedNexusKill":0.0,"perfectDragonSoulsTaken":0.0,"perfectGame":0.0,"pickKillWithAlly":4.0,"poroExplosions":0.0,"quickCleanse":0.0,"quickFirstTurret":0.0,"quickSoloKills":0.0,"riftHeraldTakedowns":0.0,"saveAllyFromDeath":0.0,"scuttleCrabKills":0.0,"skillshotsDodged":71.0,"skillshotsHit":48.0,"snowballsHit":0.0,"soloBaronKills":0.0,"soloKills":0.0,"stealthWardsPlaced":7.0,"survivedSingleDigitHpCount":0.0,"survivedThreeImmobilizesInFight":13.0,"takedownOnFirstTurret":0.0,"takedowns":4.0,"takedownsAfterGainingLevelAdvantage":0.0,"takedownsBeforeJungleMinionSpawn":0.0,"takedownsFirstXMinutes":2.0,"takedownsInAlcove":0.0,"takedownsInEnemyFountain":0.0,"teamBaronKills":0.0,"teamDamagePercentage":0.17546303397382662,"teamElderDragonKills":0.0,"teamRiftHeraldKills":0.0,"tookLargeDamageSurvived":0.0,"turretPlatesTaken":0.0,"turretTakedowns":0.0,"turretsTakenWithRiftHerald":0.0,"twentyMinionsIn3SecondsCount":0.0,"twoWardsOneSweeperCount":0.0,"unseenRecalls":0.0,"visionScoreAdvantageLaneOpponent":-0.399946928024292,"visionScorePerMinute":0.6302498485146963,"voidMonsterKill":0.0,"wardTakedowns":2.0,"wardTakedownsBefore20M":2.0,"wardsGuarded":1.0},"champExperience":11083,"champLevel":13,"championId":516,"championName":"Ornn","championTransform":0,"commandPings":11,"consumablesPurchased":1,"damageDealtToBuildings":0,"damageDealtToObjectives":399,"damageDealtToTurrets":0,"damageSelfMitigated":25862,"dangerPings":0,"deaths":6,"detectorWardsPlaced":0,"doubleKills":0,"dragonKills":0,"eligibleForProgression":false,"enemyMissingPings":1,"enemyVisionPings":6,"firstBloodAssist":false,"firstBloodKill":false,"firstTowerAssist":false,"firstTowerKill":false,"gameEndedInEarlySurrender":false,"gameEndedInSurrender":true,"getBackPings":10,"goldEarned":7498,"goldSpent":6650,"holdPings":0,"individualPosition":"AFK","inhibitorKills":0,"inhibitorTakedowns":0,"inhibitorsLost":0,"item0":3047,"item1":3121,"item2":1054,"item3":3068,"item4":0,"item5":0,"item6":3364,"itemsPurchased":17,"killingSprees":0,"kills":2,"lane":"MIDDLE","largestCriticalStrike":0,"largestKillingSpree":0,"largestMultiKill":1,"longestTimeSpentLiving":499,"magicDamageDealt":44192,"magicDamageDealtToChampions":7846,"magicDamageTaken":7265,"missions":{"ActMission_S1_A2_ArenaRoundsWon":0,"ActMission_S1_A2_BloodyPetalsCollected":22,"ActMission_S1_A2_FeatsOfStrength":0,"DemonsHand_MissionPointsA":163,"DemonsHand_MissionPointsB":14,"DemonsHand_MissionPointsC":20,"DemonsHand_MissionPointsD":15,"DemonsHand_MissionPointsE":15,"DemonsHand_MissionPointsF":15,"Event_2025LR_StructuresEpicMonsters":0,"Event_S1_A2_Arena_BraveryChampions":0,"Event_S1_A2_Arena_NoxianChampions":0,"Event_S1_A2_Arena_ReviveAllies":0,"Event_S1_A2_Esports_TakedownEpicMonstersSingleGame":0,"Missions_CannonMinionsKilled":9,"Missions_ChampionTakedownsWhileGhosted":0,"Missions_ChampionTakedownsWithIgnite":0,"Missions_ChampionsHitWithAbilitiesEarlyGame":21,"Missions_ChampionsKilled":2,"Missions_CreepScore":159,"Missions_CreepScoreBy10Minutes":0,"Missions_Crepe_DamageDealtSpeedZone":0,"Missions_Crepe_SnowballLanded":0,"Missions_Crepe_TakedownsWithInhibBuff":0,"Missions_DamageToChampsWithItems":810,"Missions_DamageToStructures":0,"Missions_DestroyPlants":2,"Missions_DominationRune":0,"Missions_GoldFromStructuresDestroyed":100,"Missions_GoldFromTurretPlatesTaken":0,"Missions_GoldPerMinute":0,"Missions_HealingFromLevelObjects":0,"Missions_HexgatesUsed":0,"Missions_ImmobilizeChampions":31,"Missions_InspirationRune":0,"Missions_LegendaryItems":2,"Missions_MinionsKilled":156,"Missions_PeriodicDamage":5680,"Missions_PlaceUsefulControlWards":0,"Missions_PlaceUsefulWards":7,"Missions_PorosFed":0,"Missions_PrecisionRune":0,"Missions_ResolveRune":1,"Missions_SnowballsHit":0,"Missions_SorceryRune":0,"Missions_TakedownBaronsElderDragons":0,"Missions_TakedownDragons":0,"Missions_TakedownEpicMonsters":0,"Missions_TakedownEpicMonstersSingleGame":0,"Missions_TakedownGold":795,"Missions_TakedownStructures":0,"Missions_TakedownWards":2,"Missions_TakedownsAfterExhausting":2,"Missions_TakedownsAfterTeleporting":2,"Missions_TakedownsBefore15Min":2,"Missions_TakedownsUnderTurret":0,"Missions_TakedownsWithHelpFromMonsters":0,"Missions_TimeSpentActivelyPlaying":23,"Missions_TotalGold":0,"Missions_TrueDamageToStructures":0,"Missions_TurretPlatesDestroyed":0,"Missions_TwoChampsKilledWithSameAbility":0,"Missions_VoidMitesSummoned":0,"PlayerScore0":0.0,"PlayerScore1":0.0,"PlayerScore10":0.0,"PlayerScore11":0.0,"PlayerScore2":0.0,"PlayerScore3":0.0,"PlayerScore4":0.0,"PlayerScore5":0.0,"PlayerScore6":0.0,"PlayerScore7":0.0,"PlayerScore8":0.0,"PlayerScore9":0.0,"SeasonalMissions_TakedownAtakhan":0},"needVisionPings":0,"neutralMinionsKilled":0,"nexusKills":0,"nexusLost":1,"nexusTakedowns":0,"objectivesStolen":0,"objectivesStolenAssists":0,"onMyWayPings":4,"participantId":1,"pentaKills":0,"perks":{"statPerks":{"defense":5001,"flex":5008,"offense":5008},"styles":[{"description":"primaryStyle","selections":[{"perk":8437,"var1":415,"var2":428,"var3":0},{"perk":8446,"var1":0,"var2":0,"var3":0},{"perk":8473,"var1":775,"var2":0,"var3":0},{"perk":8451,"var1":217,"var2":0,"var3":0}],"style":8400},{"description":"subStyle","selections":[{"perk":8304,"var1":11,"var2":1,"var3":5},{"perk":8345,"var1":3,"var2":0,"var3":310}],"style":8300}]},"physicalDamageDealt":33017,"physicalDamageDealtToChampions":5054,"physicalDamageTaken":14582,"placement":0,"playerAugment1":0,"playerAugment2":0,"playerAugment3":0,"playerAugment4":0,"playerAugment5":0,"playerAugment6":0,"playerSubteamId":0,"profileIcon":29,"pushPings":0,"puuid":"235cd3e9-ccfb-5d29-8724-8ed78b41fff7","quadraKills":0,"retreatPings":0,"riotIdGameName":"BKR Szygenda","riotIdTagline":"eProd","role":"SUPPORT","sightWardsBoughtInGame":0,"spell1Casts":60,"spell1Id":12,"spell2Casts":58,"spell2Id":4,"spell3Casts":25,"spell4Casts":15,"subteamPlacement":0,"summoner1Casts":3,"summoner2Casts":3,"summonerId":3372422380578144,"summonerLevel":30,"summonerName":"","teamEarlySurrendered":false,"teamId":100,"teamPosition":"AFK","timeCCingOthers":36,"timePlayed":1432,"totalAllyJungleMinionsKilled":0,"totalDamageDealt":77210,"totalDamageDealtToChampions":12900,"totalDamageShieldedOnTeammates":0,"totalDamageTaken":24214,"totalEnemyJungleMinionsKilled":0,"totalHeal":630,"totalHealsOnTeammates":0,"totalMinionsKilled":159,"totalTimeCCDealt":344,"totalTimeSpentDead":164,"totalUnitsHealed":1,"tripleKills":0,"trueDamageDealt":0,"trueDamageDealtToChampions":0,"trueDamageTaken":2366,"turretKills":0,"turretTakedowns":0,"turretsLost":7,"unrealKills":0,"visionClearedPings":0,"visionScore":15,"visionWardsBoughtInGame":0,"wardsKilled":2,"wardsPlaced":7,"win":false},{"PlayerScore0":0.0,"PlayerScore1":0.0,"PlayerScore10":0.0,"PlayerScore11":0.0,"PlayerScore2":0.0,"PlayerScore3":0.0,"PlayerScore4":0.0,"PlayerScore5":0.0,"PlayerScore6":0.0,"PlayerScore7":0.0,"PlayerScore8":0.0,"PlayerScore9":0.0,"allInPings":0,"assistMePings":0,"assists":7,"baronKills":0,"basicPings":0,"bountyLevel":1,"challenges":{"12AssistStreakCount":0.0,"HealFromMapSources":0.0,"InfernalScalePickup":0.0,"SWARM_DefeatAatrox":0.0,"SWARM_DefeatBriar":0.0,"SWARM_DefeatMiniBosses":0.0,"SWARM_EvolveWeapon":0.0,"SWARM_Have3Passives":0.0,"SWARM_KillEnemy":0.0,"SWARM_PickupGold":0.0,"SWARM_ReachLevel50":0.0,"SWARM_Survive15Min":0.0,"SWARM_WinWith5EvolvedWeapons":0.0,"abilityUses":336.0,"acesBefore15Minutes":0.0,"alliedJungleMonsterKills":0.0,"baronTakedowns":0.0,"blastConeOppositeOpponentCount":0.0,"bountyGold":0.0,"buffsStolen":8.0,"completeSupportQuestInTime":0.0,"controlWardTimeCoverageInRiverOrEnemyHalf":0.5689458949406918,"controlWardsPlaced":4.0,"damagePerMinute":828.0158377456933,"damageTakenOnTeamPercentage":0.19974961282822087,"dancedWithRiftHerald":0.0,"deathsByEnemyChamps":7.0,"dodgeSkillShotsSmallWindow":1.0,"doubleAces":0.0,"dragonTakedowns":0.0,"earlyLaningPhaseGoldExpAdvantage":0.0,"effectiveHealAndShielding":0.0,"elderDragonKillsWithOpposingSoul":0.0,"elderDragonMultikills":0.0,"enemyChampionImmobilizations":27.0,"enemyJungleMonsterKills":0.0,"epicMonsterKillsNearEnemyJungler":0.0,"epicMonsterKillsWithin30SecondsOfSpawn":0.0,"epicMonsterSteals":0.0,"epicMonsterStolenWithoutSmite":0.0,"firstTurretKilled":0.0,"fistBumpParticipation":0.0,"flawlessAces":0.0,"fullTeamTakedown":0.0,"gameLength":1432.588370054,"getTakedownsInAllLanesEarlyJungleAsLaner":0.0,"goldPerMinute":344.51196061740774,"hadOpenNexus":0.0,"highestCrowdControlScore":1.0,"highestWardKills":1.0,"immobilizeAndKillWithAlly":7.0,"initialBuffCount":2.0,"initialCrabCount":1.0,"jungleCsBefore10Minutes":76.5500001013279,"junglerTakedownsNearDamagedEpicMonster":0.0,"kTurretsDestroyedBeforePlatesFall":0.0,"kda":1.1428571428571428,"killAfterHiddenWithAlly":0.0,"killParticipation":0.8888888888888888,"killedChampTookFullTeamDamageSurvived":0.0,"killingSprees":0.0,"killsNearEnemyTurret":0.0,"killsOnOtherLanesEarlyJungleAsLaner":0.0,"killsOnRecentlyHealedByAramPack":0.0,"killsUnderOwnTurret":0.0,"killsWithHelpFromEpicMonster":0.0,"knockEnemyIntoTeamAndKill":0.0,"landSkillShotsEarlyGame":3.0,"laneMinionsFirst10Minutes":2.0,"laningPhaseGoldExpAdvantage":0.0,"legendaryCount":0.0,"legendaryItemUsed":[6653.0,3157.0],"lostAnInhibitor":0.0,"maxCsAdvantageOnLaneOpponent":13.000000059604645,"maxKillDeficit":0.0,"maxLevelLeadLaneOpponent":2.0,"mejaisFullStackInTime":0.0,"moreEnemyJungleThanOpponent":0.0,"multiKillOneSpell":0.0,"multiTurretRiftHeraldCount":0.0,"multikills":0.0,"multikillsAfterAggressiveFlash":0.0,"outerTurretExecutesBefore10Minutes":0.0,"outnumberedKills":0.0,"outnumberedNexusKill":0.0,"perfectDragonSoulsTaken":0.0,"perfectGame":0.0,"pickKillWithAlly":8.0,"poroExplosions":0.0,"quickCleanse":0.0,"quickFirstTurret":0.0,"quickSoloKills":0.0,"riftHeraldTakedowns":0.0,"saveAllyFromDeath":0.0,"scuttleCrabKills":3.0,"skillshotsDodged":24.0,"skillshotsHit":23.0,"snowballsHit":0.0,"soloBaronKills":0.0,"soloKills":0.0,"stealthWardsPlaced":1.0,"survivedSingleDigitHpCount":0.0,"survivedThreeImmobilizesInFight":4.0,"takedownOnFirstTurret":0.0,"takedowns":8.0,"takedownsAfterGainingLevelAdvantage":0.0,"takedownsBeforeJungleMinionSpawn":0.0,"takedownsFirstXMinutes":2.0,"takedownsInAlcove":0.0,"takedownsInEnemyFountain":0.0,"teamBaronKills":0.0,"teamDamagePercentage":0.2688936472415123,"teamElderDragonKills":0.0,"teamRiftHeraldKills":0.0,"tookLargeDamageSurvived":0.0,"turretPlatesTaken":0.0,"turretTakedowns":0.0,"turretsTakenWithRiftHerald":0.0,"twentyMinionsIn3SecondsCount":0.0,"twoWardsOneSweeperCount":0.0,"unseenRecalls":0.0,"visionScoreAdvantageLaneOpponent":0.6814162731170654,"visionScorePerMinute":1.2311928862733772,"voidMonsterKill":3.0,"wardTakedowns":7.0,"wardTakedownsBefore20M":5.0,"wardsGuarded":0.0},"champExperience":10605,"champLevel":13,"championId":143,"championName":"Zyra","championTransform":0,"commandPings":25,"consumablesPurchased":5,"damageDealtToBuildings":0,"damageDealtToObjectives":6521,"damageDealtToTurrets":0,"damageSelfMitigated":9594,"dangerPings":0,"deaths":7,"detectorWardsPlaced":4,"doubleKills":0,"dragonKills":0,"eligibleForProgression":false,"enemyMissingPings":11,"enemyVisionPings":14,"firstBloodAssist":false,"firstBloodKill":false,"firstTowerAssist":false,"firstTowerKill":false,"gameEndedInEarlySurrender":false,"gameEndedInSurrender":true,"getBackPings":7,"goldEarned":8225,"goldSpent":8175,"holdPings":0,"individualPosition":"AFK","inhibitorKills":0,"inhibitorTakedowns":0,"inhibitorsLost":0,"item0":3020,"item1":6653,"item2":2055,"item3":3157,"item4":0,"item5":0,"item6":3364,"itemsPurchased":19,"killingSprees":0,"kills":1,"lane":"MIDDLE","largestCriticalStrike":0,"largestKillingSpree":0,"largestMultiKill":1,"longestTimeSpentLiving":323,"magicDamageDealt":125815,"magicDamageDealtToChampions":16561,"magicDamageTaken":6046,"missions":{"ActMission_S1_A2_ArenaRoundsWon":0,"ActMission_S1_A2_BloodyPetalsCollected":22,"ActMission_S1_A2_FeatsOfStrength":0,"DemonsHand_MissionPointsA":39,"DemonsHand_MissionPointsB":25,"DemonsHand_MissionPointsC":34,"DemonsHand_MissionPointsD":63,"DemonsHand_MissionPointsE":17,"DemonsHand_MissionPointsF":61,"Event_2025LR_StructuresEpicMonsters":3,"Event_S1_A2_Arena_BraveryChampions":0,"Event_S1_A2_Arena_NoxianChampions":0,"Event_S1_A2_Arena_ReviveAllies":0,"Event_S1_A2_Esports_TakedownEpicMonstersSingleGame":0,"Missions_CannonMinionsKilled":0,"Missions_ChampionTakedownsWhileGhosted":0,"Missions_ChampionTakedownsWithIgnite":2,"Missions_ChampionsHitWithAbilitiesEarlyGame":7,"Missions_ChampionsKilled":1,"Missions_CreepScore":164,"Missions_CreepScoreBy10Minutes":1,"Missions_Crepe_DamageDealtSpeedZone":0,"Missions_Crepe_SnowballLanded":0,"Missions_Crepe_TakedownsWithInhibBuff":0,"Missions_DamageToChampsWithItems":3535,"Missions_DamageToStructures":0,"Missions_DestroyPlants":6,"Missions_DominationRune":0,"Missions_GoldFromStructuresDestroyed":100,"Missions_GoldFromTurretPlatesTaken":0,"Missions_GoldPerMinute":0,"Missions_HealingFromLevelObjects":0,"Missions_HexgatesUsed":0,"Missions_ImmobilizeChampions":27,"Missions_InspirationRune":0,"Missions_LegendaryItems":2,"Missions_MinionsKilled":9,"Missions_PeriodicDamage":5185,"Missions_PlaceUsefulControlWards":4,"Missions_PlaceUsefulWards":5,"Missions_PorosFed":0,"Missions_PrecisionRune":0,"Missions_ResolveRune":0,"Missions_SnowballsHit":0,"Missions_SorceryRune":1,"Missions_TakedownBaronsElderDragons":0,"Missions_TakedownDragons":0,"Missions_TakedownEpicMonsters":1,"Missions_TakedownEpicMonstersSingleGame":1,"Missions_TakedownGold":971,"Missions_TakedownStructures":0,"Missions_TakedownWards":7,"Missions_TakedownsAfterExhausting":7,"Missions_TakedownsAfterTeleporting":1,"Missions_TakedownsBefore15Min":2,"Missions_TakedownsUnderTurret":0,"Missions_TakedownsWithHelpFromMonsters":0,"Missions_TimeSpentActivelyPlaying":23,"Missions_TotalGold":0,"Missions_TrueDamageToStructures":0,"Missions_TurretPlatesDestroyed":0,"Missions_TwoChampsKilledWithSameAbility":0,"Missions_VoidMitesSummoned":0,"PlayerScore0":0.0,"PlayerScore1":0.0,"PlayerScore10":0.0,"PlayerScore11":0.0,"PlayerScore2":0.0,"PlayerScore3":0.0,"PlayerScore4":0.0,"PlayerScore5":0.0,"PlayerScore6":0.0,"PlayerScore7":0.0,"PlayerScore8":0.0,"PlayerScore9":0.0,"SeasonalMissions_TakedownAtakhan":0},"needVisionPings":2,"neutralMinionsKilled":148,"nexusKills":0,"nexusLost":1,"nexusTakedowns":0,"objectivesStolen":0,"objectivesStolenAssists":0,"onMyWayPings":21,"participantId":2,"pentaKills":0,"perks":{"statPerks":{"defense":5001,"flex":5008,"offense":5007},"styles":[{"description":"primaryStyle","selections":[{"perk":8229,"var1":1450,"var2":0,"var3":0},{"perk":8224,"var1":35,"var2":194,"var3":0},{"perk":8233,"var1":14,"var2":50,"var3":0},{"perk":8232,"var1":3,"var2":50,"var3":0}],"style":8200},{"description":"subStyle","selections":[{"perk":9105,"var1":14,"var2":50,"var3":0},{"perk":8017,"var1":960,"var2":0,"var3":0}],"style":8000}]},"physicalDamageDealt":14855,"physicalDamageDealtToChampions":1309,"physicalDamageTaken":10645,"placement":0,"playerAugment1":0,"playerAugment2":0,"playerAugment3":0,"playerAugment4":0,"playerAugment5":0,"playerAugment6":0,"playerSubteamId":0,"profileIcon":5180,"pushPings":0,"puuid":"eb170a7c-2508-5783-ab22-31e7fdfc0784","quadraKills":0,"retreatPings":1,"riotIdGameName":"BKR Rhilech","riotIdTagline":"eProd","role":"SUPPORT","sightWardsBoughtInGame":0,"spell1Casts":134,"spell1Id":4,"spell2Casts":133,"spell2Id":11,"spell3Casts":58,"spell4Casts":11,"subteamPlacement":0,"summoner1Casts":4,"summoner2Casts":14,"summonerId":3372421562189152,"summonerLevel":30,"summonerName":"","teamEarlySurrendered":false,"teamId":100,"teamPosition":"UTILITY","timeCCingOthers":52,"timePlayed":1432,"totalAllyJungleMinionsKilled":0,"totalDamageDealt":190507,"totalDamageDealtToChampions":19770,"totalDamageShieldedOnTeammates":0,"totalDamageTaken":17743,"totalEnemyJungleMinionsKilled":0,"totalHeal":3384,"totalHealsOnTeammates":0,"totalMinionsKilled":16,"totalTimeCCDealt":399,"totalTimeSpentDead":157,"totalUnitsHealed":1,"tripleKills":0,"trueDamageDealt":49835,"trueDamageDealtToChampions":1898,"trueDamageTaken":1050,"turretKills":0,"turretTakedowns":0,"turretsLost":7,"unrealKills":0,"visionClearedPings":0,"visionScore":29,"visionWardsBoughtInGame":5,"wardsKilled":7,"wardsPlaced":5,"win":false},{"PlayerScore0":0.0,"PlayerScore1":0.0,"PlayerScore10":0.0,"PlayerScore11":0.0,"PlayerScore2":0.0,"PlayerScore3":0.0,"PlayerScore4":0.0,"PlayerScore5":0.0,"PlayerScore6":0.0,"PlayerScore7":0.0,"PlayerScore8":0.0,"PlayerScore9":0.0,"allInPings":0,"assistMePings":0,"assists":0,"baronKills":0,"basicPings":0,"bountyLevel":4,"challenges":{"12AssistStreakCount":0.0,"HealFromMapSources":220.0,"InfernalScalePickup":0.0,"SWARM_DefeatAatrox":0.0,"SWARM_DefeatBriar":0.0,"SWARM_DefeatMiniBosses":0.0,"SWARM_EvolveWeapon":0.0,"SWARM_Have3Passives":0.0,"SWARM_KillEnemy":0.0,"SWARM_PickupGold":0.0,"SWARM_ReachLevel50":0.0,"SWARM_Survive15Min":0.0,"SWARM_WinWith5EvolvedWeapons":0.0,"abilityUses":209.0,"acesBefore15Minutes":0.0,"alliedJungleMonsterKills":0.0,"baronTakedowns":0.0,"blastConeOppositeOpponentCount":0.0,"bountyGold":505.3736572265625,"buffsStolen":0.0,"completeSupportQuestInTime":0.0,"controlWardsPlaced":1.0,"damagePerMinute":877.4152772353021,"damageTakenOnTeamPercentage":0.23635041512523744,"dancedWithRiftHerald":0.0,"deathsByEnemyChamps":7.0,"dodgeSkillShotsSmallWindow":8.0,"doubleAces":0.0,"dragonTakedowns":0.0,"earlyLaningPhaseGoldExpAdvantage":0.0,"effectiveHealAndShielding":0.0,"elderDragonKillsWithOpposingSoul":0.0,"elderDragonMultikills":0.0,"enemyChampionImmobilizations":1.0,"enemyJungleMonsterKills":0.0,"epicMonsterKillsNearEnemyJungler":0.0,"epicMonsterKillsWithin30SecondsOfSpawn":0.0,"epicMonsterSteals":0.0,"epicMonsterStolenWithoutSmite":0.0,"firstTurretKilled":0.0,"fistBumpParticipation":0.0,"flawlessAces":0.0,"fullTeamTakedown":0.0,"gameLength":1432.588370054,"getTakedownsInAllLanesEarlyJungleAsLaner":0.0,"goldPerMinute":421.8996522591255,"hadOpenNexus":0.0,"immobilizeAndKillWithAlly":0.0,"initialBuffCount":0.0,"initialCrabCount":0.0,"jungleCsBefore10Minutes":1.2000000178813934,"junglerTakedownsNearDamagedEpicMonster":0.0,"kTurretsDestroyedBeforePlatesFall":0.0,"kda":0.5714285714285714,"killAfterHiddenWithAlly":0.0,"killParticipation":0.4444444444444444,"killedChampTookFullTeamDamageSurvived":0.0,"killingSprees":0.0,"killsNearEnemyTurret":0.0,"killsOnOtherLanesEarlyJungleAsLaner":0.0,"killsOnRecentlyHealedByAramPack":0.0,"killsUnderOwnTurret":1.0,"killsWithHelpFromEpicMonster":0.0,"knockEnemyIntoTeamAndKill":0.0,"landSkillShotsEarlyGame":5.0,"laneMinionsFirst10Minutes":73.0,"laningPhaseGoldExpAdvantage":0.0,"legendaryCount":0.0,"legendaryItemUsed":[3508.0,3031.0,3094.0],"lostAnInhibitor":0.0,"maxCsAdvantageOnLaneOpponent":30.19999983906746,"maxKillDeficit":0.0,"maxLevelLeadLaneOpponent":1.0,"mejaisFullStackInTime":0.0,"moreEnemyJungleThanOpponent":0.0,"multiKillOneSpell":0.0,"multiTurretRiftHeraldCount":0.0,"multikills":0.0,"multikillsAfterAggressiveFlash":0.0,"outerTurretExecutesBefore10Minutes":0.0,"outnumberedKills":2.0,"outnumberedNexusKill":0.0,"perfectDragonSoulsTaken":0.0,"perfectGame":0.0,"pickKillWithAlly":4.0,"poroExplosions":0.0,"quickCleanse":0.0,"quickFirstTurret":0.0,"quickSoloKills":0.0,"riftHeraldTakedowns":0.0,"saveAllyFromDeath":0.0,"scuttleCrabKills":0.0,"skillshotsDodged":52.0,"skillshotsHit":31.0,"snowballsHit":0.0,"soloBaronKills":0.0,"soloKills":0.0,"soloTurretsLategame":2.0,"stealthWardsPlaced":7.0,"survivedSingleDigitHpCount":0.0,"survivedThreeImmobilizesInFight":4.0,"takedownOnFirstTurret":0.0,"takedowns":4.0,"takedownsAfterGainingLevelAdvantage":0.0,"takedownsBeforeJungleMinionSpawn":0.0,"takedownsFirstXMinutes":0.0,"takedownsInAlcove":0.0,"takedownsInEnemyFountain":0.0,"teamBaronKills":0.0,"teamDamagePercentage":0.28493584698036195,"teamElderDragonKills":0.0,"teamRiftHeraldKills":0.0,"tookLargeDamageSurvived":0.0,"turretPlatesTaken":1.0,"turretTakedowns":2.0,"turretsTakenWithRiftHerald":0.0,"twentyMinionsIn3SecondsCount":0.0,"twoWardsOneSweeperCount":0.0,"unseenRecalls":0.0,"visionScoreAdvantageLaneOpponent":-0.5249924659729004,"visionScorePerMinute":0.6203148726605073,"voidMonsterKill":0.0,"wardTakedowns":2.0,"wardTakedownsBefore20M":1.0,"wardsGuarded":0.0},"champExperience":11656,"champLevel":14,"championId":901,"championName":"Smolder","championTransform":0,"commandPings":11,"consumablesPurchased":2,"damageDealtToBuildings":6271,"damageDealtToObjectives":6271,"damageDealtToTurrets":6271,"damageSelfMitigated":10727,"dangerPings":0,"deaths":7,"detectorWardsPlaced":1,"doubleKills":0,"dragonKills":0,"eligibleForProgression":false,"enemyMissingPings":3,"enemyVisionPings":0,"firstBloodAssist":false,"firstBloodKill":false,"firstTowerAssist":false,"firstTowerKill":false,"gameEndedInEarlySurrender":false,"gameEndedInSurrender":true,"getBackPings":0,"goldEarned":10073,"goldSpent":9725,"holdPings":0,"individualPosition":"AFK","inhibitorKills":0,"inhibitorTakedowns":0,"inhibitorsLost":0,"item0":3031,"item1":3508,"item2":1055,"item3":3094,"item4":2422,"item5":0,"item6":3363,"itemsPurchased":20,"killingSprees":2,"kills":4,"lane":"BOTTOM","largestCriticalStrike":507,"largestKillingSpree":2,"largestMultiKill":1,"longestTimeSpentLiving":328,"magicDamageDealt":9582,"magicDamageDealtToChampions":2936,"magicDamageTaken":7234,"missions":{"ActMission_S1_A2_ArenaRoundsWon":0,"ActMission_S1_A2_BloodyPetalsCollected":22,"ActMission_S1_A2_FeatsOfStrength":0,"DemonsHand_MissionPointsA":16,"DemonsHand_MissionPointsB":35,"DemonsHand_MissionPointsC":85,"DemonsHand_MissionPointsD":15,"DemonsHand_MissionPointsE":72,"DemonsHand_MissionPointsF":16,"Event_2025LR_StructuresEpicMonsters":2,"Event_S1_A2_Arena_BraveryChampions":0,"Event_S1_A2_Arena_NoxianChampions":0,"Event_S1_A2_Arena_ReviveAllies":0,"Event_S1_A2_Esports_TakedownEpicMonstersSingleGame":0,"Missions_CannonMinionsKilled":11,"Missions_ChampionTakedownsWhileGhosted":0,"Missions_ChampionTakedownsWithIgnite":0,"Missions_ChampionsHitWithAbilitiesEarlyGame":19,"Missions_ChampionsKilled":4,"Missions_CreepScore":207,"Missions_CreepScoreBy10Minutes":1,"Missions_Crepe_DamageDealtSpeedZone":0,"Missions_Crepe_SnowballLanded":0,"Missions_Crepe_TakedownsWithInhibBuff":0,"Missions_DamageToChampsWithItems":0,"Missions_DamageToStructures":6271,"Missions_DestroyPlants":9,"Missions_DominationRune":0,"Missions_GoldFromStructuresDestroyed":725,"Missions_GoldFromTurretPlatesTaken":125,"Missions_GoldPerMinute":1,"Missions_HealingFromLevelObjects":220,"Missions_HexgatesUsed":0,"Missions_ImmobilizeChampions":1,"Missions_InspirationRune":0,"Missions_LegendaryItems":3,"Missions_MinionsKilled":195,"Missions_PeriodicDamage":1547,"Missions_PlaceUsefulControlWards":0,"Missions_PlaceUsefulWards":7,"Missions_PorosFed":0,"Missions_PrecisionRune":0,"Missions_ResolveRune":1,"Missions_SnowballsHit":0,"Missions_SorceryRune":0,"Missions_TakedownBaronsElderDragons":0,"Missions_TakedownDragons":0,"Missions_TakedownEpicMonsters":0,"Missions_TakedownEpicMonstersSingleGame":0,"Missions_TakedownGold":1675,"Missions_TakedownStructures":2,"Missions_TakedownWards":2,"Missions_TakedownsAfterExhausting":0,"Missions_TakedownsAfterTeleporting":1,"Missions_TakedownsBefore15Min":0,"Missions_TakedownsUnderTurret":0,"Missions_TakedownsWithHelpFromMonsters":0,"Missions_TimeSpentActivelyPlaying":23,"Missions_TotalGold":0,"Missions_TrueDamageToStructures":387,"Missions_TurretPlatesDestroyed":1,"Missions_TwoChampsKilledWithSameAbility":0,"Missions_VoidMitesSummoned":0,"PlayerScore0":0.0,"PlayerScore1":0.0,"PlayerScore10":0.0,"PlayerScore11":0.0,"PlayerScore2":0.0,"PlayerScore3":0.0,"PlayerScore4":0.0,"PlayerScore5":0.0,"PlayerScore6":0.0,"PlayerScore7":0.0,"PlayerScore8":0.0,"PlayerScore9":0.0,"SeasonalMissions_TakedownAtakhan":0},"needVisionPings":0,"neutralMinionsKilled":5,"nexusKills":0,"nexusLost":1,"nexusTakedowns":0,"objectivesStolen":0,"objectivesStolenAssists":0,"onMyWayPings":26,"participantId":3,"pentaKills":0,"perks":{"statPerks":{"defense":5011,"flex":5008,"offense":5005},"styles":[{"description":"primaryStyle","selections":[{"perk":8437,"var1":504,"var2":338,"var3":0},{"perk":8446,"var1":1615,"var2":0,"var3":0},{"perk":8473,"var1":818,"var2":0,"var3":0},{"perk":8451,"var1":170,"var2":0,"var3":0}],"style":8400},{"description":"subStyle","selections":[{"perk":8345,"var1":3,"var2":0,"var3":297},{"perk":8304,"var1":12,"var2":0,"var3":0}],"style":8300}]},"physicalDamageDealt":134434,"physicalDamageDealtToChampions":17510,"physicalDamageTaken":12084,"placement":0,"playerAugment1":0,"playerAugment2":0,"playerAugment3":0,"playerAugment4":0,"playerAugment5":0,"playerAugment6":0,"playerSubteamId":0,"profileIcon":5848,"pushPings":0,"puuid":"75099c11-fb6b-5fbe-ab36-e7601095851a","quadraKills":0,"retreatPings":0,"riotIdGameName":"BKR OMON","riotIdTagline":"eProd","role":"SUPPORT","sightWardsBoughtInGame":0,"spell1Casts":144,"spell1Id":4,"spell2Casts":40,"spell2Id":12,"spell3Casts":19,"spell4Casts":6,"subteamPlacement":0,"summoner1Casts":3,"summoner2Casts":3,"summonerId":3373306975970656,"summonerLevel":30,"summonerName":"","teamEarlySurrendered":false,"teamId":100,"teamPosition":"BOTTOM","timeCCingOthers":9,"timePlayed":1432,"totalAllyJungleMinionsKilled":0,"totalDamageDealt":145466,"totalDamageDealtToChampions":20949,"totalDamageShieldedOnTeammates":0,"totalDamageTaken":20994,"totalEnemyJungleMinionsKilled":0,"totalHeal":3235,"totalHealsOnTeammates":0,"totalMinionsKilled":202,"totalTimeCCDealt":164,"totalTimeSpentDead":162,"totalUnitsHealed":1,"tripleKills":0,"trueDamageDealt":1449,"trueDamageDealtToChampions":502,"trueDamageTaken":1675,"turretKills":2,"turretTakedowns":2,"turretsLost":7,"unrealKills":0,"visionClearedPings":0,"visionScore":14,"visionWardsBoughtInGame":1,"wardsKilled":2,"wardsPlaced":8,"win":false},{"PlayerScore0":0.0,"PlayerScore1":0.0,"PlayerScore10":0.0,"PlayerScore11":0.0,"PlayerScore2":0.0,"PlayerScore3":0.0,"PlayerScore4":0.0,"PlayerScore5":0.0,"PlayerScore6":0.0,"PlayerScore7":0.0,"PlayerScore8":0.0,"PlayerScore9":0.0,"allInPings":0,"assistMePings":0,"assists":1,"baronKills":0,"basicPings":0,"bountyLevel":2,"challenges":{"12AssistStreakCount":0.0,"HealFromMapSources":0.0,"InfernalScalePickup":0.0,"SWARM_DefeatAatrox":0.0,"SWARM_DefeatBriar":0.0,"SWARM_DefeatMiniBosses":0.0,"SWARM_EvolveWeapon":0.0,"SWARM_Have3Passives":0.0,"SWARM_KillEnemy":0.0,"SWARM_PickupGold":0.0,"SWARM_ReachLevel50":0.0,"SWARM_Survive15Min":0.0,"SWARM_WinWith5EvolvedWeapons":0.0,"abilityUses":321.0,"acesBefore15Minutes":0.0,"alliedJungleMonsterKills":0.0,"baronTakedowns":0.0,"blastConeOppositeOpponentCount":0.0,"bountyGold":0.0,"buffsStolen":0.0,"completeSupportQuestInTime":0.0,"controlWardsPlaced":0.0,"damagePerMinute":591.8672429780295,"damageTakenOnTeamPercentage":0.11458028683770748,"dancedWithRiftHerald":0.0,"deathsByEnemyChamps":2.0,"dodgeSkillShotsSmallWindow":9.0,"doubleAces":0.0,"dragonTakedowns":0.0,"earlyLaningPhaseGoldExpAdvantage":0.0,"effectiveHealAndShielding":0.0,"elderDragonKillsWithOpposingSoul":0.0,"elderDragonMultikills":0.0,"enemyChampionImmobilizations":0.0,"enemyJungleMonsterKills":0.0,"epicMonsterKillsNearEnemyJungler":0.0,"epicMonsterKillsWithin30SecondsOfSpawn":0.0,"epicMonsterSteals":0.0,"epicMonsterStolenWithoutSmite":0.0,"firstTurretKilled":0.0,"fistBumpParticipation":0.0,"flawlessAces":0.0,"fullTeamTakedown":0.0,"gameLength":1432.588370054,"getTakedownsInAllLanesEarlyJungleAsLaner":0.0,"goldPerMinute":401.1092545050747,"hadOpenNexus":0.0,"immobilizeAndKillWithAlly":0.0,"initialBuffCount":0.0,"initialCrabCount":0.0,"jungleCsBefore10Minutes":0.0,"junglerTakedownsNearDamagedEpicMonster":0.0,"kTurretsDestroyedBeforePlatesFall":0.0,"kda":1.5,"killAfterHiddenWithAlly":0.0,"killParticipation":0.3333333333333333,"killedChampTookFullTeamDamageSurvived":0.0,"killingSprees":0.0,"killsNearEnemyTurret":0.0,"killsOnOtherLanesEarlyJungleAsLaner":0.0,"killsOnRecentlyHealedByAramPack":0.0,"killsUnderOwnTurret":0.0,"killsWithHelpFromEpicMonster":0.0,"knockEnemyIntoTeamAndKill":0.0,"landSkillShotsEarlyGame":17.0,"laneMinionsFirst10Minutes":71.0,"laningPhaseGoldExpAdvantage":0.0,"legendaryCount":0.0,"legendaryItemUsed":[3078.0,3004.0,3042.0],"lostAnInhibitor":0.0,"maxCsAdvantageOnLaneOpponent":26.0,"maxKillDeficit":0.0,"maxLevelLeadLaneOpponent":0.0,"mejaisFullStackInTime":0.0,"moreEnemyJungleThanOpponent":0.0,"multiKillOneSpell":0.0,"multiTurretRiftHeraldCount":0.0,"multikills":0.0,"multikillsAfterAggressiveFlash":0.0,"outerTurretExecutesBefore10Minutes":0.0,"outnumberedKills":0.0,"outnumberedNexusKill":0.0,"perfectDragonSoulsTaken":0.0,"perfectGame":0.0,"pickKillWithAlly":3.0,"poroExplosions":0.0,"quickCleanse":0.0,"quickFirstTurret":0.0,"quickSoloKills":0.0,"riftHeraldTakedowns":0.0,"saveAllyFromDeath":0.0,"scuttleCrabKills":0.0,"skillshotsDodged":66.0,"skillshotsHit":64.0,"snowballsHit":0.0,"soloBaronKills":0.0,"soloKills":0.0,"stealthWardsPlaced":5.0,"survivedSingleDigitHpCount":0.0,"survivedThreeImmobilizesInFight":0.0,"takedownOnFirstTurret":0.0,"takedowns":3.0,"takedownsAfterGainingLevelAdvantage":0.0,"takedownsBeforeJungleMinionSpawn":0.0,"takedownsFirstXMinutes":1.0,"takedownsInAlcove":0.0,"takedownsInEnemyFountain":0.0,"teamBaronKills":0.0,"teamDamagePercentage":0.19220567336058603,"teamElderDragonKills":0.0,"teamRiftHeraldKills":0.0,"tookLargeDamageSurvived":0.0,"turretPlatesTaken":3.0,"turretTakedowns":0.0,"turretsTakenWithRiftHerald":0.0,"twentyMinionsIn3SecondsCount":0.0,"twoWardsOneSweeperCount":0.0,"unseenRecalls":0.0,"visionScoreAdvantageLaneOpponent":-0.5164294838905334,"visionScorePerMinute":0.36020283765684596,"voidMonsterKill":0.0,"wardTakedowns":0.0,"wardTakedownsBefore20M":0.0,"wardsGuarded":0.0},"champExperience":11628,"champLevel":14,"championId":81,"championName":"Ezreal","championTransform":0,"commandPings":3,"consumablesPurchased":1,"damageDealtToBuildings":2616,"damageDealtToObjectives":4022,"damageDealtToTurrets":2616,"damageSelfMitigated":4696,"dangerPings":0,"deaths":2,"detectorWardsPlaced":0,"doubleKills":0,"dragonKills":0,"eligibleForProgression":false,"enemyMissingPings":5,"enemyVisionPings":7,"firstBloodAssist":false,"firstBloodKill":false,"firstTowerAssist":false,"firstTowerKill":false,"gameEndedInEarlySurrender":false,"gameEndedInSurrender":true,"getBackPings":1,"goldEarned":9577,"goldSpent":8858,"holdPings":0,"individualPosition":"AFK","inhibitorKills":0,"inhibitorTakedowns":0,"inhibitorsLost":0,"item0":1055,"item1":3158,"item2":3078,"item3":3042,"item4":1037,"item5":1036,"item6":3363,"itemsPurchased":19,"killingSprees":0,"kills":2,"lane":"BOTTOM","largestCriticalStrike":0,"largestKillingSpree":0,"largestMultiKill":1,"longestTimeSpentLiving":998,"magicDamageDealt":16293,"magicDamageDealtToChampions":4587,"magicDamageTaken":1881,"missions":{"ActMission_S1_A2_ArenaRoundsWon":0,"ActMission_S1_A2_BloodyPetalsCollected":22,"ActMission_S1_A2_FeatsOfStrength":0,"DemonsHand_MissionPointsA":15,"DemonsHand_MissionPointsB":26,"DemonsHand_MissionPointsC":21,"DemonsHand_MissionPointsD":14,"DemonsHand_MissionPointsE":15,"DemonsHand_MissionPointsF":150,"Event_2025LR_StructuresEpicMonsters":1,"Event_S1_A2_Arena_BraveryChampions":0,"Event_S1_A2_Arena_NoxianChampions":0,"Event_S1_A2_Arena_ReviveAllies":0,"Event_S1_A2_Esports_TakedownEpicMonstersSingleGame":0,"Missions_CannonMinionsKilled":16,"Missions_ChampionTakedownsWhileGhosted":0,"Missions_ChampionTakedownsWithIgnite":1,"Missions_ChampionsHitWithAbilitiesEarlyGame":17,"Missions_ChampionsKilled":2,"Missions_CreepScore":238,"Missions_CreepScoreBy10Minutes":1,"Missions_Crepe_DamageDealtSpeedZone":0,"Missions_Crepe_SnowballLanded":0,"Missions_Crepe_TakedownsWithInhibBuff":0,"Missions_DamageToChampsWithItems":1734,"Missions_DamageToStructures":2616,"Missions_DestroyPlants":3,"Missions_DominationRune":0,"Missions_GoldFromStructuresDestroyed":475,"Missions_GoldFromTurretPlatesTaken":375,"Missions_GoldPerMinute":1,"Missions_HealingFromLevelObjects":0,"Missions_HexgatesUsed":0,"Missions_ImmobilizeChampions":0,"Missions_InspirationRune":0,"Missions_LegendaryItems":2,"Missions_MinionsKilled":219,"Missions_PeriodicDamage":478,"Missions_PlaceUsefulControlWards":0,"Missions_PlaceUsefulWards":7,"Missions_PorosFed":0,"Missions_PrecisionRune":1,"Missions_ResolveRune":0,"Missions_SnowballsHit":0,"Missions_SorceryRune":0,"Missions_TakedownBaronsElderDragons":0,"Missions_TakedownDragons":0,"Missions_TakedownEpicMonsters":1,"Missions_TakedownEpicMonstersSingleGame":1,"Missions_TakedownGold":678,"Missions_TakedownStructures":0,"Missions_TakedownWards":0,"Missions_TakedownsAfterExhausting":1,"Missions_TakedownsAfterTeleporting":2,"Missions_TakedownsBefore15Min":1,"Missions_TakedownsUnderTurret":0,"Missions_TakedownsWithHelpFromMonsters":0,"Missions_TimeSpentActivelyPlaying":23,"Missions_TotalGold":0,"Missions_TrueDamageToStructures":279,"Missions_TurretPlatesDestroyed":3,"Missions_TwoChampsKilledWithSameAbility":0,"Missions_VoidMitesSummoned":0,"PlayerScore0":0.0,"PlayerScore1":0.0,"PlayerScore10":0.0,"PlayerScore11":0.0,"PlayerScore2":0.0,"PlayerScore3":0.0,"PlayerScore4":0.0,"PlayerScore5":0.0,"PlayerScore6":0.0,"PlayerScore7":0.0,"PlayerScore8":0.0,"PlayerScore9":0.0,"SeasonalMissions_TakedownAtakhan":0},"needVisionPings":0,"neutralMinionsKilled":0,"nexusKills":0,"nexusLost":1,"nexusTakedowns":0,"objectivesStolen":0,"objectivesStolenAssists":0,"onMyWayPings":5,"participantId":4,"pentaKills":0,"perks":{"statPerks":{"defense":5011,"flex":5008,"offense":5005},"styles":[{"description":"primaryStyle","selections":[{"perk":8008,"var1":210,"var2":210,"var3":0},{"perk":8009,"var1":954,"var2":0,"var3":0},{"perk":9105,"var1":19,"var2":40,"var3":0},{"perk":8017,"var1":724,"var2":0,"var3":0}],"style":8000},{"description":"subStyle","selections":[{"perk":8347,"var1":0,"var2":0,"var3":0},{"perk":8345,"var1":3,"var2":0,"var3":81}],"style":8300}]},"physicalDamageDealt":103797,"physicalDamageDealtToChampions":9065,"physicalDamageTaken":7761,"placement":0,"playerAugment1":0,"playerAugment2":0,"playerAugment3":0,"playerAugment4":0,"playerAugment5":0,"playerAugment6":0,"playerSubteamId":0,"profileIcon":29,"pushPings":0,"puuid":"d6bd841f-1ae8-5e3c-8434-813e0531dcf3","quadraKills":0,"retreatPings":1,"riotIdGameName":"WD BOOSHI","riotIdTagline":"eProd","role":"SUPPORT","sightWardsBoughtInGame":0,"spell1Casts":248,"spell1Id":1,"spell2Casts":35,"spell2Id":4,"spell3Casts":28,"spell4Casts":10,"subteamPlacement":0,"summoner1Casts":2,"summoner2Casts":2,"summonerId":3394942409688352,"summonerLevel":30,"summonerName":"","teamEarlySurrendered":false,"teamId":100,"teamPosition":"TOP","timeCCingOthers":3,"timePlayed":1432,"totalAllyJungleMinionsKilled":0,"totalDamageDealt":122841,"totalDamageDealtToChampions":14131,"totalDamageShieldedOnTeammates":0,"totalDamageTaken":10177,"totalEnemyJungleMinionsKilled":0,"totalHeal":1823,"totalHealsOnTeammates":0,"totalMinionsKilled":238,"totalTimeCCDealt":58,"totalTimeSpentDead":35,"totalUnitsHealed":1,"tripleKills":0,"trueDamageDealt":2750,"trueDamageDealtToChampions":478,"trueDamageTaken":534,"turretKills":0,"turretTakedowns":0,"turretsLost":7,"unrealKills":0,"visionClearedPings":0,"visionScore":8,"visionWardsBoughtInGame":0,"wardsKilled":0,"wardsPlaced":7,"win":false},{"PlayerScore0":0.0,"PlayerScore1":0.0,"PlayerScore10":0.0,"PlayerScore11":0.0,"PlayerScore2":0.0,"PlayerScore3":0.0,"PlayerScore4":0.0,"PlayerScore5":0.0,"PlayerScore6":0.0,"PlayerScore7":0.0,"PlayerScore8":0.0,"PlayerScore9":0.0,"allInPings":1,"assistMePings":7,"assists":6,"baronKills":0,"basicPings":0,"bountyLevel":0,"challenges":{"12AssistStreakCount":0.0,"HealFromMapSources":0.0,"InfernalScalePickup":0.0,"SWARM_DefeatAatrox":0.0,"SWARM_DefeatBriar":0.0,"SWARM_DefeatMiniBosses":0.0,"SWARM_EvolveWeapon":0.0,"SWARM_Have3Passives":0.0,"SWARM_KillEnemy":0.0,"SWARM_PickupGold":0.0,"SWARM_ReachLevel50":0.0,"SWARM_Survive15Min":0.0,"SWARM_WinWith5EvolvedWeapons":0.0,"abilityUses":75.0,"acesBefore15Minutes":0.0,"alliedJungleMonsterKills":0.0,"baronTakedowns":0.0,"blastConeOppositeOpponentCount":0.0,"bountyGold":0.0,"buffsStolen":0.0,"completeSupportQuestInTime":0.0,"controlWardTimeCoverageInRiverOrEnemyHalf":0.3795588922695944,"controlWardsPlaced":3.0,"damagePerMinute":241.7339831927411,"damageTakenOnTeamPercentage":0.1767166052095897,"dancedWithRiftHerald":0.0,"deathsByEnemyChamps":6.0,"dodgeSkillShotsSmallWindow":12.0,"doubleAces":0.0,"dragonTakedowns":0.0,"earlyLaningPhaseGoldExpAdvantage":0.0,"effectiveHealAndShielding":1918.759521484375,"elderDragonKillsWithOpposingSoul":0.0,"elderDragonMultikills":0.0,"enemyChampionImmobilizations":36.0,"enemyJungleMonsterKills":0.0,"epicMonsterKillsNearEnemyJungler":0.0,"epicMonsterKillsWithin30SecondsOfSpawn":0.0,"epicMonsterSteals":0.0,"epicMonsterStolenWithoutSmite":0.0,"firstTurretKilled":0.0,"fistBumpParticipation":0.0,"flawlessAces":0.0,"fullTeamTakedown":0.0,"gameLength":1432.588370054,"goldPerMinute":226.10166465484116,"hadOpenNexus":0.0,"highestWardKills":1.0,"immobilizeAndKillWithAlly":5.0,"initialBuffCount":0.0,"initialCrabCount":0.0,"jungleCsBefore10Minutes":0.0,"junglerKillsEarlyJungle":0.0,"junglerTakedownsNearDamagedEpicMonster":0.0,"kTurretsDestroyedBeforePlatesFall":0.0,"kda":1.0,"killAfterHiddenWithAlly":0.0,"killParticipation":0.6666666666666666,"killedChampTookFullTeamDamageSurvived":0.0,"killingSprees":0.0,"killsNearEnemyTurret":0.0,"killsOnLanersEarlyJungleAsJungler":0.0,"killsOnRecentlyHealedByAramPack":0.0,"killsUnderOwnTurret":0.0,"killsWithHelpFromEpicMonster":0.0,"knockEnemyIntoTeamAndKill":0.0,"landSkillShotsEarlyGame":2.0,"laneMinionsFirst10Minutes":19.0,"laningPhaseGoldExpAdvantage":0.0,"legendaryCount":0.0,"legendaryItemUsed":[3869.0,3190.0],"lostAnInhibitor":0.0,"maxCsAdvantageOnLaneOpponent":11.0,"maxKillDeficit":0.0,"maxLevelLeadLaneOpponent":1.0,"mejaisFullStackInTime":0.0,"moreEnemyJungleThanOpponent":0.0,"multiKillOneSpell":0.0,"multiTurretRiftHeraldCount":0.0,"multikills":0.0,"multikillsAfterAggressiveFlash":0.0,"outerTurretExecutesBefore10Minutes":0.0,"outnumberedKills":0.0,"outnumberedNexusKill":0.0,"perfectDragonSoulsTaken":0.0,"perfectGame":0.0,"pickKillWithAlly":6.0,"poroExplosions":0.0,"quickCleanse":0.0,"quickFirstTurret":0.0,"quickSoloKills":0.0,"riftHeraldTakedowns":0.0,"saveAllyFromDeath":0.0,"scuttleCrabKills":0.0,"skillshotsDodged":93.0,"skillshotsHit":15.0,"snowballsHit":0.0,"soloBaronKills":0.0,"soloKills":0.0,"stealthWardsPlaced":37.0,"survivedSingleDigitHpCount":0.0,"survivedThreeImmobilizesInFight":0.0,"takedownOnFirstTurret":0.0,"takedowns":6.0,"takedownsAfterGainingLevelAdvantage":0.0,"takedownsBeforeJungleMinionSpawn":0.0,"takedownsFirstXMinutes":2.0,"takedownsInAlcove":0.0,"takedownsInEnemyFountain":0.0,"teamBaronKills":0.0,"teamDamagePercentage":0.07850179844371302,"teamElderDragonKills":0.0,"teamRiftHeraldKills":0.0,"tookLargeDamageSurvived":0.0,"turretPlatesTaken":0.0,"turretTakedowns":0.0,"turretsTakenWithRiftHerald":0.0,"twentyMinionsIn3SecondsCount":0.0,"twoWardsOneSweeperCount":1.0,"unseenRecalls":0.0,"visionScoreAdvantageLaneOpponent":-0.11594825983047485,"visionScorePerMinute":2.803450755596279,"voidMonsterKill":0.0,"wardTakedowns":7.0,"wardTakedownsBefore20M":6.0,"wardsGuarded":0.0},"champExperience":6302,"champLevel":10,"championId":89,"championName":"Leona","championTransform":0,"commandPings":14,"consumablesPurchased":6,"damageDealtToBuildings":0,"damageDealtToObjectives":0,"damageDealtToTurrets":0,"damageSelfMitigated":17660,"dangerPings":0,"deaths":6,"detectorWardsPlaced":3,"doubleKills":0,"dragonKills":0,"eligibleForProgression":false,"enemyMissingPings":2,"enemyVisionPings":0,"firstBloodAssist":false,"firstBloodKill":false,"firstTowerAssist":false,"firstTowerKill":false,"gameEndedInEarlySurrender":false,"gameEndedInSurrender":true,"getBackPings":2,"goldEarned":5398,"goldSpent":5000,"holdPings":0,"individualPosition":"AFK","inhibitorKills":0,"inhibitorTakedowns":0,"inhibitorsLost":0,"item0":3869,"item1":3013,"item2":3190,"item3":1029,"item4":2055,"item5":3067,"item6":3364,"itemsPurchased":22,"killingSprees":0,"kills":0,"lane":"BOTTOM","largestCriticalStrike":0,"largestKillingSpree":0,"largestMultiKill":0,"longestTimeSpentLiving":546,"magicDamageDealt":4754,"magicDamageDealtToChampions":3851,"magicDamageTaken":5057,"missions":{"ActMission_S1_A2_ArenaRoundsWon":0,"ActMission_S1_A2_BloodyPetalsCollected":22,"ActMission_S1_A2_FeatsOfStrength":0,"DemonsHand_MissionPointsA":43,"DemonsHand_MissionPointsB":65,"DemonsHand_MissionPointsC":17,"DemonsHand_MissionPointsD":39,"DemonsHand_MissionPointsE":36,"DemonsHand_MissionPointsF":39,"Event_2025LR_StructuresEpicMonsters":0,"Event_S1_A2_Arena_BraveryChampions":0,"Event_S1_A2_Arena_NoxianChampions":0,"Event_S1_A2_Arena_ReviveAllies":0,"Event_S1_A2_Esports_TakedownEpicMonstersSingleGame":0,"Missions_CannonMinionsKilled":5,"Missions_ChampionTakedownsWhileGhosted":0,"Missions_ChampionTakedownsWithIgnite":2,"Missions_ChampionsHitWithAbilitiesEarlyGame":4,"Missions_ChampionsKilled":0,"Missions_CreepScore":31,"Missions_CreepScoreBy10Minutes":0,"Missions_Crepe_DamageDealtSpeedZone":0,"Missions_Crepe_SnowballLanded":0,"Missions_Crepe_TakedownsWithInhibBuff":0,"Missions_DamageToChampsWithItems":958,"Missions_DamageToStructures":0,"Missions_DestroyPlants":4,"Missions_DominationRune":0,"Missions_GoldFromStructuresDestroyed":100,"Missions_GoldFromTurretPlatesTaken":0,"Missions_GoldPerMinute":0,"Missions_HealingFromLevelObjects":0,"Missions_HexgatesUsed":0,"Missions_ImmobilizeChampions":35,"Missions_InspirationRune":0,"Missions_LegendaryItems":2,"Missions_MinionsKilled":24,"Missions_PeriodicDamage":958,"Missions_PlaceUsefulControlWards":2,"Missions_PlaceUsefulWards":37,"Missions_PorosFed":0,"Missions_PrecisionRune":0,"Missions_ResolveRune":1,"Missions_SnowballsHit":0,"Missions_SorceryRune":0,"Missions_TakedownBaronsElderDragons":0,"Missions_TakedownDragons":0,"Missions_TakedownEpicMonsters":0,"Missions_TakedownEpicMonstersSingleGame":0,"Missions_TakedownGold":569,"Missions_TakedownStructures":0,"Missions_TakedownWards":7,"Missions_TakedownsAfterExhausting":6,"Missions_TakedownsAfterTeleporting":1,"Missions_TakedownsBefore15Min":2,"Missions_TakedownsUnderTurret":0,"Missions_TakedownsWithHelpFromMonsters":0,"Missions_TimeSpentActivelyPlaying":23,"Missions_TotalGold":0,"Missions_TrueDamageToStructures":0,"Missions_TurretPlatesDestroyed":0,"Missions_TwoChampsKilledWithSameAbility":0,"Missions_VoidMitesSummoned":0,"PlayerScore0":0.0,"PlayerScore1":0.0,"PlayerScore10":0.0,"PlayerScore11":0.0,"PlayerScore2":0.0,"PlayerScore3":0.0,"PlayerScore4":0.0,"PlayerScore5":0.0,"PlayerScore6":0.0,"PlayerScore7":0.0,"PlayerScore8":0.0,"PlayerScore9":0.0,"SeasonalMissions_TakedownAtakhan":0},"needVisionPings":0,"neutralMinionsKilled":0,"nexusKills":0,"nexusLost":1,"nexusTakedowns":0,"objectivesStolen":0,"objectivesStolenAssists":0,"onMyWayPings":56,"participantId":5,"pentaKills":0,"perks":{"statPerks":{"defense":5011,"flex":5010,"offense":5007},"styles":[{"description":"primaryStyle","selections":[{"perk":8439,"var1":340,"var2":583,"var3":0},{"perk":8463,"var1":571,"var2":0,"var3":0},{"perk":8473,"var1":453,"var2":0,"var3":0},{"perk":8451,"var1":138,"var2":0,"var3":0}],"style":8400},{"description":"subStyle","selections":[{"perk":8345,"var1":3,"var2":0,"var3":106},{"perk":8347,"var1":0,"var2":0,"var3":0}],"style":8300}]},"physicalDamageDealt":3646,"physicalDamageDealtToChampions":962,"physicalDamageTaken":9805,"placement":0,"playerAugment1":0,"playerAugment2":0,"playerAugment3":0,"playerAugment4":0,"playerAugment5":0,"playerAugment6":0,"playerSubteamId":0,"profileIcon":29,"pushPings":0,"puuid":"655f6c44-d126-53cd-a5e7-5e32394c1834","quadraKills":0,"retreatPings":0,"riotIdGameName":"BKR Doss","riotIdTagline":"eProd","role":"SUPPORT","sightWardsBoughtInGame":0,"spell1Casts":31,"spell1Id":4,"spell2Casts":20,"spell2Id":14,"spell3Casts":14,"spell4Casts":10,"subteamPlacement":0,"summoner1Casts":4,"summoner2Casts":6,"summonerId":3372424902583648,"summonerLevel":30,"summonerName":"","teamEarlySurrendered":false,"teamId":100,"teamPosition":"JUNGLE","timeCCingOthers":30,"timePlayed":1432,"totalAllyJungleMinionsKilled":0,"totalDamageDealt":13366,"totalDamageDealtToChampions":5771,"totalDamageShieldedOnTeammates":1699,"totalDamageTaken":15697,"totalEnemyJungleMinionsKilled":0,"totalHeal":602,"totalHealsOnTeammates":219,"totalMinionsKilled":31,"totalTimeCCDealt":49,"totalTimeSpentDead":116,"totalUnitsHealed":5,"tripleKills":0,"trueDamageDealt":4966,"trueDamageDealtToChampions":958,"trueDamageTaken":833,"turretKills":0,"turretTakedowns":0,"turretsLost":7,"unrealKills":0,"visionClearedPings":0,"visionScore":66,"visionWardsBoughtInGame":4,"wardsKilled":7,"wardsPlaced":40,"win":false},{"PlayerScore0":0.0,"PlayerScore1":0.0,"PlayerScore10":0.0,"PlayerScore11":0.0,"PlayerScore2":0.0,"PlayerScore3":0.0,"PlayerScore4":0.0,"PlayerScore5":0.0,"PlayerScore6":0.0,"PlayerScore7":0.0,"PlayerScore8":0.0,"PlayerScore9":0.0,"allInPings":0,"assistMePings":2,"assists":10,"baronKills":0,"basicPings":0,"bountyLevel":4,"challenges":{"12AssistStreakCount":0.0,"HealFromMapSources":0.0,"InfernalScalePickup":0.0,"SWARM_DefeatAatrox":0.0,"SWARM_DefeatBriar":0.0,"SWARM_DefeatMiniBosses":0.0,"SWARM_EvolveWeapon":0.0,"SWARM_Have3Passives":0.0,"SWARM_KillEnemy":0.0,"SWARM_PickupGold":0.0,"SWARM_ReachLevel50":0.0,"SWARM_Survive15Min":0.0,"SWARM_WinWith5EvolvedWeapons":0.0,"abilityUses":108.0,"acesBefore15Minutes":0.0,"alliedJungleMonsterKills":0.0,"baronTakedowns":0.0,"blastConeOppositeOpponentCount":0.0,"bountyGold":0.0,"buffsStolen":0.0,"completeSupportQuestInTime":0.0,"controlWardTimeCoverageInRiverOrEnemyHalf":0.7146222502835272,"controlWardsPlaced":3.0,"damagePerMinute":624.1303050453683,"damageTakenOnTeamPercentage":0.22558210548041324,"dancedWithRiftHerald":0.0,"deathsByEnemyChamps":2.0,"dodgeSkillShotsSmallWindow":0.0,"doubleAces":0.0,"dragonTakedowns":0.0,"earlyLaningPhaseGoldExpAdvantage":0.0,"effectiveHealAndShielding":0.0,"elderDragonKillsWithOpposingSoul":0.0,"elderDragonMultikills":0.0,"enemyChampionImmobilizations":46.0,"enemyJungleMonsterKills":0.0,"epicMonsterKillsNearEnemyJungler":0.0,"epicMonsterKillsWithin30SecondsOfSpawn":0.0,"epicMonsterSteals":0.0,"epicMonsterStolenWithoutSmite":0.0,"firstTurretKilled":1.0,"firstTurretKilledTime":828.653186674,"fistBumpParticipation":0.0,"flawlessAces":1.0,"fullTeamTakedown":2.0,"gameLength":1432.588370054,"goldPerMinute":454.0108503309876,"hadOpenNexus":0.0,"immobilizeAndKillWithAlly":7.0,"initialBuffCount":0.0,"initialCrabCount":0.0,"jungleCsBefore10Minutes":0.0,"junglerTakedownsNearDamagedEpicMonster":0.0,"kTurretsDestroyedBeforePlatesFall":0.0,"kda":7.0,"killAfterHiddenWithAlly":0.0,"killParticipation":0.5,"killedChampTookFullTeamDamageSurvived":0.0,"killingSprees":1.0,"killsNearEnemyTurret":1.0,"killsOnRecentlyHealedByAramPack":0.0,"killsUnderOwnTurret":0.0,"killsWithHelpFromEpicMonster":0.0,"knockEnemyIntoTeamAndKill":4.0,"landSkillShotsEarlyGame":0.0,"laneMinionsFirst10Minutes":90.0,"laningPhaseGoldExpAdvantage":0.0,"legendaryCount":0.0,"legendaryItemUsed":[6631.0,3053.0],"lostAnInhibitor":0.0,"maxCsAdvantageOnLaneOpponent":46.0,"maxKillDeficit":0.0,"maxLevelLeadLaneOpponent":3.0,"mejaisFullStackInTime":0.0,"moreEnemyJungleThanOpponent":0.0,"multiKillOneSpell":0.0,"multiTurretRiftHeraldCount":0.0,"multikills":0.0,"multikillsAfterAggressiveFlash":0.0,"outerTurretExecutesBefore10Minutes":0.0,"outnumberedKills":1.0,"outnumberedNexusKill":0.0,"perfectDragonSoulsTaken":0.0,"perfectGame":0.0,"pickKillWithAlly":6.0,"poroExplosions":0.0,"quickCleanse":0.0,"quickFirstTurret":0.0,"quickSoloKills":0.0,"riftHeraldTakedowns":0.0,"saveAllyFromDeath":0.0,"scuttleCrabKills":0.0,"shortestTimeToAceFromFirstTakedown":10.170741601999907,"skillshotsDodged":15.0,"skillshotsHit":0.0,"snowballsHit":0.0,"soloBaronKills":0.0,"soloKills":0.0,"soloTurretsLategame":1.0,"stealthWardsPlaced":7.0,"survivedSingleDigitHpCount":0.0,"survivedThreeImmobilizesInFight":9.0,"takedownOnFirstTurret":0.0,"takedowns":14.0,"takedownsAfterGainingLevelAdvantage":0.0,"takedownsBeforeJungleMinionSpawn":0.0,"takedownsFirstXMinutes":2.0,"takedownsInAlcove":0.0,"takedownsInEnemyFountain":0.0,"teamBaronKills":0.0,"teamDamagePercentage":0.18842470117047416,"teamElderDragonKills":0.0,"teamRiftHeraldKills":1.0,"tookLargeDamageSurvived":0.0,"turretPlatesTaken":3.0,"turretTakedowns":3.0,"turretsTakenWithRiftHerald":5.0,"twentyMinionsIn3SecondsCount":0.0,"twoWardsOneSweeperCount":0.0,"unseenRecalls":0.0,"visionScoreAdvantageLaneOpponent":0.6665191650390625,"visionScorePerMinute":1.0503234824479235,"voidMonsterKill":0.0,"wardTakedowns":3.0,"wardTakedownsBefore20M":2.0,"wardsGuarded":0.0},"champExperience":14841,"champLevel":16,"championId":875,"championName":"Sett","championTransform":0,"commandPings":8,"consumablesPurchased":4,"damageDealtToBuildings":8878,"damageDealtToObjectives":8878,"damageDealtToTurrets":8878,"damageSelfMitigated":19569,"dangerPings":0,"deaths":2,"detectorWardsPlaced":3,"doubleKills":0,"dragonKills":0,"eligibleForProgression":false,"enemyMissingPings":4,"enemyVisionPings":0,"firstBloodAssist":false,"firstBloodKill":false,"firstTowerAssist":false,"firstTowerKill":false,"gameEndedInEarlySurrender":false,"gameEndedInSurrender":true,"getBackPings":7,"goldEarned":10840,"goldSpent":9375,"holdPings":0,"individualPosition":"AFK","inhibitorKills":0,"inhibitorTakedowns":0,"inhibitorsLost":0,"item0":1028,"item1":6631,"item2":1036,"item3":3111,"item4":3053,"item5":0,"item6":3364,"itemsPurchased":18,"killingSprees":1,"kills":4,"lane":"JUNGLE","largestCriticalStrike":0,"largestKillingSpree":3,"largestMultiKill":1,"longestTimeSpentLiving":635,"magicDamageDealt":0,"magicDamageDealtToChampions":0,"magicDamageTaken":10848,"missions":{"ActMission_S1_A2_ArenaRoundsWon":0,"ActMission_S1_A2_BloodyPetalsCollected":54,"ActMission_S1_A2_FeatsOfStrength":2,"DemonsHand_MissionPointsA":22,"DemonsHand_MissionPointsB":15,"DemonsHand_MissionPointsC":18,"DemonsHand_MissionPointsD":83,"DemonsHand_MissionPointsE":86,"DemonsHand_MissionPointsF":15,"Event_2025LR_StructuresEpicMonsters":3,"Event_S1_A2_Arena_BraveryChampions":0,"Event_S1_A2_Arena_NoxianChampions":0,"Event_S1_A2_Arena_ReviveAllies":0,"Event_S1_A2_Esports_TakedownEpicMonstersSingleGame":0,"Missions_CannonMinionsKilled":14,"Missions_ChampionTakedownsWhileGhosted":0,"Missions_ChampionTakedownsWithIgnite":0,"Missions_ChampionsHitWithAbilitiesEarlyGame":17,"Missions_ChampionsKilled":4,"Missions_CreepScore":201,"Missions_CreepScoreBy10Minutes":1,"Missions_Crepe_DamageDealtSpeedZone":0,"Missions_Crepe_SnowballLanded":0,"Missions_Crepe_TakedownsWithInhibBuff":0,"Missions_DamageToChampsWithItems":807,"Missions_DamageToStructures":8878,"Missions_DestroyPlants":14,"Missions_DominationRune":0,"Missions_GoldFromStructuresDestroyed":1068,"Missions_GoldFromTurretPlatesTaken":375,"Missions_GoldPerMinute":1,"Missions_HealingFromLevelObjects":0,"Missions_HexgatesUsed":0,"Missions_ImmobilizeChampions":34,"Missions_InspirationRune":0,"Missions_LegendaryItems":2,"Missions_MinionsKilled":194,"Missions_PeriodicDamage":62,"Missions_PlaceUsefulControlWards":2,"Missions_PlaceUsefulWards":9,"Missions_PorosFed":0,"Missions_PrecisionRune":1,"Missions_ResolveRune":0,"Missions_SnowballsHit":0,"Missions_SorceryRune":0,"Missions_TakedownBaronsElderDragons":0,"Missions_TakedownDragons":0,"Missions_TakedownEpicMonsters":0,"Missions_TakedownEpicMonstersSingleGame":0,"Missions_TakedownGold":1791,"Missions_TakedownStructures":3,"Missions_TakedownWards":3,"Missions_TakedownsAfterExhausting":10,"Missions_TakedownsAfterTeleporting":8,"Missions_TakedownsBefore15Min":2,"Missions_TakedownsUnderTurret":2,"Missions_TakedownsWithHelpFromMonsters":0,"Missions_TimeSpentActivelyPlaying":23,"Missions_TotalGold":0,"Missions_TrueDamageToStructures":2377,"Missions_TurretPlatesDestroyed":3,"Missions_TwoChampsKilledWithSameAbility":0,"Missions_VoidMitesSummoned":8,"PlayerScore0":0.0,"PlayerScore1":0.0,"PlayerScore10":0.0,"PlayerScore11":0.0,"PlayerScore2":0.0,"PlayerScore3":0.0,"PlayerScore4":0.0,"PlayerScore5":0.0,"PlayerScore6":0.0,"PlayerScore7":0.0,"PlayerScore8":0.0,"PlayerScore9":0.0,"SeasonalMissions_TakedownAtakhan":0},"needVisionPings":1,"neutralMinionsKilled":4,"nexusKills":0,"nexusLost":0,"nexusTakedowns":0,"objectivesStolen":0,"objectivesStolenAssists":0,"onMyWayPings":11,"participantId":6,"pentaKills":0,"perks":{"statPerks":{"defense":5001,"flex":5008,"offense":5005},"styles":[{"description":"primaryStyle","selections":[{"perk":8010,"var1":154,"var2":0,"var3":0},{"perk":9111,"var1":1451,"var2":280,"var3":0},{"perk":9104,"var1":16,"var2":50,"var3":0},{"perk":8299,"var1":345,"var2":0,"var3":0}],"style":8000},{"description":"subStyle","selections":[{"perk":8446,"var1":2559,"var2":0,"var3":0},{"perk":8444,"var1":1432,"var2":0,"var3":0}],"style":8400}]},"physicalDamageDealt":111015,"physicalDamageDealtToChampions":12390,"physicalDamageTaken":10405,"placement":0,"playerAugment1":0,"playerAugment2":0,"playerAugment3":0,"playerAugment4":0,"playerAugment5":0,"playerAugment6":0,"playerSubteamId":0,"profileIcon":29,"pushPings":0,"puuid":"fb22f9db-4f42-562c-a80c-6acdb3b59817","quadraKills":0,"retreatPings":0,"riotIdGameName":"M8 Empyros","riotIdTagline":"eProd","role":"NONE","sightWardsBoughtInGame":0,"spell1Casts":54,"spell1Id":4,"spell2Casts":18,"spell2Id":12,"spell3Casts":32,"spell4Casts":4,"subteamPlacement":0,"summoner1Casts":3,"summoner2Casts":2,"summonerId":3372423612359712,"summonerLevel":30,"summonerName":"","teamEarlySurrendered":false,"teamId":200,"teamPosition":"AFK","timeCCingOthers":24,"timePlayed":1432,"totalAllyJungleMinionsKilled":0,"totalDamageDealt":123855,"totalDamageDealtToChampions":14902,"totalDamageShieldedOnTeammates":0,"totalDamageTaken":21601,"totalEnemyJungleMinionsKilled":0,"totalHeal":3552,"totalHealsOnTeammates":0,"totalMinionsKilled":197,"totalTimeCCDealt":313,"totalTimeSpentDead":60,"totalUnitsHealed":1,"tripleKills":0,"trueDamageDealt":12839,"trueDamageDealtToChampions":2511,"trueDamageTaken":347,"turretKills":2,"turretTakedowns":3,"turretsLost":2,"unrealKills":0,"visionClearedPings":0,"visionScore":25,"visionWardsBoughtInGame":3,"wardsKilled":3,"wardsPlaced":10,"win":true},{"PlayerScore0":0.0,"PlayerScore1":0.0,"PlayerScore10":0.0,"PlayerScore11":0.0,"PlayerScore2":0.0,"PlayerScore3":0.0,"PlayerScore4":0.0,"PlayerScore5":0.0,"PlayerScore6":0.0,"PlayerScore7":0.0,"PlayerScore8":0.0,"PlayerScore9":0.0,"allInPings":3,"assistMePings":17,"assists":10,"baronKills":0,"basicPings":0,"bountyLevel":7,"challenges":{"12AssistStreakCount":0.0,"HealFromMapSources":152.0,"InfernalScalePickup":0.0,"SWARM_DefeatAatrox":0.0,"SWARM_DefeatBriar":0.0,"SWARM_DefeatMiniBosses":0.0,"SWARM_EvolveWeapon":0.0,"SWARM_Have3Passives":0.0,"SWARM_KillEnemy":0.0,"SWARM_PickupGold":0.0,"SWARM_ReachLevel50":0.0,"SWARM_Survive15Min":0.0,"SWARM_WinWith5EvolvedWeapons":0.0,"abilityUses":242.0,"acesBefore15Minutes":0.0,"alliedJungleMonsterKills":0.0,"baronTakedowns":0.0,"blastConeOppositeOpponentCount":0.0,"bountyGold":0.0,"buffsStolen":7.0,"completeSupportQuestInTime":0.0,"controlWardTimeCoverageInRiverOrEnemyHalf":0.7127575708125503,"controlWardsPlaced":5.0,"damagePerMinute":805.0643740263831,"damageTakenOnTeamPercentage":0.2718422706307774,"dancedWithRiftHerald":0.0,"deathsByEnemyChamps":3.0,"dodgeSkillShotsSmallWindow":0.0,"doubleAces":0.0,"dragonTakedowns":3.0,"earliestDragonTakedown":388.459940048,"earlyLaningPhaseGoldExpAdvantage":0.0,"effectiveHealAndShielding":0.0,"elderDragonKillsWithOpposingSoul":0.0,"elderDragonMultikills":0.0,"enemyChampionImmobilizations":12.0,"enemyJungleMonsterKills":0.0,"epicMonsterKillsNearEnemyJungler":0.0,"epicMonsterKillsWithin30SecondsOfSpawn":0.0,"epicMonsterSteals":0.0,"epicMonsterStolenWithoutSmite":0.0,"firstTurretKilled":1.0,"firstTurretKilledTime":828.653186674,"fistBumpParticipation":0.0,"flawlessAces":1.0,"fullTeamTakedown":2.0,"gameLength":1432.588370054,"getTakedownsInAllLanesEarlyJungleAsLaner":0.0,"goldPerMinute":432.11740380397316,"hadOpenNexus":0.0,"immobilizeAndKillWithAlly":7.0,"initialBuffCount":2.0,"initialCrabCount":1.0,"jungleCsBefore10Minutes":68.00000005960464,"junglerTakedownsNearDamagedEpicMonster":0.0,"kTurretsDestroyedBeforePlatesFall":0.0,"kda":5.666666666666667,"killAfterHiddenWithAlly":0.0,"killParticipation":0.6071428571428571,"killedChampTookFullTeamDamageSurvived":0.0,"killingSprees":1.0,"killsNearEnemyTurret":2.0,"killsOnOtherLanesEarlyJungleAsLaner":0.0,"killsOnRecentlyHealedByAramPack":0.0,"killsUnderOwnTurret":0.0,"killsWithHelpFromEpicMonster":0.0,"knockEnemyIntoTeamAndKill":7.0,"landSkillShotsEarlyGame":8.0,"laneMinionsFirst10Minutes":4.0,"laningPhaseGoldExpAdvantage":1.0,"legendaryCount":0.0,"legendaryItemUsed":[6653.0,3041.0,4633.0],"lostAnInhibitor":0.0,"maxCsAdvantageOnLaneOpponent":9.800000071525574,"maxKillDeficit":0.0,"maxLevelLeadLaneOpponent":1.0,"mejaisFullStackInTime":0.0,"moreEnemyJungleThanOpponent":0.0,"multiKillOneSpell":0.0,"multiTurretRiftHeraldCount":0.0,"multikills":1.0,"multikillsAfterAggressiveFlash":0.0,"outerTurretExecutesBefore10Minutes":0.0,"outnumberedKills":3.0,"outnumberedNexusKill":0.0,"perfectDragonSoulsTaken":0.0,"perfectGame":0.0,"pickKillWithAlly":8.0,"poroExplosions":0.0,"quickCleanse":0.0,"quickFirstTurret":0.0,"quickSoloKills":0.0,"riftHeraldTakedowns":1.0,"saveAllyFromDeath":0.0,"scuttleCrabKills":2.0,"shortestTimeToAceFromFirstTakedown":10.170741601999907,"skillshotsDodged":19.0,"skillshotsHit":26.0,"snowballsHit":0.0,"soloBaronKills":0.0,"soloKills":2.0,"stealthWardsPlaced":2.0,"survivedSingleDigitHpCount":0.0,"survivedThreeImmobilizesInFight":1.0,"takedownOnFirstTurret":0.0,"takedowns":17.0,"takedownsAfterGainingLevelAdvantage":0.0,"takedownsBeforeJungleMinionSpawn":0.0,"takedownsFirstXMinutes":9.0,"takedownsInAlcove":0.0,"takedownsInEnemyFountain":0.0,"teamBaronKills":0.0,"teamDamagePercentage":0.2430486276225433,"teamElderDragonKills":0.0,"teamRiftHeraldKills":1.0,"tookLargeDamageSurvived":0.0,"turretPlatesTaken":0.0,"turretTakedowns":0.0,"turretsTakenWithRiftHerald":5.0,"twentyMinionsIn3SecondsCount":0.0,"twoWardsOneSweeperCount":0.0,"unseenRecalls":0.0,"visionScoreAdvantageLaneOpponent":1.1052296161651611,"visionScorePerMinute":1.305905294678826,"voidMonsterKill":4.0,"wardTakedowns":5.0,"wardTakedownsBefore20M":3.0,"wardsGuarded":1.0},"champExperience":12832,"champLevel":14,"championId":131,"championName":"Diana","championTransform":0,"commandPings":6,"consumablesPurchased":5,"damageDealtToBuildings":0,"damageDealtToObjectives":49095,"damageDealtToTurrets":0,"damageSelfMitigated":34655,"dangerPings":0,"deaths":3,"detectorWardsPlaced":5,"doubleKills":1,"dragonKills":3,"eligibleForProgression":false,"enemyMissingPings":7,"enemyVisionPings":18,"firstBloodAssist":false,"firstBloodKill":true,"firstTowerAssist":false,"firstTowerKill":false,"gameEndedInEarlySurrender":false,"gameEndedInSurrender":true,"getBackPings":0,"goldEarned":10317,"goldSpent":8625,"holdPings":0,"individualPosition":"AFK","inhibitorKills":0,"inhibitorTakedowns":0,"inhibitorsLost":0,"item0":3111,"item1":6653,"item2":0,"item3":4633,"item4":1082,"item5":1028,"item6":3364,"itemsPurchased":18,"killingSprees":2,"kills":7,"lane":"JUNGLE","largestCriticalStrike":0,"largestKillingSpree":4,"largestMultiKill":2,"longestTimeSpentLiving":1001,"magicDamageDealt":144200,"magicDamageDealtToChampions":15902,"magicDamageTaken":6670,"missions":{"ActMission_S1_A2_ArenaRoundsWon":0,"ActMission_S1_A2_BloodyPetalsCollected":54,"ActMission_S1_A2_FeatsOfStrength":2,"DemonsHand_MissionPointsA":103,"DemonsHand_MissionPointsB":15,"DemonsHand_MissionPointsC":43,"DemonsHand_MissionPointsD":14,"DemonsHand_MissionPointsE":28,"DemonsHand_MissionPointsF":36,"Event_2025LR_StructuresEpicMonsters":8,"Event_S1_A2_Arena_BraveryChampions":0,"Event_S1_A2_Arena_NoxianChampions":0,"Event_S1_A2_Arena_ReviveAllies":0,"Event_S1_A2_Esports_TakedownEpicMonstersSingleGame":0,"Missions_CannonMinionsKilled":1,"Missions_ChampionTakedownsWhileGhosted":0,"Missions_ChampionTakedownsWithIgnite":0,"Missions_ChampionsHitWithAbilitiesEarlyGame":40,"Missions_ChampionsKilled":7,"Missions_CreepScore":176,"Missions_CreepScoreBy10Minutes":1,"Missions_Crepe_DamageDealtSpeedZone":0,"Missions_Crepe_SnowballLanded":0,"Missions_Crepe_TakedownsWithInhibBuff":0,"Missions_DamageToChampsWithItems":2328,"Missions_DamageToStructures":0,"Missions_DestroyPlants":27,"Missions_DominationRune":0,"Missions_GoldFromStructuresDestroyed":250,"Missions_GoldFromTurretPlatesTaken":0,"Missions_GoldPerMinute":1,"Missions_HealingFromLevelObjects":152,"Missions_HexgatesUsed":0,"Missions_ImmobilizeChampions":12,"Missions_InspirationRune":0,"Missions_LegendaryItems":2,"Missions_MinionsKilled":14,"Missions_PeriodicDamage":3027,"Missions_PlaceUsefulControlWards":5,"Missions_PlaceUsefulWards":7,"Missions_PorosFed":0,"Missions_PrecisionRune":1,"Missions_ResolveRune":0,"Missions_SnowballsHit":0,"Missions_SorceryRune":0,"Missions_TakedownBaronsElderDragons":0,"Missions_TakedownDragons":3,"Missions_TakedownEpicMonsters":7,"Missions_TakedownEpicMonstersSingleGame":7,"Missions_TakedownGold":2536,"Missions_TakedownStructures":0,"Missions_TakedownWards":5,"Missions_TakedownsAfterExhausting":10,"Missions_TakedownsAfterTeleporting":8,"Missions_TakedownsBefore15Min":9,"Missions_TakedownsUnderTurret":1,"Missions_TakedownsWithHelpFromMonsters":0,"Missions_TimeSpentActivelyPlaying":23,"Missions_TotalGold":0,"Missions_TrueDamageToStructures":0,"Missions_TurretPlatesDestroyed":0,"Missions_TwoChampsKilledWithSameAbility":0,"Missions_VoidMitesSummoned":0,"PlayerScore0":0.0,"PlayerScore1":0.0,"PlayerScore10":0.0,"PlayerScore11":0.0,"PlayerScore2":0.0,"PlayerScore3":0.0,"PlayerScore4":0.0,"PlayerScore5":0.0,"PlayerScore6":0.0,"PlayerScore7":0.0,"PlayerScore8":0.0,"PlayerScore9":0.0,"SeasonalMissions_TakedownAtakhan":1},"needVisionPings":0,"neutralMinionsKilled":157,"nexusKills":0,"nexusLost":0,"nexusTakedowns":0,"objectivesStolen":0,"objectivesStolenAssists":0,"onMyWayPings":90,"participantId":7,"pentaKills":0,"perks":{"statPerks":{"defense":5001,"flex":5008,"offense":5008},"styles":[{"description":"primaryStyle","selections":[{"perk":8010,"var1":823,"var2":0,"var3":0},{"perk":9111,"var1":1232,"var2":340,"var3":0},{"perk":9104,"var1":9,"var2":40,"var3":0},{"perk":8299,"var1":548,"var2":0,"var3":0}],"style":8000},{"description":"subStyle","selections":[{"perk":8304,"var1":9,"var2":0,"var3":0},{"perk":8347,"var1":0,"var2":0,"var3":0}],"style":8300}]},"physicalDamageDealt":30935,"physicalDamageDealtToChampions":2492,"physicalDamageTaken":18072,"placement":0,"playerAugment1":0,"playerAugment2":0,"playerAugment3":0,"playerAugment4":0,"playerAugment5":0,"playerAugment6":0,"playerSubteamId":0,"profileIcon":29,"pushPings":0,"puuid":"2d1bb646-cc94-5e41-8811-b53cf6e1379b","quadraKills":0,"retreatPings":10,"riotIdGameName":"M8 Zicssi","riotIdTagline":"eProd","role":"NONE","sightWardsBoughtInGame":0,"spell1Casts":105,"spell1Id":11,"spell2Casts":54,"spell2Id":4,"spell3Casts":76,"spell4Casts":7,"subteamPlacement":0,"summoner1Casts":14,"summoner2Casts":4,"summonerId":3373192200619040,"summonerLevel":30,"summonerName":"","teamEarlySurrendered":false,"teamId":200,"teamPosition":"BOTTOM","timeCCingOthers":14,"timePlayed":1432,"totalAllyJungleMinionsKilled":0,"totalDamageDealt":245581,"totalDamageDealtToChampions":19222,"totalDamageShieldedOnTeammates":0,"totalDamageTaken":26030,"totalEnemyJungleMinionsKilled":0,"totalHeal":11875,"totalHealsOnTeammates":0,"totalMinionsKilled":19,"totalTimeCCDealt":265,"totalTimeSpentDead":116,"totalUnitsHealed":1,"tripleKills":0,"trueDamageDealt":70445,"trueDamageDealtToChampions":826,"trueDamageTaken":1288,"turretKills":0,"turretTakedowns":0,"turretsLost":2,"unrealKills":0,"visionClearedPings":0,"visionScore":31,"visionWardsBoughtInGame":5,"wardsKilled":5,"wardsPlaced":7,"win":true},{"PlayerScore0":0.0,"PlayerScore1":0.0,"PlayerScore10":0.0,"PlayerScore11":0.0,"PlayerScore2":0.0,"PlayerScore3":0.0,"PlayerScore4":0.0,"PlayerScore5":0.0,"PlayerScore6":0.0,"PlayerScore7":0.0,"PlayerScore8":0.0,"PlayerScore9":0.0,"allInPings":0,"assistMePings":5,"assists":6,"baronKills":0,"basicPings":0,"bountyLevel":7,"challenges":{"12AssistStreakCount":0.0,"HealFromMapSources":294.0,"InfernalScalePickup":0.0,"SWARM_DefeatAatrox":0.0,"SWARM_DefeatBriar":0.0,"SWARM_DefeatMiniBosses":0.0,"SWARM_EvolveWeapon":0.0,"SWARM_Have3Passives":0.0,"SWARM_KillEnemy":0.0,"SWARM_PickupGold":0.0,"SWARM_ReachLevel50":0.0,"SWARM_Survive15Min":0.0,"SWARM_WinWith5EvolvedWeapons":0.0,"abilityUses":339.0,"acesBefore15Minutes":0.0,"alliedJungleMonsterKills":0.0,"baronTakedowns":0.0,"blastConeOppositeOpponentCount":0.0,"bountyGold":0.0,"buffsStolen":0.0,"completeSupportQuestInTime":0.0,"controlWardTimeCoverageInRiverOrEnemyHalf":0.7348308536179999,"controlWardsPlaced":3.0,"damagePerMinute":767.5643968012608,"damageTakenOnTeamPercentage":0.21325205122378518,"dancedWithRiftHerald":0.0,"deathsByEnemyChamps":0.0,"dodgeSkillShotsSmallWindow":0.0,"doubleAces":0.0,"dragonTakedowns":0.0,"earlyLaningPhaseGoldExpAdvantage":0.0,"effectiveHealAndShielding":0.0,"elderDragonKillsWithOpposingSoul":0.0,"elderDragonMultikills":0.0,"enemyChampionImmobilizations":26.0,"enemyJungleMonsterKills":0.0,"epicMonsterKillsNearEnemyJungler":0.0,"epicMonsterKillsWithin30SecondsOfSpawn":0.0,"epicMonsterSteals":0.0,"epicMonsterStolenWithoutSmite":0.0,"firstTurretKilled":1.0,"firstTurretKilledTime":828.653186674,"fistBumpParticipation":0.0,"flawlessAces":1.0,"fullTeamTakedown":2.0,"gameLength":1432.588370054,"getTakedownsInAllLanesEarlyJungleAsLaner":0.0,"goldPerMinute":521.3194435236471,"hadOpenNexus":0.0,"immobilizeAndKillWithAlly":3.0,"initialBuffCount":0.0,"initialCrabCount":0.0,"jungleCsBefore10Minutes":0.0,"junglerTakedownsNearDamagedEpicMonster":0.0,"kTurretsDestroyedBeforePlatesFall":1.0,"kda":13.0,"killAfterHiddenWithAlly":0.0,"killParticipation":0.4642857142857143,"killedChampTookFullTeamDamageSurvived":0.0,"killingSprees":1.0,"killsNearEnemyTurret":0.0,"killsOnOtherLanesEarlyJungleAsLaner":2.0,"killsOnRecentlyHealedByAramPack":0.0,"killsUnderOwnTurret":0.0,"killsWithHelpFromEpicMonster":0.0,"knockEnemyIntoTeamAndKill":0.0,"landSkillShotsEarlyGame":3.0,"laneMinionsFirst10Minutes":74.0,"laningPhaseGoldExpAdvantage":0.0,"legendaryCount":0.0,"legendaryItemUsed":[3032.0,3031.0],"lostAnInhibitor":0.0,"maxCsAdvantageOnLaneOpponent":14.0,"maxKillDeficit":0.0,"maxLevelLeadLaneOpponent":2.0,"mejaisFullStackInTime":0.0,"moreEnemyJungleThanOpponent":0.0,"multiKillOneSpell":0.0,"multiTurretRiftHeraldCount":0.0,"multikills":1.0,"multikillsAfterAggressiveFlash":0.0,"outerTurretExecutesBefore10Minutes":0.0,"outnumberedKills":2.0,"outnumberedNexusKill":0.0,"perfectDragonSoulsTaken":0.0,"perfectGame":0.0,"pickKillWithAlly":5.0,"poroExplosions":0.0,"quickCleanse":0.0,"quickFirstTurret":0.0,"quickSoloKills":0.0,"riftHeraldTakedowns":1.0,"saveAllyFromDeath":0.0,"scuttleCrabKills":0.0,"skillshotsDodged":15.0,"skillshotsHit":10.0,"snowballsHit":0.0,"soloBaronKills":0.0,"soloKills":1.0,"soloTurretsLategame":1.0,"stealthWardsPlaced":4.0,"survivedSingleDigitHpCount":0.0,"survivedThreeImmobilizesInFight":6.0,"takedownOnFirstTurret":1.0,"takedowns":13.0,"takedownsAfterGainingLevelAdvantage":0.0,"takedownsBeforeJungleMinionSpawn":0.0,"takedownsFirstXMinutes":3.0,"takedownsInAlcove":0.0,"takedownsInEnemyFountain":0.0,"teamBaronKills":0.0,"teamDamagePercentage":0.23172739879352558,"teamElderDragonKills":0.0,"teamRiftHeraldKills":1.0,"tookLargeDamageSurvived":0.0,"turretPlatesTaken":3.0,"turretTakedowns":5.0,"turretsTakenWithRiftHerald":5.0,"twentyMinionsIn3SecondsCount":0.0,"twoWardsOneSweeperCount":0.0,"unseenRecalls":0.0,"visionScoreAdvantageLaneOpponent":1.06795072555542,"visionScorePerMinute":0.7448817396138044,"voidMonsterKill":1.0,"wardTakedowns":3.0,"wardTakedownsBefore20M":2.0,"wardsGuarded":1.0},"champExperience":15016,"champLevel":16,"championId":777,"championName":"Yone","championTransform":0,"commandPings":25,"consumablesPurchased":4,"damageDealtToBuildings":8877,"damageDealtToObjectives":19185,"damageDealtToTurrets":8877,"damageSelfMitigated":20265,"dangerPings":0,"deaths":0,"detectorWardsPlaced":3,"doubleKills":1,"dragonKills":0,"eligibleForProgression":false,"enemyMissingPings":9,"enemyVisionPings":6,"firstBloodAssist":false,"firstBloodKill":false,"firstTowerAssist":false,"firstTowerKill":true,"gameEndedInEarlySurrender":false,"gameEndedInSurrender":true,"getBackPings":4,"goldEarned":12447,"goldSpent":10655,"holdPings":0,"individualPosition":"AFK","inhibitorKills":0,"inhibitorTakedowns":0,"inhibitorsLost":0,"item0":1038,"item1":3032,"item2":1053,"item3":3006,"item4":3031,"item5":1054,"item6":3364,"itemsPurchased":19,"killingSprees":1,"kills":7,"lane":"JUNGLE","largestCriticalStrike":719,"largestKillingSpree":7,"largestMultiKill":2,"longestTimeSpentLiving":0,"magicDamageDealt":20689,"magicDamageDealtToChampions":3489,"magicDamageTaken":7390,"missions":{"ActMission_S1_A2_ArenaRoundsWon":0,"ActMission_S1_A2_BloodyPetalsCollected":54,"ActMission_S1_A2_FeatsOfStrength":2,"DemonsHand_MissionPointsA":20,"DemonsHand_MissionPointsB":18,"DemonsHand_MissionPointsC":72,"DemonsHand_MissionPointsD":64,"DemonsHand_MissionPointsE":47,"DemonsHand_MissionPointsF":18,"Event_2025LR_StructuresEpicMonsters":6,"Event_S1_A2_Arena_BraveryChampions":0,"Event_S1_A2_Arena_NoxianChampions":0,"Event_S1_A2_Arena_ReviveAllies":0,"Event_S1_A2_Esports_TakedownEpicMonstersSingleGame":0,"Missions_CannonMinionsKilled":14,"Missions_ChampionTakedownsWhileGhosted":0,"Missions_ChampionTakedownsWithIgnite":0,"Missions_ChampionsHitWithAbilitiesEarlyGame":17,"Missions_ChampionsKilled":7,"Missions_CreepScore":205,"Missions_CreepScoreBy10Minutes":1,"Missions_Crepe_DamageDealtSpeedZone":0,"Missions_Crepe_SnowballLanded":0,"Missions_Crepe_TakedownsWithInhibBuff":0,"Missions_DamageToChampsWithItems":188,"Missions_DamageToStructures":8877,"Missions_DestroyPlants":32,"Missions_DominationRune":0,"Missions_GoldFromStructuresDestroyed":2293,"Missions_GoldFromTurretPlatesTaken":250,"Missions_GoldPerMinute":1,"Missions_HealingFromLevelObjects":294,"Missions_HexgatesUsed":0,"Missions_ImmobilizeChampions":20,"Missions_InspirationRune":0,"Missions_LegendaryItems":2,"Missions_MinionsKilled":202,"Missions_PeriodicDamage":110,"Missions_PlaceUsefulControlWards":3,"Missions_PlaceUsefulWards":7,"Missions_PorosFed":0,"Missions_PrecisionRune":1,"Missions_ResolveRune":0,"Missions_SnowballsHit":0,"Missions_SorceryRune":0,"Missions_TakedownBaronsElderDragons":0,"Missions_TakedownDragons":0,"Missions_TakedownEpicMonsters":3,"Missions_TakedownEpicMonstersSingleGame":3,"Missions_TakedownGold":2329,"Missions_TakedownStructures":4,"Missions_TakedownWards":3,"Missions_TakedownsAfterExhausting":6,"Missions_TakedownsAfterTeleporting":5,"Missions_TakedownsBefore15Min":3,"Missions_TakedownsUnderTurret":0,"Missions_TakedownsWithHelpFromMonsters":0,"Missions_TimeSpentActivelyPlaying":23,"Missions_TotalGold":0,"Missions_TrueDamageToStructures":857,"Missions_TurretPlatesDestroyed":1,"Missions_TwoChampsKilledWithSameAbility":0,"Missions_VoidMitesSummoned":0,"PlayerScore0":0.0,"PlayerScore1":0.0,"PlayerScore10":0.0,"PlayerScore11":0.0,"PlayerScore2":0.0,"PlayerScore3":0.0,"PlayerScore4":0.0,"PlayerScore5":0.0,"PlayerScore6":0.0,"PlayerScore7":0.0,"PlayerScore8":0.0,"PlayerScore9":0.0,"SeasonalMissions_TakedownAtakhan":1},"needVisionPings":0,"neutralMinionsKilled":0,"nexusKills":0,"nexusLost":0,"nexusTakedowns":0,"objectivesStolen":0,"objectivesStolenAssists":0,"onMyWayPings":17,"participantId":8,"pentaKills":0,"perks":{"statPerks":{"defense":5011,"flex":5008,"offense":5005},"styles":[{"description":"primaryStyle","selections":[{"perk":8021,"var1":2204,"var2":0,"var3":0},{"perk":9101,"var1":1132,"var2":0,"var3":0},{"perk":9104,"var1":16,"var2":40,"var3":0},{"perk":8017,"var1":802,"var2":0,"var3":0}],"style":8000},{"description":"subStyle","selections":[{"perk":8451,"var1":189,"var2":0,"var3":0},{"perk":8444,"var1":1322,"var2":0,"var3":0}],"style":8400}]},"physicalDamageDealt":130769,"physicalDamageDealtToChampions":12135,"physicalDamageTaken":12408,"placement":0,"playerAugment1":0,"playerAugment2":0,"playerAugment3":0,"playerAugment4":0,"playerAugment5":0,"playerAugment6":0,"playerSubteamId":0,"profileIcon":29,"pushPings":0,"puuid":"441ab9d1-1ce9-5225-9426-94108f65f662","quadraKills":0,"retreatPings":4,"riotIdGameName":"M8 Eika","riotIdTagline":"eProd","role":"NONE","sightWardsBoughtInGame":0,"spell1Casts":207,"spell1Id":4,"spell2Casts":59,"spell2Id":12,"spell3Casts":68,"spell4Casts":5,"subteamPlacement":0,"summoner1Casts":3,"summoner2Casts":3,"summonerId":3372419577259360,"summonerLevel":30,"summonerName":"","teamEarlySurrendered":false,"teamId":200,"teamPosition":"TOP","timeCCingOthers":16,"timePlayed":1432,"totalAllyJungleMinionsKilled":0,"totalDamageDealt":156969,"totalDamageDealtToChampions":18326,"totalDamageShieldedOnTeammates":0,"totalDamageTaken":20420,"totalEnemyJungleMinionsKilled":0,"totalHeal":9554,"totalHealsOnTeammates":0,"totalMinionsKilled":205,"totalTimeCCDealt":120,"totalTimeSpentDead":0,"totalUnitsHealed":1,"tripleKills":0,"trueDamageDealt":5510,"trueDamageDealtToChampions":2702,"trueDamageTaken":621,"turretKills":5,"turretTakedowns":5,"turretsLost":2,"unrealKills":0,"visionClearedPings":0,"visionScore":17,"visionWardsBoughtInGame":3,"wardsKilled":3,"wardsPlaced":7,"win":true},{"PlayerScore0":0.0,"PlayerScore1":0.0,"PlayerScore10":0.0,"PlayerScore11":0.0,"PlayerScore2":0.0,"PlayerScore3":0.0,"PlayerScore4":0.0,"PlayerScore5":0.0,"PlayerScore6":0.0,"PlayerScore7":0.0,"PlayerScore8":0.0,"PlayerScore9":0.0,"allInPings":0,"assistMePings":2,"assists":5,"baronKills":0,"basicPings":0,"bountyLevel":9,"challenges":{"12AssistStreakCount":0.0,"HealFromMapSources":0.0,"InfernalScalePickup":0.0,"SWARM_DefeatAatrox":0.0,"SWARM_DefeatBriar":0.0,"SWARM_DefeatMiniBosses":0.0,"SWARM_EvolveWeapon":0.0,"SWARM_Have3Passives":0.0,"SWARM_KillEnemy":0.0,"SWARM_PickupGold":0.0,"SWARM_ReachLevel50":0.0,"SWARM_Survive15Min":0.0,"SWARM_WinWith5EvolvedWeapons":0.0,"abilityUses":142.0,"acesBefore15Minutes":0.0,"alliedJungleMonsterKills":0.0,"baronTakedowns":0.0,"blastConeOppositeOpponentCount":0.0,"bountyGold":0.0,"buffsStolen":0.0,"completeSupportQuestInTime":0.0,"controlWardTimeCoverageInRiverOrEnemyHalf":0.3814053932054496,"controlWardsPlaced":1.0,"damagePerMinute":938.6542186830769,"damageTakenOnTeamPercentage":0.10677887727131519,"dancedWithRiftHerald":0.0,"deathsByEnemyChamps":0.0,"dodgeSkillShotsSmallWindow":0.0,"doubleAces":0.0,"dragonTakedowns":1.0,"earliestDragonTakedown":773.6126709710001,"earlyLaningPhaseGoldExpAdvantage":0.0,"effectiveHealAndShielding":0.0,"elderDragonKillsWithOpposingSoul":0.0,"elderDragonMultikills":0.0,"enemyChampionImmobilizations":16.0,"enemyJungleMonsterKills":0.0,"epicMonsterKillsNearEnemyJungler":0.0,"epicMonsterKillsWithin30SecondsOfSpawn":0.0,"epicMonsterSteals":0.0,"epicMonsterStolenWithoutSmite":0.0,"fastestLegendary":1301.691768743,"firstTurretKilled":1.0,"firstTurretKilledTime":828.653186674,"fistBumpParticipation":0.0,"flawlessAces":1.0,"fullTeamTakedown":2.0,"gameLength":1432.588370054,"getTakedownsInAllLanesEarlyJungleAsLaner":0.0,"goldPerMinute":512.268872921143,"hadOpenNexus":0.0,"highestChampionDamage":1.0,"immobilizeAndKillWithAlly":4.0,"initialBuffCount":0.0,"initialCrabCount":0.0,"jungleCsBefore10Minutes":0.0,"junglerTakedownsNearDamagedEpicMonster":0.0,"kTurretsDestroyedBeforePlatesFall":1.0,"kda":14.0,"killAfterHiddenWithAlly":2.0,"killParticipation":0.5,"killedChampTookFullTeamDamageSurvived":0.0,"killingSprees":1.0,"killsNearEnemyTurret":4.0,"killsOnOtherLanesEarlyJungleAsLaner":0.0,"killsOnRecentlyHealedByAramPack":0.0,"killsUnderOwnTurret":1.0,"killsWithHelpFromEpicMonster":0.0,"knockEnemyIntoTeamAndKill":0.0,"landSkillShotsEarlyGame":8.0,"laneMinionsFirst10Minutes":83.0,"laningPhaseGoldExpAdvantage":1.0,"legendaryCount":1.0,"legendaryItemUsed":[3142.0,3004.0,3042.0,6694.0],"lostAnInhibitor":0.0,"maxCsAdvantageOnLaneOpponent":59.44999983906746,"maxKillDeficit":0.0,"maxLevelLeadLaneOpponent":3.0,"mejaisFullStackInTime":0.0,"moreEnemyJungleThanOpponent":0.0,"multiKillOneSpell":0.0,"multiTurretRiftHeraldCount":0.0,"multikills":0.0,"multikillsAfterAggressiveFlash":0.0,"outerTurretExecutesBefore10Minutes":0.0,"outnumberedKills":0.0,"outnumberedNexusKill":0.0,"perfectDragonSoulsTaken":0.0,"perfectGame":0.0,"pickKillWithAlly":10.0,"poroExplosions":0.0,"quickCleanse":1.0,"quickFirstTurret":0.0,"quickSoloKills":0.0,"riftHeraldTakedowns":1.0,"saveAllyFromDeath":0.0,"scuttleCrabKills":1.0,"shortestTimeToAceFromFirstTakedown":10.170741601999907,"skillshotsDodged":20.0,"skillshotsHit":59.0,"snowballsHit":0.0,"soloBaronKills":0.0,"soloKills":0.0,"stealthWardsPlaced":3.0,"survivedSingleDigitHpCount":0.0,"survivedThreeImmobilizesInFight":0.0,"takedownOnFirstTurret":0.0,"takedowns":14.0,"takedownsAfterGainingLevelAdvantage":0.0,"takedownsBeforeJungleMinionSpawn":0.0,"takedownsFirstXMinutes":5.0,"takedownsInAlcove":0.0,"takedownsInEnemyFountain":0.0,"teamBaronKills":0.0,"teamDamagePercentage":0.28337935079904064,"teamElderDragonKills":0.0,"teamRiftHeraldKills":1.0,"tookLargeDamageSurvived":0.0,"turretPlatesTaken":4.0,"turretTakedowns":4.0,"turretsTakenWithRiftHerald":5.0,"twentyMinionsIn3SecondsCount":0.0,"twoWardsOneSweeperCount":0.0,"unseenRecalls":0.0,"visionScoreAdvantageLaneOpponent":-0.4052633047103882,"visionScorePerMinute":0.732235619947708,"voidMonsterKill":2.0,"wardTakedowns":2.0,"wardTakedownsBefore20M":2.0,"wardsGuarded":0.0},"champExperience":14062,"champLevel":15,"championId":110,"championName":"Varus","championTransform":0,"commandPings":8,"consumablesPurchased":3,"damageDealtToBuildings":2867,"damageDealtToObjectives":8321,"damageDealtToTurrets":2867,"damageSelfMitigated":5276,"dangerPings":0,"deaths":0,"detectorWardsPlaced":1,"doubleKills":0,"dragonKills":0,"eligibleForProgression":false,"enemyMissingPings":3,"enemyVisionPings":0,"firstBloodAssist":false,"firstBloodKill":false,"firstTowerAssist":true,"firstTowerKill":false,"gameEndedInEarlySurrender":false,"gameEndedInSurrender":true,"getBackPings":7,"goldEarned":12231,"goldSpent":11325,"holdPings":0,"individualPosition":"AFK","inhibitorKills":0,"inhibitorTakedowns":0,"inhibitorsLost":0,"item0":3009,"item1":3142,"item2":3042,"item3":6694,"item4":3134,"item5":1055,"item6":3363,"itemsPurchased":22,"killingSprees":1,"kills":9,"lane":"BOTTOM","largestCriticalStrike":0,"largestKillingSpree":9,"largestMultiKill":1,"longestTimeSpentLiving":0,"magicDamageDealt":8299,"magicDamageDealtToChampions":4653,"magicDamageTaken":4555,"missions":{"ActMission_S1_A2_ArenaRoundsWon":0,"ActMission_S1_A2_BloodyPetalsCollected":54,"ActMission_S1_A2_FeatsOfStrength":2,"DemonsHand_MissionPointsA":14,"DemonsHand_MissionPointsB":21,"DemonsHand_MissionPointsC":38,"DemonsHand_MissionPointsD":18,"DemonsHand_MissionPointsE":62,"DemonsHand_MissionPointsF":86,"Event_2025LR_StructuresEpicMonsters":8,"Event_S1_A2_Arena_BraveryChampions":0,"Event_S1_A2_Arena_NoxianChampions":0,"Event_S1_A2_Arena_ReviveAllies":0,"Event_S1_A2_Esports_TakedownEpicMonstersSingleGame":0,"Missions_CannonMinionsKilled":13,"Missions_ChampionTakedownsWhileGhosted":0,"Missions_ChampionTakedownsWithIgnite":0,"Missions_ChampionsHitWithAbilitiesEarlyGame":8,"Missions_ChampionsKilled":9,"Missions_CreepScore":232,"Missions_CreepScoreBy10Minutes":1,"Missions_Crepe_DamageDealtSpeedZone":0,"Missions_Crepe_SnowballLanded":0,"Missions_Crepe_TakedownsWithInhibBuff":0,"Missions_DamageToChampsWithItems":354,"Missions_DamageToStructures":2867,"Missions_DestroyPlants":10,"Missions_DominationRune":0,"Missions_GoldFromStructuresDestroyed":1131,"Missions_GoldFromTurretPlatesTaken":312,"Missions_GoldPerMinute":1,"Missions_HealingFromLevelObjects":0,"Missions_HexgatesUsed":0,"Missions_ImmobilizeChampions":16,"Missions_InspirationRune":0,"Missions_LegendaryItems":3,"Missions_MinionsKilled":216,"Missions_PeriodicDamage":419,"Missions_PlaceUsefulControlWards":1,"Missions_PlaceUsefulWards":7,"Missions_PorosFed":0,"Missions_PrecisionRune":0,"Missions_ResolveRune":0,"Missions_SnowballsHit":0,"Missions_SorceryRune":0,"Missions_TakedownBaronsElderDragons":0,"Missions_TakedownDragons":1,"Missions_TakedownEpicMonsters":4,"Missions_TakedownEpicMonstersSingleGame":4,"Missions_TakedownGold":2883,"Missions_TakedownStructures":4,"Missions_TakedownWards":2,"Missions_TakedownsAfterExhausting":5,"Missions_TakedownsAfterTeleporting":1,"Missions_TakedownsBefore15Min":5,"Missions_TakedownsUnderTurret":2,"Missions_TakedownsWithHelpFromMonsters":0,"Missions_TimeSpentActivelyPlaying":23,"Missions_TotalGold":0,"Missions_TrueDamageToStructures":140,"Missions_TurretPlatesDestroyed":3,"Missions_TwoChampsKilledWithSameAbility":0,"Missions_VoidMitesSummoned":0,"PlayerScore0":0.0,"PlayerScore1":0.0,"PlayerScore10":0.0,"PlayerScore11":0.0,"PlayerScore2":0.0,"PlayerScore3":0.0,"PlayerScore4":0.0,"PlayerScore5":0.0,"PlayerScore6":0.0,"PlayerScore7":0.0,"PlayerScore8":0.0,"PlayerScore9":0.0,"SeasonalMissions_TakedownAtakhan":1},"needVisionPings":0,"neutralMinionsKilled":4,"nexusKills":0,"nexusLost":0,"nexusTakedowns":0,"objectivesStolen":0,"objectivesStolenAssists":0,"onMyWayPings":15,"participantId":9,"pentaKills":0,"perks":{"statPerks":{"defense":5011,"flex":5008,"offense":5005},"styles":[{"description":"primaryStyle","selections":[{"perk":8229,"var1":1251,"var2":0,"var3":0},{"perk":8226,"var1":250,"var2":671,"var3":0},{"perk":8210,"var1":36,"var2":0,"var3":0},{"perk":8236,"var1":14,"var2":0,"var3":0}],"style":8200},{"description":"subStyle","selections":[{"perk":9105,"var1":13,"var2":10,"var3":0},{"perk":8017,"var1":883,"var2":0,"var3":0}],"style":8000}]},"physicalDamageDealt":141755,"physicalDamageDealtToChampions":17338,"physicalDamageTaken":5258,"placement":0,"playerAugment1":0,"playerAugment2":0,"playerAugment3":0,"playerAugment4":0,"playerAugment5":0,"playerAugment6":0,"playerSubteamId":0,"profileIcon":22,"pushPings":0,"puuid":"db7d6558-f73c-54aa-97a2-1ba186e8f94e","quadraKills":0,"retreatPings":0,"riotIdGameName":"M8 Comp","riotIdTagline":"eProd","role":"SUPPORT","sightWardsBoughtInGame":0,"spell1Casts":86,"spell1Id":4,"spell2Casts":11,"spell2Id":1,"spell3Casts":38,"spell4Casts":7,"subteamPlacement":0,"summoner1Casts":1,"summoner2Casts":1,"summonerId":3372424556266848,"summonerLevel":30,"summonerName":"","teamEarlySurrendered":false,"teamId":200,"teamPosition":"UTILITY","timeCCingOthers":24,"timePlayed":1432,"totalAllyJungleMinionsKilled":0,"totalDamageDealt":151704,"totalDamageDealtToChampions":22411,"totalDamageShieldedOnTeammates":0,"totalDamageTaken":10224,"totalEnemyJungleMinionsKilled":0,"totalHeal":2683,"totalHealsOnTeammates":0,"totalMinionsKilled":228,"totalTimeCCDealt":197,"totalTimeSpentDead":0,"totalUnitsHealed":1,"tripleKills":0,"trueDamageDealt":1649,"trueDamageDealtToChampions":419,"trueDamageTaken":410,"turretKills":0,"turretTakedowns":4,"turretsLost":2,"unrealKills":0,"visionClearedPings":0,"visionScore":17,"visionWardsBoughtInGame":1,"wardsKilled":2,"wardsPlaced":7,"win":true},{"PlayerScore0":0.0,"PlayerScore1":0.0,"PlayerScore10":0.0,"PlayerScore11":0.0,"PlayerScore2":0.0,"PlayerScore3":0.0,"PlayerScore4":0.0,"PlayerScore5":0.0,"PlayerScore6":0.0,"PlayerScore7":0.0,"PlayerScore8":0.0,"PlayerScore9":0.0,"allInPings":0,"assistMePings":0,"assists":19,"baronKills":0,"basicPings":0,"bountyLevel":1,"challenges":{"12AssistStreakCount":0.0,"HealFromMapSources":0.0,"InfernalScalePickup":0.0,"SWARM_DefeatAatrox":0.0,"SWARM_DefeatBriar":0.0,"SWARM_DefeatMiniBosses":0.0,"SWARM_EvolveWeapon":0.0,"SWARM_Have3Passives":0.0,"SWARM_KillEnemy":0.0,"SWARM_PickupGold":0.0,"SWARM_ReachLevel50":0.0,"SWARM_Survive15Min":0.0,"SWARM_WinWith5EvolvedWeapons":0.0,"abilityUses":130.0,"acesBefore15Minutes":0.0,"alliedJungleMonsterKills":0.0,"baronTakedowns":0.0,"blastConeOppositeOpponentCount":0.0,"bountyGold":0.0,"buffsStolen":1.0,"completeSupportQuestInTime":0.0,"controlWardTimeCoverageInRiverOrEnemyHalf":0.6491165736009344,"controlWardsPlaced":6.0,"damagePerMinute":176.945972399556,"damageTakenOnTeamPercentage":0.182544695393709,"dancedWithRiftHerald":0.0,"deathsByEnemyChamps":4.0,"dodgeSkillShotsSmallWindow":0.0,"doubleAces":0.0,"dragonTakedowns":1.0,"earliestDragonTakedown":773.6126709710001,"earlyLaningPhaseGoldExpAdvantage":0.0,"effectiveHealAndShielding":4987.79443359375,"elderDragonKillsWithOpposingSoul":0.0,"elderDragonMultikills":0.0,"enemyChampionImmobilizations":20.0,"enemyJungleMonsterKills":0.0,"epicMonsterKillsNearEnemyJungler":0.0,"epicMonsterKillsWithin30SecondsOfSpawn":0.0,"epicMonsterSteals":0.0,"epicMonsterStolenWithoutSmite":0.0,"firstTurretKilled":1.0,"firstTurretKilledTime":828.653186674,"fistBumpParticipation":0.0,"flawlessAces":1.0,"fullTeamTakedown":2.0,"gameLength":1432.588370054,"goldPerMinute":290.09057961941653,"hadOpenNexus":0.0,"highestWardKills":1.0,"immobilizeAndKillWithAlly":10.0,"initialBuffCount":0.0,"initialCrabCount":0.0,"jungleCsBefore10Minutes":4.0,"junglerKillsEarlyJungle":0.0,"junglerTakedownsNearDamagedEpicMonster":0.0,"kTurretsDestroyedBeforePlatesFall":0.0,"kda":5.0,"killAfterHiddenWithAlly":2.0,"killParticipation":0.7142857142857143,"killedChampTookFullTeamDamageSurvived":0.0,"killingSprees":0.0,"killsNearEnemyTurret":0.0,"killsOnLanersEarlyJungleAsJungler":0.0,"killsOnRecentlyHealedByAramPack":0.0,"killsUnderOwnTurret":0.0,"killsWithHelpFromEpicMonster":0.0,"knockEnemyIntoTeamAndKill":0.0,"landSkillShotsEarlyGame":12.0,"laneMinionsFirst10Minutes":8.0,"laningPhaseGoldExpAdvantage":0.0,"legendaryCount":0.0,"legendaryItemUsed":[3869.0,3190.0],"lostAnInhibitor":0.0,"maxCsAdvantageOnLaneOpponent":1.0,"maxKillDeficit":0.0,"maxLevelLeadLaneOpponent":1.0,"mejaisFullStackInTime":0.0,"moreEnemyJungleThanOpponent":0.0,"multiKillOneSpell":0.0,"multiTurretRiftHeraldCount":0.0,"multikills":0.0,"multikillsAfterAggressiveFlash":0.0,"outerTurretExecutesBefore10Minutes":0.0,"outnumberedKills":1.0,"outnumberedNexusKill":0.0,"perfectDragonSoulsTaken":0.0,"perfectGame":0.0,"pickKillWithAlly":10.0,"poroExplosions":0.0,"quickCleanse":0.0,"quickFirstTurret":0.0,"quickSoloKills":0.0,"riftHeraldTakedowns":1.0,"saveAllyFromDeath":0.0,"scuttleCrabKills":0.0,"shortestTimeToAceFromFirstTakedown":10.170741601999907,"skillshotsDodged":19.0,"skillshotsHit":28.0,"snowballsHit":0.0,"soloBaronKills":0.0,"soloKills":0.0,"stealthWardsPlaced":27.0,"survivedSingleDigitHpCount":0.0,"survivedThreeImmobilizesInFight":5.0,"takedownOnFirstTurret":0.0,"takedowns":20.0,"takedownsAfterGainingLevelAdvantage":0.0,"takedownsBeforeJungleMinionSpawn":0.0,"takedownsFirstXMinutes":6.0,"takedownsInAlcove":0.0,"takedownsInEnemyFountain":0.0,"teamBaronKills":0.0,"teamDamagePercentage":0.0534199216144163,"teamElderDragonKills":0.0,"teamRiftHeraldKills":1.0,"tookLargeDamageSurvived":0.0,"turretPlatesTaken":1.0,"turretTakedowns":1.0,"turretsTakenWithRiftHerald":5.0,"twentyMinionsIn3SecondsCount":0.0,"twoWardsOneSweeperCount":0.0,"unseenRecalls":0.0,"visionScoreAdvantageLaneOpponent":0.13115549087524414,"visionScorePerMinute":3.1711386859827337,"voidMonsterKill":1.0,"wardTakedowns":7.0,"wardTakedownsBefore20M":5.0,"wardsGuarded":0.0},"champExperience":8038,"champLevel":11,"championId":497,"championName":"Rakan","championTransform":0,"commandPings":23,"consumablesPurchased":9,"damageDealtToBuildings":146,"damageDealtToObjectives":537,"damageDealtToTurrets":146,"damageSelfMitigated":18061,"dangerPings":0,"deaths":4,"detectorWardsPlaced":6,"doubleKills":0,"dragonKills":0,"eligibleForProgression":false,"enemyMissingPings":3,"enemyVisionPings":4,"firstBloodAssist":false,"firstBloodKill":false,"firstTowerAssist":false,"firstTowerKill":false,"gameEndedInEarlySurrender":false,"gameEndedInSurrender":true,"getBackPings":0,"goldEarned":6926,"goldSpent":5875,"holdPings":0,"individualPosition":"AFK","inhibitorKills":0,"inhibitorTakedowns":0,"inhibitorsLost":0,"item0":3190,"item1":3869,"item2":3111,"item3":3067,"item4":3114,"item5":2055,"item6":3364,"itemsPurchased":24,"killingSprees":0,"kills":1,"lane":"BOTTOM","largestCriticalStrike":0,"largestKillingSpree":0,"largestMultiKill":1,"longestTimeSpentLiving":540,"magicDamageDealt":5208,"magicDamageDealtToChampions":3440,"magicDamageTaken":8082,"missions":{"ActMission_S1_A2_ArenaRoundsWon":0,"ActMission_S1_A2_BloodyPetalsCollected":54,"ActMission_S1_A2_FeatsOfStrength":2,"DemonsHand_MissionPointsA":15,"DemonsHand_MissionPointsB":15,"DemonsHand_MissionPointsC":15,"DemonsHand_MissionPointsD":169,"DemonsHand_MissionPointsE":14,"DemonsHand_MissionPointsF":15,"Event_2025LR_StructuresEpicMonsters":3,"Event_S1_A2_Arena_BraveryChampions":0,"Event_S1_A2_Arena_NoxianChampions":0,"Event_S1_A2_Arena_ReviveAllies":0,"Event_S1_A2_Esports_TakedownEpicMonstersSingleGame":0,"Missions_CannonMinionsKilled":1,"Missions_ChampionTakedownsWhileGhosted":0,"Missions_ChampionTakedownsWithIgnite":0,"Missions_ChampionsHitWithAbilitiesEarlyGame":16,"Missions_ChampionsKilled":1,"Missions_CreepScore":22,"Missions_CreepScoreBy10Minutes":0,"Missions_Crepe_DamageDealtSpeedZone":0,"Missions_Crepe_SnowballLanded":0,"Missions_Crepe_TakedownsWithInhibBuff":0,"Missions_DamageToChampsWithItems":0,"Missions_DamageToStructures":146,"Missions_DestroyPlants":26,"Missions_DominationRune":0,"Missions_GoldFromStructuresDestroyed":406,"Missions_GoldFromTurretPlatesTaken":62,"Missions_GoldPerMinute":0,"Missions_HealingFromLevelObjects":0,"Missions_HexgatesUsed":0,"Missions_ImmobilizeChampions":19,"Missions_InspirationRune":0,"Missions_LegendaryItems":2,"Missions_MinionsKilled":11,"Missions_PeriodicDamage":0,"Missions_PlaceUsefulControlWards":6,"Missions_PlaceUsefulWards":30,"Missions_PorosFed":0,"Missions_PrecisionRune":0,"Missions_ResolveRune":0,"Missions_SnowballsHit":0,"Missions_SorceryRune":0,"Missions_TakedownBaronsElderDragons":0,"Missions_TakedownDragons":1,"Missions_TakedownEpicMonsters":2,"Missions_TakedownEpicMonstersSingleGame":2,"Missions_TakedownGold":1509,"Missions_TakedownStructures":1,"Missions_TakedownWards":7,"Missions_TakedownsAfterExhausting":19,"Missions_TakedownsAfterTeleporting":7,"Missions_TakedownsBefore15Min":6,"Missions_TakedownsUnderTurret":2,"Missions_TakedownsWithHelpFromMonsters":0,"Missions_TimeSpentActivelyPlaying":23,"Missions_TotalGold":0,"Missions_TrueDamageToStructures":36,"Missions_TurretPlatesDestroyed":1,"Missions_TwoChampsKilledWithSameAbility":0,"Missions_VoidMitesSummoned":0,"PlayerScore0":0.0,"PlayerScore1":0.0,"PlayerScore10":0.0,"PlayerScore11":0.0,"PlayerScore2":0.0,"PlayerScore3":0.0,"PlayerScore4":0.0,"PlayerScore5":0.0,"PlayerScore6":0.0,"PlayerScore7":0.0,"PlayerScore8":0.0,"PlayerScore9":0.0,"SeasonalMissions_TakedownAtakhan":0},"needVisionPings":0,"neutralMinionsKilled":4,"nexusKills":0,"nexusLost":0,"nexusTakedowns":0,"objectivesStolen":0,"objectivesStolenAssists":0,"onMyWayPings":23,"participantId":10,"pentaKills":0,"perks":{"statPerks":{"defense":5011,"flex":5010,"offense":5007},"styles":[{"description":"primaryStyle","selections":[{"perk":8465,"var1":2073,"var2":0,"var3":0},{"perk":8401,"var1":271,"var2":0,"var3":0},{"perk":8473,"var1":434,"var2":0,"var3":0},{"perk":8451,"var1":127,"var2":0,"var3":0}],"style":8400},{"description":"subStyle","selections":[{"perk":8321,"var1":132,"var2":0,"var3":0},{"perk":8347,"var1":0,"var2":0,"var3":0}],"style":8300}]},"physicalDamageDealt":3448,"physicalDamageDealtToChampions":784,"physicalDamageTaken":8227,"placement":0,"playerAugment1":0,"playerAugment2":0,"playerAugment3":0,"playerAugment4":0,"playerAugment5":0,"playerAugment6":0,"playerSubteamId":0,"profileIcon":567,"pushPings":0,"puuid":"9219250b-bb29-5a96-bffb-77b9efea5187","quadraKills":0,"retreatPings":17,"riotIdGameName":"M8 Erdote","riotIdTagline":"eProd","role":"SUPPORT","sightWardsBoughtInGame":0,"spell1Casts":42,"spell1Id":7,"spell2Casts":42,"spell2Id":4,"spell3Casts":38,"spell4Casts":8,"subteamPlacement":0,"summoner1Casts":5,"summoner2Casts":3,"summonerId":3373249008903520,"summonerLevel":30,"summonerName":"","teamEarlySurrendered":false,"teamId":200,"teamPosition":"JUNGLE","timeCCingOthers":19,"timePlayed":1432,"totalAllyJungleMinionsKilled":0,"totalDamageDealt":10865,"totalDamageDealtToChampions":4224,"totalDamageShieldedOnTeammates":3160,"totalDamageTaken":17480,"totalEnemyJungleMinionsKilled":0,"totalHeal":6298,"totalHealsOnTeammates":1827,"totalMinionsKilled":18,"totalTimeCCDealt":70,"totalTimeSpentDead":93,"totalUnitsHealed":5,"tripleKills":0,"trueDamageDealt":2208,"trueDamageDealtToChampions":0,"trueDamageTaken":1170,"turretKills":0,"turretTakedowns":1,"turretsLost":2,"unrealKills":0,"visionClearedPings":0,"visionScore":75,"visionWardsBoughtInGame":7,"wardsKilled":7,"wardsPlaced":33,"win":true}],"platformId":"LOLTMNT01","queueId":0,"seasonId":0,"teams":[{"bans":[{"championId":429,"pickTurn":1},{"championId":895,"pickTurn":3},{"championId":107,"pickTurn":5},{"championId":799,"pickTurn":2},{"championId":887,"pickTurn":4}],"feats":{"EPIC_MONSTER_KILL":{"featState":1001},"FIRST_BLOOD":{"featState":1001},"FIRST_TURRET":{"featState":0}},"objectives":{"atakhan":{"first":false,"kills":0},"baron":{"first":false,"kills":0},"champion":{"first":false,"kills":9},"dragon":{"first":false,"kills":0},"horde":{"first":true,"kills":3},"inhibitor":{"first":false,"kills":0},"riftHerald":{"first":false,"kills":0},"tower":{"first":false,"kills":2}},"teamId":100,"win":false},{"bans":[{"championId":166,"pickTurn":2},{"championId":233,"pickTurn":4},{"championId":32,"pickTurn":6},{"championId":42,"pickTurn":1},{"championId":18,"pickTurn":3}],"feats":{"EPIC_MONSTER_KILL":{"featState":3},"FIRST_BLOOD":{"featState":3},"FIRST_TURRET":{"featState":0}},"objectives":{"atakhan":{"first":true,"kills":1},"baron":{"first":false,"kills":0},"champion":{"first":true,"kills":28},"dragon":{"first":true,"kills":3},"horde":{"first":false,"kills":3},"inhibitor":{"first":false,"kills":0},"riftHerald":{"first":true,"kills":1},"tower":{"first":true,"kills":7}},"teamId":200,"win":true}],"tournamentCode":""}