{"endOfGameResult":"GameComplete","gameCreation":1743521715421,"gameDuration":1508,"gameEndTimestamp":1743523234388,"gameId":397510,"gameMode":"CLASSIC","gameName":"scrim| m8 game 5","gameStartTimestamp":1743521725786,"gameType":"CUSTOM_GAME","gameVersion":"15.7.668.6919","mapId":11,"participants":[{"PlayerScore0":0.0,"PlayerScore1":0.0,"PlayerScore10":0.0,"PlayerScore11":0.0,"PlayerScore2":0.0,"PlayerScore3":0.0,"PlayerScore4":0.0,"PlayerScore5":0.0,"PlayerScore6":0.0,"PlayerScore7":0.0,"PlayerScore8":0.0,"PlayerScore9":0.0,"allInPings":0,"assistMePings":2,"assists":6,"baronKills":0,"basicPings":0,"bountyLevel":4,"challenges":{"12AssistStreakCount":0.0,"HealFromMapSources":622.8146362304688,"InfernalScalePickup":0.0,"SWARM_DefeatAatrox":0.0,"SWARM_DefeatBriar":0.0,"SWARM_DefeatMiniBosses":0.0,"SWARM_EvolveWeapon":0.0,"SWARM_Have3Passives":0.0,"SWARM_KillEnemy":0.0,"SWARM_PickupGold":0.0,"SWARM_ReachLevel50":0.0,"SWARM_Survive15Min":0.0,"SWARM_WinWith5EvolvedWeapons":0.0,"abilityUses":76.0,"acesBefore15Minutes":0.0,"alliedJungleMonsterKills":2.0,"baronTakedowns":0.0,"blastConeOppositeOpponentCount":0.0,"bountyGold":0.0,"buffsStolen":0.0,"completeSupportQuestInTime":0.0,"controlWardTimeCoverageInRiverOrEnemyHalf":0.7595975639099453,"controlWardsPlaced":4.0,"damagePerMinute":424.2935136940848,"damageTakenOnTeamPercentage":0.28716992510559763,"dancedWithRiftHerald":0.0,"deathsByEnemyChamps":1.0,"dodgeSkillShotsSmallWindow":0.0,"doubleAces":0.0,"dragonTakedowns":1.0,"earliestDragonTakedown":1088.548450851,"earlyLaningPhaseGoldExpAdvantage":0.0,"effectiveHealAndShielding":0.0,"elderDragonKillsWithOpposingSoul":0.0,"elderDragonMultikills":0.0,"enemyChampionImmobilizations":19.0,"enemyJungleMonsterKills":1.0,"epicMonsterKillsNearEnemyJungler":0.0,"epicMonsterKillsWithin30SecondsOfSpawn":0.0,"epicMonsterSteals":0.0,"epicMonsterStolenWithoutSmite":0.0,"firstTurretKilled":1.0,"firstTurretKilledTime":901.8482614870001,"fistBumpParticipation":0.0,"flawlessAces":0.0,"fullTeamTakedown":2.0,"gameLength":1508.899957649,"goldPerMinute":419.6950555616709,"hadOpenNexus":0.0,"immobilizeAndKillWithAlly":5.0,"initialBuffCount":0.0,"initialCrabCount":0.0,"jungleCsBefore10Minutes":4.0,"junglerTakedownsNearDamagedEpicMonster":0.0,"kTurretsDestroyedBeforePlatesFall":0.0,"kda":10.0,"killAfterHiddenWithAlly":1.0,"killParticipation":0.5,"killedChampTookFullTeamDamageSurvived":0.0,"killingSprees":1.0,"killsNearEnemyTurret":1.0,"killsOnRecentlyHealedByAramPack":0.0,"killsUnderOwnTurret":0.0,"killsWithHelpFromEpicMonster":0.0,"knockEnemyIntoTeamAndKill":0.0,"landSkillShotsEarlyGame":0.0,"laneMinionsFirst10Minutes":92.0,"laningPhaseGoldExpAdvantage":0.0,"legendaryCount":0.0,"legendaryItemUsed":[6631.0,3153.0],"lostAnInhibitor":0.0,"maxCsAdvantageOnLaneOpponent":18.0,"maxKillDeficit":0.0,"maxLevelLeadLaneOpponent":2.0,"mejaisFullStackInTime":0.0,"moreEnemyJungleThanOpponent":0.0,"multiKillOneSpell":0.0,"multiTurretRiftHeraldCount":0.0,"multikills":0.0,"multikillsAfterAggressiveFlash":0.0,"outerTurretExecutesBefore10Minutes":0.0,"outnumberedKills":0.0,"outnumberedNexusKill":0.0,"perfectDragonSoulsTaken":0.0,"perfectGame":0.0,"pickKillWithAlly":4.0,"poroExplosions":0.0,"quickCleanse":0.0,"quickFirstTurret":0.0,"quickSoloKills":0.0,"riftHeraldTakedowns":0.0,"saveAllyFromDeath":0.0,"scuttleCrabKills":1.0,"skillshotsDodged":4.0,"skillshotsHit":0.0,"snowballsHit":0.0,"soloBaronKills":0.0,"soloKills":2.0,"soloTurretsLategame":1.0,"stealthWardsPlaced":5.0,"survivedSingleDigitHpCount":0.0,"survivedThreeImmobilizesInFight":0.0,"takedownOnFirstTurret":1.0,"takedowns":10.0,"takedownsAfterGainingLevelAdvantage":0.0,"takedownsBeforeJungleMinionSpawn":0.0,"takedownsFirstXMinutes":2.0,"takedownsInAlcove":0.0,"takedownsInEnemyFountain":0.0,"teamBaronKills":0.0,"teamDamagePercentage":0.14608115878560166,"teamElderDragonKills":0.0,"teamRiftHeraldKills":1.0,"tookLargeDamageSurvived":0.0,"turretPlatesTaken":3.0,"turretTakedowns":1.0,"turretsTakenWithRiftHerald":5.0,"twentyMinionsIn3SecondsCount":0.0,"twoWardsOneSweeperCount":0.0,"unseenRecalls":0.0,"visionScoreAdvantageLaneOpponent":0.8322774171829224,"visionScorePerMinute":1.2130994756123428,"voidMonsterKill":2.0,"wardTakedowns":3.0,"wardTakedownsBefore20M":2.0,"wardsGuarded":2.0},"champExperience":14814,"champLevel":16,"championId":19,"championName":"Warwick","championTransform":0,"commandPings":8,"consumablesPurchased":5,"damageDealtToBuildings":6144,"damageDealtToObjectives":17148,"damageDealtToTurrets":6144,"damageSelfMitigated":20453,"dangerPings":0,"deaths":1,"detectorWardsPlaced":4,"doubleKills":0,"dragonKills":0,"eligibleForProgression":false,"enemyMissingPings":5,"enemyVisionPings":0,"firstBloodAssist":false,"firstBloodKill":true,"firstTowerAssist":false,"firstTowerKill":true,"gameEndedInEarlySurrender":false,"gameEndedInSurrender":true,"getBackPings":4,"goldEarned":10554,"goldSpent":8900,"holdPings":0,"individualPosition":"AFK","inhibitorKills":0,"inhibitorTakedowns":0,"inhibitorsLost":0,"item0":1055,"item1":6631,"item2":0,"item3":3153,"item4":1028,"item5":3047,"item6":3364,"itemsPurchased":19,"killingSprees":1,"kills":4,"lane":"MIDDLE","largestCriticalStrike":0,"largestKillingSpree":3,"largestMultiKill":1,"longestTimeSpentLiving":1268,"magicDamageDealt":29250,"magicDamageDealtToChampions":5878,"magicDamageTaken":5417,"missions":{"ActMission_S1_A2_ArenaRoundsWon":0,"ActMission_S1_A2_BloodyPetalsCollected":42,"ActMission_S1_A2_FeatsOfStrength":2,"DemonsHand_MissionPointsA":68,"DemonsHand_MissionPointsB":69,"DemonsHand_MissionPointsC":69,"DemonsHand_MissionPointsD":73,"DemonsHand_MissionPointsE":105,"DemonsHand_MissionPointsF":69,"Event_2025LR_StructuresEpicMonsters":5,"Event_S1_A1_AprilFools_Dragon":0,"Event_S1_A1_AprilFools_Snowball":0,"Event_S1_A2_AprilFools_Dragon":0,"Event_S1_A2_AprilFools_Garen_Play":0,"Event_S1_A2_AprilFools_Garen_Takedown":1,"Event_S1_A2_AprilFools_Snowball":0,"Event_S1_A2_Arena_BraveryChampions":0,"Event_S1_A2_Arena_NoxianChampions":0,"Event_S1_A2_Arena_ReviveAllies":0,"Event_S1_A2_Esports_TakedownEpicMonstersSingleGame":0,"Missions_CannonMinionsKilled":14,"Missions_ChampionTakedownsWhileGhosted":0,"Missions_ChampionTakedownsWithIgnite":1,"Missions_ChampionsHitWithAbilitiesEarlyGame":7,"Missions_ChampionsKilled":4,"Missions_CreepScore":224,"Missions_CreepScoreBy10Minutes":1,"Missions_Crepe_DamageDealtSpeedZone":0,"Missions_Crepe_SnowballLanded":0,"Missions_Crepe_TakedownsWithInhibBuff":0,"Missions_DamageToChampsWithItems":1441,"Missions_DamageToStructures":6144,"Missions_DestroyPlants":32,"Missions_DominationRune":0,"Missions_GoldFromStructuresDestroyed":700,"Missions_GoldFromTurretPlatesTaken":375,"Missions_GoldPerMinute":1,"Missions_HealingFromLevelObjects":622,"Missions_HexgatesUsed":0,"Missions_ImmobilizeChampions":12,"Missions_InspirationRune":0,"Missions_LegendaryItems":2,"Missions_MinionsKilled":208,"Missions_PeriodicDamage":0,"Missions_PlaceUsefulControlWards":3,"Missions_PlaceUsefulWards":8,"Missions_PorosFed":0,"Missions_PrecisionRune":1,"Missions_ResolveRune":0,"Missions_SnowballsHit":0,"Missions_SorceryRune":0,"Missions_TakedownBaronsElderDragons":0,"Missions_TakedownDragons":1,"Missions_TakedownEpicMonsters":3,"Missions_TakedownEpicMonstersSingleGame":3,"Missions_TakedownGold":1508,"Missions_TakedownStructures":1,"Missions_TakedownWards":3,"Missions_TakedownsAfterExhausting":6,"Missions_TakedownsAfterTeleporting":9,"Missions_TakedownsBefore15Min":2,"Missions_TakedownsUnderTurret":2,"Missions_TakedownsWithHelpFromMonsters":0,"Missions_TimeSpentActivelyPlaying":25,"Missions_TotalGold":0,"Missions_TrueDamageToStructures":1716,"Missions_TurretPlatesDestroyed":3,"Missions_TwoChampsKilledWithSameAbility":0,"Missions_VoidMitesSummoned":5,"PlayerScore0":0.0,"PlayerScore1":0.0,"PlayerScore10":0.0,"PlayerScore11":0.0,"PlayerScore2":0.0,"PlayerScore3":0.0,"PlayerScore4":0.0,"PlayerScore5":0.0,"PlayerScore6":0.0,"PlayerScore7":0.0,"PlayerScore8":0.0,"PlayerScore9":0.0,"SeasonalMissions_TakedownAtakhan":1},"needVisionPings":0,"neutralMinionsKilled":13,"nexusKills":0,"nexusLost":0,"nexusTakedowns":0,"objectivesStolen":0,"objectivesStolenAssists":0,"onMyWayPings":16,"participantId":1,"pentaKills":0,"perks":{"statPerks":{"defense":5011,"flex":5008,"offense":5008},"styles":[{"description":"primaryStyle","selections":[{"perk":8008,"var1":642,"var2":642,"var3":0},{"perk":8009,"var1":1187,"var2":0,"var3":0},{"perk":9104,"var1":16,"var2":30,"var3":0},{"perk":8299,"var1":733,"var2":0,"var3":0}],"style":8000},{"description":"subStyle","selections":[{"perk":8444,"var1":1437,"var2":0,"var3":0},{"perk":8453,"var1":1494,"var2":122,"var3":0}],"style":8400}]},"physicalDamageDealt":105904,"physicalDamageDealtToChampions":4791,"physicalDamageTaken":20988,"placement":0,"playerAugment1":0,"playerAugment2":0,"playerAugment3":0,"playerAugment4":0,"playerAugment5":0,"playerAugment6":0,"playerSubteamId":0,"profileIcon":29,"pushPings":1,"puuid":"fb22f9db-4f42-562c-a80c-6acdb3b59817","quadraKills":0,"retreatPings":1,"riotIdGameName":"M8 Empyros","riotIdTagline":"eProd","role":"SUPPORT","sightWardsBoughtInGame":0,"spell1Casts":43,"spell1Id":4,"spell2Casts":8,"spell2Id":21,"spell3Casts":19,"spell4Casts":6,"subteamPlacement":0,"summoner1Casts":2,"summoner2Casts":1,"summonerId":3372423616250912,"summonerLevel":30,"summonerName":"","teamEarlySurrendered":false,"teamId":100,"teamPosition":"AFK","timeCCingOthers":16,"timePlayed":1508,"totalAllyJungleMinionsKilled":2,"totalDamageDealt":137615,"totalDamageDealtToChampions":10670,"totalDamageShieldedOnTeammates":0,"totalDamageTaken":27282,"totalEnemyJungleMinionsKilled":2,"totalHeal":17075,"totalHealsOnTeammates":0,"totalMinionsKilled":211,"totalTimeCCDealt":199,"totalTimeSpentDead":47,"totalUnitsHealed":1,"tripleKills":0,"trueDamageDealt":2461,"trueDamageDealtToChampions":0,"trueDamageTaken":875,"turretKills":1,"turretTakedowns":1,"turretsLost":1,"unrealKills":0,"visionClearedPings":0,"visionScore":30,"visionWardsBoughtInGame":4,"wardsKilled":3,"wardsPlaced":9,"win":true},{"PlayerScore0":0.0,"PlayerScore1":0.0,"PlayerScore10":0.0,"PlayerScore11":0.0,"PlayerScore2":0.0,"PlayerScore3":0.0,"PlayerScore4":0.0,"PlayerScore5":0.0,"PlayerScore6":0.0,"PlayerScore7":0.0,"PlayerScore8":0.0,"PlayerScore9":0.0,"allInPings":2,"assistMePings":22,"assists":8,"baronKills":0,"basicPings":0,"bountyLevel":6,"challenges":{"12AssistStreakCount":0.0,"HealFromMapSources":0.0,"InfernalScalePickup":0.0,"SWARM_DefeatAatrox":0.0,"SWARM_DefeatBriar":0.0,"SWARM_DefeatMiniBosses":0.0,"SWARM_EvolveWeapon":0.0,"SWARM_Have3Passives":0.0,"SWARM_KillEnemy":0.0,"SWARM_PickupGold":0.0,"SWARM_ReachLevel50":0.0,"SWARM_Survive15Min":0.0,"SWARM_WinWith5EvolvedWeapons":0.0,"abilityUses":247.0,"acesBefore15Minutes":0.0,"alliedJungleMonsterKills":87.0,"baronTakedowns":0.0,"blastConeOppositeOpponentCount":0.0,"bountyGold":107.11444091796875,"buffsStolen":1.0,"completeSupportQuestInTime":0.0,"controlWardTimeCoverageInRiverOrEnemyHalf":0.7296205633528798,"controlWardsPlaced":6.0,"damagePerMinute":799.7847890825672,"damageTakenOnTeamPercentage":0.29426281465302184,"dancedWithRiftHerald":0.0,"deathsByEnemyChamps":3.0,"dodgeSkillShotsSmallWindow":0.0,"doubleAces":0.0,"dragonTakedowns":2.0,"earliestDragonTakedown":1088.548450851,"earlyLaningPhaseGoldExpAdvantage":0.0,"effectiveHealAndShielding":0.0,"elderDragonKillsWithOpposingSoul":0.0,"elderDragonMultikills":0.0,"enemyChampionImmobilizations":13.0,"enemyJungleMonsterKills":8.0,"epicMonsterKillsNearEnemyJungler":0.0,"epicMonsterKillsWithin30SecondsOfSpawn":1.0,"epicMonsterSteals":0.0,"epicMonsterStolenWithoutSmite":0.0,"firstTurretKilled":1.0,"firstTurretKilledTime":901.8482614870001,"fistBumpParticipation":0.0,"flawlessAces":0.0,"fullTeamTakedown":2.0,"gameLength":1508.899957649,"getTakedownsInAllLanesEarlyJungleAsLaner":0.0,"goldPerMinute":421.9667720869274,"hadOpenNexus":0.0,"highestChampionDamage":1.0,"immobilizeAndKillWithAlly":8.0,"initialBuffCount":3.0,"initialCrabCount":0.0,"jungleCsBefore10Minutes":70.00000008940697,"junglerTakedownsNearDamagedEpicMonster":0.0,"kTurretsDestroyedBeforePlatesFall":0.0,"kda":4.666666666666667,"killAfterHiddenWithAlly":2.0,"killParticipation":0.7,"killedChampTookFullTeamDamageSurvived":0.0,"killingSprees":1.0,"killsNearEnemyTurret":4.0,"killsOnOtherLanesEarlyJungleAsLaner":1.0,"killsOnRecentlyHealedByAramPack":0.0,"killsUnderOwnTurret":0.0,"killsWithHelpFromEpicMonster":0.0,"knockEnemyIntoTeamAndKill":8.0,"landSkillShotsEarlyGame":5.0,"laneMinionsFirst10Minutes":2.0,"laningPhaseGoldExpAdvantage":0.0,"legendaryCount":0.0,"legendaryItemUsed":[6653.0,4633.0],"lostAnInhibitor":0.0,"maxCsAdvantageOnLaneOpponent":6.25,"maxKillDeficit":0.0,"maxLevelLeadLaneOpponent":2.0,"mejaisFullStackInTime":0.0,"moreEnemyJungleThanOpponent":0.0,"multiKillOneSpell":0.0,"multiTurretRiftHeraldCount":0.0,"multikills":1.0,"multikillsAfterAggressiveFlash":1.0,"outerTurretExecutesBefore10Minutes":0.0,"outnumberedKills":2.0,"outnumberedNexusKill":0.0,"perfectDragonSoulsTaken":0.0,"perfectGame":0.0,"pickKillWithAlly":8.0,"poroExplosions":0.0,"quickCleanse":0.0,"quickFirstTurret":0.0,"quickSoloKills":0.0,"riftHeraldTakedowns":1.0,"saveAllyFromDeath":0.0,"scuttleCrabKills":3.0,"skillshotsDodged":11.0,"skillshotsHit":33.0,"snowballsHit":0.0,"soloBaronKills":0.0,"soloKills":0.0,"stealthWardsPlaced":2.0,"survivedSingleDigitHpCount":0.0,"survivedThreeImmobilizesInFight":7.0,"takedownOnFirstTurret":0.0,"takedowns":14.0,"takedownsAfterGainingLevelAdvantage":0.0,"takedownsBeforeJungleMinionSpawn":0.0,"takedownsFirstXMinutes":4.0,"takedownsInAlcove":0.0,"takedownsInEnemyFountain":0.0,"teamBaronKills":0.0,"teamDamagePercentage":0.27536006325214823,"teamElderDragonKills":0.0,"teamRiftHeraldKills":1.0,"tookLargeDamageSurvived":0.0,"turretPlatesTaken":0.0,"turretTakedowns":1.0,"turretsTakenWithRiftHerald":5.0,"twentyMinionsIn3SecondsCount":0.0,"twoWardsOneSweeperCount":0.0,"unseenRecalls":0.0,"visionScoreAdvantageLaneOpponent":-0.10668468475341797,"visionScorePerMinute":1.4097516631704607,"voidMonsterKill":6.0,"wardTakedowns":5.0,"wardTakedownsBefore20M":4.0,"wardsGuarded":1.0},"champExperience":12461,"champLevel":14,"championId":131,"championName":"Diana","championTransform":0,"commandPings":11,"consumablesPurchased":6,"damageDealtToBuildings":164,"damageDealtToObjectives":39687,"damageDealtToTurrets":164,"damageSelfMitigated":36839,"dangerPings":0,"deaths":3,"detectorWardsPlaced":6,"doubleKills":1,"dragonKills":1,"eligibleForProgression":false,"enemyMissingPings":22,"enemyVisionPings":14,"firstBloodAssist":false,"firstBloodKill":false,"firstTowerAssist":true,"firstTowerKill":false,"gameEndedInEarlySurrender":false,"gameEndedInSurrender":true,"getBackPings":0,"goldEarned":10611,"goldSpent":8700,"holdPings":0,"individualPosition":"AFK","inhibitorKills":0,"inhibitorTakedowns":0,"inhibitorsLost":0,"item0":3111,"item1":6653,"item2":0,"item3":4633,"item4":1082,"item5":1028,"item6":3364,"itemsPurchased":20,"killingSprees":2,"kills":6,"lane":"MIDDLE","largestCriticalStrike":0,"largestKillingSpree":3,"largestMultiKill":2,"longestTimeSpentLiving":664,"magicDamageDealt":152540,"magicDamageDealtToChampions":18010,"magicDamageTaken":10860,"missions":{"ActMission_S1_A2_ArenaRoundsWon":0,"ActMission_S1_A2_BloodyPetalsCollected":42,"ActMission_S1_A2_FeatsOfStrength":2,"DemonsHand_MissionPointsA":75,"DemonsHand_MissionPointsB":100,"DemonsHand_MissionPointsC":72,"DemonsHand_MissionPointsD":68,"DemonsHand_MissionPointsE":69,"DemonsHand_MissionPointsF":69,"Event_2025LR_StructuresEpicMonsters":10,"Event_S1_A1_AprilFools_Dragon":0,"Event_S1_A1_AprilFools_Snowball":0,"Event_S1_A2_AprilFools_Dragon":0,"Event_S1_A2_AprilFools_Garen_Play":0,"Event_S1_A2_AprilFools_Garen_Takedown":1,"Event_S1_A2_AprilFools_Snowball":0,"Event_S1_A2_Arena_BraveryChampions":0,"Event_S1_A2_Arena_NoxianChampions":0,"Event_S1_A2_Arena_ReviveAllies":0,"Event_S1_A2_Esports_TakedownEpicMonstersSingleGame":0,"Missions_CannonMinionsKilled":1,"Missions_ChampionTakedownsWhileGhosted":0,"Missions_ChampionTakedownsWithIgnite":2,"Missions_ChampionsHitWithAbilitiesEarlyGame":23,"Missions_ChampionsKilled":6,"Missions_CreepScore":169,"Missions_CreepScoreBy10Minutes":1,"Missions_Crepe_DamageDealtSpeedZone":0,"Missions_Crepe_SnowballLanded":0,"Missions_Crepe_TakedownsWithInhibBuff":0,"Missions_DamageToChampsWithItems":2734,"Missions_DamageToStructures":164,"Missions_DestroyPlants":32,"Missions_DominationRune":0,"Missions_GoldFromStructuresDestroyed":408,"Missions_GoldFromTurretPlatesTaken":0,"Missions_GoldPerMinute":1,"Missions_HealingFromLevelObjects":0,"Missions_HexgatesUsed":0,"Missions_ImmobilizeChampions":13,"Missions_InspirationRune":0,"Missions_LegendaryItems":2,"Missions_MinionsKilled":3,"Missions_PeriodicDamage":2907,"Missions_PlaceUsefulControlWards":5,"Missions_PlaceUsefulWards":7,"Missions_PorosFed":0,"Missions_PrecisionRune":1,"Missions_ResolveRune":0,"Missions_SnowballsHit":0,"Missions_SorceryRune":0,"Missions_TakedownBaronsElderDragons":0,"Missions_TakedownDragons":2,"Missions_TakedownEpicMonsters":6,"Missions_TakedownEpicMonstersSingleGame":6,"Missions_TakedownGold":2396,"Missions_TakedownStructures":1,"Missions_TakedownWards":5,"Missions_TakedownsAfterExhausting":8,"Missions_TakedownsAfterTeleporting":7,"Missions_TakedownsBefore15Min":4,"Missions_TakedownsUnderTurret":2,"Missions_TakedownsWithHelpFromMonsters":0,"Missions_TimeSpentActivelyPlaying":25,"Missions_TotalGold":0,"Missions_TrueDamageToStructures":150,"Missions_TurretPlatesDestroyed":0,"Missions_TwoChampsKilledWithSameAbility":0,"Missions_VoidMitesSummoned":2,"PlayerScore0":0.0,"PlayerScore1":0.0,"PlayerScore10":0.0,"PlayerScore11":0.0,"PlayerScore2":0.0,"PlayerScore3":0.0,"PlayerScore4":0.0,"PlayerScore5":0.0,"PlayerScore6":0.0,"PlayerScore7":0.0,"PlayerScore8":0.0,"PlayerScore9":0.0,"SeasonalMissions_TakedownAtakhan":1},"needVisionPings":1,"neutralMinionsKilled":161,"nexusKills":0,"nexusLost":0,"nexusTakedowns":0,"objectivesStolen":0,"objectivesStolenAssists":0,"onMyWayPings":94,"participantId":2,"pentaKills":0,"perks":{"statPerks":{"defense":5001,"flex":5008,"offense":5008},"styles":[{"description":"primaryStyle","selections":[{"perk":8010,"var1":612,"var2":0,"var3":0},{"perk":9111,"var1":1707,"var2":280,"var3":0},{"perk":9104,"var1":9,"var2":10,"var3":0},{"perk":8299,"var1":863,"var2":0,"var3":0}],"style":8000},{"description":"subStyle","selections":[{"perk":8304,"var1":9,"var2":4,"var3":5},{"perk":8347,"var1":0,"var2":0,"var3":0}],"style":8300}]},"physicalDamageDealt":29771,"physicalDamageDealtToChampions":1680,"physicalDamageTaken":16162,"placement":0,"playerAugment1":0,"playerAugment2":0,"playerAugment3":0,"playerAugment4":0,"playerAugment5":0,"playerAugment6":0,"playerSubteamId":0,"profileIcon":29,"pushPings":0,"puuid":"2d1bb646-cc94-5e41-8811-b53cf6e1379b","quadraKills":0,"retreatPings":9,"riotIdGameName":"M8 Zicssi","riotIdTagline":"eProd","role":"SUPPORT","sightWardsBoughtInGame":0,"spell1Casts":113,"spell1Id":11,"spell2Casts":51,"spell2Id":4,"spell3Casts":75,"spell4Casts":8,"subteamPlacement":0,"summoner1Casts":16,"summoner2Casts":4,"summonerId":3373192202740768,"summonerLevel":30,"summonerName":"","teamEarlySurrendered":false,"teamId":100,"teamPosition":"BOTTOM","timeCCingOthers":12,"timePlayed":1508,"totalAllyJungleMinionsKilled":118,"totalDamageDealt":243103,"totalDamageDealtToChampions":20113,"totalDamageShieldedOnTeammates":0,"totalDamageTaken":27956,"totalEnemyJungleMinionsKilled":12,"totalHeal":14226,"totalHealsOnTeammates":0,"totalMinionsKilled":8,"totalTimeCCDealt":133,"totalTimeSpentDead":89,"totalUnitsHealed":1,"tripleKills":0,"trueDamageDealt":60789,"trueDamageDealtToChampions":422,"trueDamageTaken":932,"turretKills":0,"turretTakedowns":1,"turretsLost":1,"unrealKills":0,"visionClearedPings":0,"visionScore":35,"visionWardsBoughtInGame":6,"wardsKilled":5,"wardsPlaced":8,"win":true},{"PlayerScore0":0.0,"PlayerScore1":0.0,"PlayerScore10":0.0,"PlayerScore11":0.0,"PlayerScore2":0.0,"PlayerScore3":0.0,"PlayerScore4":0.0,"PlayerScore5":0.0,"PlayerScore6":0.0,"PlayerScore7":0.0,"PlayerScore8":0.0,"PlayerScore9":0.0,"allInPings":6,"assistMePings":4,"assists":6,"baronKills":0,"basicPings":0,"bountyLevel":4,"challenges":{"12AssistStreakCount":0.0,"HealFromMapSources":196.0,"InfernalScalePickup":0.0,"SWARM_DefeatAatrox":0.0,"SWARM_DefeatBriar":0.0,"SWARM_DefeatMiniBosses":0.0,"SWARM_EvolveWeapon":0.0,"SWARM_Have3Passives":0.0,"SWARM_KillEnemy":0.0,"SWARM_PickupGold":0.0,"SWARM_ReachLevel50":0.0,"SWARM_Survive15Min":0.0,"SWARM_WinWith5EvolvedWeapons":0.0,"abilityUses":189.0,"acesBefore15Minutes":0.0,"alliedJungleMonsterKills":0.0,"baronTakedowns":0.0,"blastConeOppositeOpponentCount":0.0,"bountyGold":0.0,"buffsStolen":0.0,"completeSupportQuestInTime":0.0,"controlWardTimeCoverageInRiverOrEnemyHalf":0.3318318613946657,"controlWardsPlaced":3.0,"damagePerMinute":641.3439683745167,"damageTakenOnTeamPercentage":0.1544037201795742,"dancedWithRiftHerald":0.0,"deathsByEnemyChamps":1.0,"dodgeSkillShotsSmallWindow":0.0,"doubleAces":0.0,"dragonTakedowns":1.0,"earliestDragonTakedown":1437.3577818830001,"earlyLaningPhaseGoldExpAdvantage":0.0,"effectiveHealAndShielding":0.0,"elderDragonKillsWithOpposingSoul":0.0,"elderDragonMultikills":0.0,"enemyChampionImmobilizations":6.0,"enemyJungleMonsterKills":0.0,"epicMonsterKillsNearEnemyJungler":0.0,"epicMonsterKillsWithin30SecondsOfSpawn":0.0,"epicMonsterSteals":0.0,"epicMonsterStolenWithoutSmite":0.0,"firstTurretKilled":1.0,"firstTurretKilledTime":901.8482614870001,"fistBumpParticipation":0.0,"flawlessAces":0.0,"fullTeamTakedown":2.0,"gameLength":1508.899957649,"getTakedownsInAllLanesEarlyJungleAsLaner":0.0,"goldPerMinute":423.7525049142371,"hadOpenNexus":0.0,"immobilizeAndKillWithAlly":4.0,"initialBuffCount":0.0,"initialCrabCount":0.0,"jungleCsBefore10Minutes":0.0,"junglerTakedownsNearDamagedEpicMonster":0.0,"kTurretsDestroyedBeforePlatesFall":0.0,"kda":10.0,"killAfterHiddenWithAlly":1.0,"killParticipation":0.5,"killedChampTookFullTeamDamageSurvived":0.0,"killingSprees":1.0,"killsNearEnemyTurret":2.0,"killsOnOtherLanesEarlyJungleAsLaner":2.0,"killsOnRecentlyHealedByAramPack":0.0,"killsUnderOwnTurret":0.0,"killsWithHelpFromEpicMonster":0.0,"knockEnemyIntoTeamAndKill":4.0,"landSkillShotsEarlyGame":0.0,"laneMinionsFirst10Minutes":71.0,"laningPhaseGoldExpAdvantage":0.0,"legendaryCount":0.0,"legendaryItemUsed":[3115.0,3089.0],"lostAnInhibitor":0.0,"maxCsAdvantageOnLaneOpponent":21.0,"maxKillDeficit":0.0,"maxLevelLeadLaneOpponent":3.0,"mejaisFullStackInTime":0.0,"moreEnemyJungleThanOpponent":0.0,"multiKillOneSpell":0.0,"multiTurretRiftHeraldCount":0.0,"multikills":0.0,"multikillsAfterAggressiveFlash":0.0,"outerTurretExecutesBefore10Minutes":0.0,"outnumberedKills":0.0,"outnumberedNexusKill":0.0,"perfectDragonSoulsTaken":0.0,"perfectGame":0.0,"pickKillWithAlly":7.0,"poroExplosions":0.0,"quickCleanse":0.0,"quickFirstTurret":0.0,"quickSoloKills":0.0,"riftHeraldTakedowns":1.0,"saveAllyFromDeath":0.0,"scuttleCrabKills":0.0,"skillshotsDodged":17.0,"skillshotsHit":6.0,"snowballsHit":0.0,"soloBaronKills":0.0,"soloKills":0.0,"soloTurretsLategame":1.0,"stealthWardsPlaced":5.0,"survivedSingleDigitHpCount":0.0,"survivedThreeImmobilizesInFight":0.0,"takedownOnFirstTurret":0.0,"takedowns":10.0,"takedownsAfterGainingLevelAdvantage":0.0,"takedownsBeforeJungleMinionSpawn":0.0,"takedownsFirstXMinutes":3.0,"takedownsInAlcove":0.0,"takedownsInEnemyFountain":0.0,"teamBaronKills":0.0,"teamDamagePercentage":0.22081004553808667,"teamElderDragonKills":0.0,"teamRiftHeraldKills":1.0,"tookLargeDamageSurvived":0.0,"turretPlatesTaken":1.0,"turretTakedowns":2.0,"turretsTakenWithRiftHerald":5.0,"twentyMinionsIn3SecondsCount":0.0,"twoWardsOneSweeperCount":0.0,"unseenRecalls":0.0,"visionScoreAdvantageLaneOpponent":0.8196111917495728,"visionScorePerMinute":1.5267244067588976,"voidMonsterKill":1.0,"wardTakedowns":7.0,"wardTakedownsBefore20M":3.0,"wardsGuarded":0.0},"champExperience":14114,"champLevel":15,"championId":268,"championName":"Azir","championTransform":0,"commandPings":12,"consumablesPurchased":5,"damageDealtToBuildings":3464,"damageDealtToObjectives":18023,"damageDealtToTurrets":3464,"damageSelfMitigated":8670,"dangerPings":0,"deaths":1,"detectorWardsPlaced":3,"doubleKills":0,"dragonKills":1,"eligibleForProgression":false,"enemyMissingPings":11,"enemyVisionPings":6,"firstBloodAssist":false,"firstBloodKill":false,"firstTowerAssist":false,"firstTowerKill":false,"gameEndedInEarlySurrender":false,"gameEndedInSurrender":true,"getBackPings":2,"goldEarned":10656,"goldSpent":9375,"holdPings":0,"individualPosition":"AFK","inhibitorKills":0,"inhibitorTakedowns":0,"inhibitorsLost":0,"item0":3089,"item1":2421,"item2":0,"item3":1056,"item4":1001,"item5":3115,"item6":3364,"itemsPurchased":22,"killingSprees":1,"kills":4,"lane":"BOTTOM","largestCriticalStrike":0,"largestKillingSpree":3,"largestMultiKill":1,"longestTimeSpentLiving":1336,"magicDamageDealt":124718,"magicDamageDealtToChampions":15423,"magicDamageTaken":10340,"missions":{"ActMission_S1_A2_ArenaRoundsWon":0,"ActMission_S1_A2_BloodyPetalsCollected":42,"ActMission_S1_A2_FeatsOfStrength":2,"DemonsHand_MissionPointsA":105,"DemonsHand_MissionPointsB":73,"DemonsHand_MissionPointsC":70,"DemonsHand_MissionPointsD":69,"DemonsHand_MissionPointsE":69,"DemonsHand_MissionPointsF":68,"Event_2025LR_StructuresEpicMonsters":5,"Event_S1_A1_AprilFools_Dragon":0,"Event_S1_A1_AprilFools_Snowball":0,"Event_S1_A2_AprilFools_Dragon":0,"Event_S1_A2_AprilFools_Garen_Play":0,"Event_S1_A2_AprilFools_Garen_Takedown":2,"Event_S1_A2_AprilFools_Snowball":0,"Event_S1_A2_Arena_BraveryChampions":0,"Event_S1_A2_Arena_NoxianChampions":0,"Event_S1_A2_Arena_ReviveAllies":0,"Event_S1_A2_Esports_TakedownEpicMonstersSingleGame":0,"Missions_CannonMinionsKilled":11,"Missions_ChampionTakedownsWhileGhosted":0,"Missions_ChampionTakedownsWithIgnite":2,"Missions_ChampionsHitWithAbilitiesEarlyGame":30,"Missions_ChampionsKilled":4,"Missions_CreepScore":216,"Missions_CreepScoreBy10Minutes":1,"Missions_Crepe_DamageDealtSpeedZone":0,"Missions_Crepe_SnowballLanded":0,"Missions_Crepe_TakedownsWithInhibBuff":0,"Missions_DamageToChampsWithItems":694,"Missions_DamageToStructures":3464,"Missions_DestroyPlants":38,"Missions_DominationRune":0,"Missions_GoldFromStructuresDestroyed":1250,"Missions_GoldFromTurretPlatesTaken":125,"Missions_GoldPerMinute":1,"Missions_HealingFromLevelObjects":0,"Missions_HexgatesUsed":0,"Missions_ImmobilizeChampions":6,"Missions_InspirationRune":0,"Missions_LegendaryItems":2,"Missions_MinionsKilled":205,"Missions_PeriodicDamage":0,"Missions_PlaceUsefulControlWards":2,"Missions_PlaceUsefulWards":7,"Missions_PorosFed":0,"Missions_PrecisionRune":1,"Missions_ResolveRune":0,"Missions_SnowballsHit":0,"Missions_SorceryRune":0,"Missions_TakedownBaronsElderDragons":0,"Missions_TakedownDragons":1,"Missions_TakedownEpicMonsters":4,"Missions_TakedownEpicMonstersSingleGame":4,"Missions_TakedownGold":1409,"Missions_TakedownStructures":2,"Missions_TakedownWards":7,"Missions_TakedownsAfterExhausting":6,"Missions_TakedownsAfterTeleporting":2,"Missions_TakedownsBefore15Min":3,"Missions_TakedownsUnderTurret":1,"Missions_TakedownsWithHelpFromMonsters":0,"Missions_TimeSpentActivelyPlaying":25,"Missions_TotalGold":0,"Missions_TrueDamageToStructures":414,"Missions_TurretPlatesDestroyed":1,"Missions_TwoChampsKilledWithSameAbility":0,"Missions_VoidMitesSummoned":6,"PlayerScore0":0.0,"PlayerScore1":0.0,"PlayerScore10":0.0,"PlayerScore11":0.0,"PlayerScore2":0.0,"PlayerScore3":0.0,"PlayerScore4":0.0,"PlayerScore5":0.0,"PlayerScore6":0.0,"PlayerScore7":0.0,"PlayerScore8":0.0,"PlayerScore9":0.0,"SeasonalMissions_TakedownAtakhan":1},"needVisionPings":0,"neutralMinionsKilled":4,"nexusKills":0,"nexusLost":0,"nexusTakedowns":0,"objectivesStolen":0,"objectivesStolenAssists":0,"onMyWayPings":2,"participantId":3,"pentaKills":0,"perks":{"statPerks":{"defense":5011,"flex":5008,"offense":5005},"styles":[{"description":"primaryStyle","selections":[{"perk":8008,"var1":322,"var2":322,"var3":0},{"perk":9101,"var1":1325,"var2":0,"var3":0},{"perk":9104,"var1":17,"var2":10,"var3":0},{"perk":8017,"var1":865,"var2":0,"var3":0}],"style":8000},{"description":"subStyle","selections":[{"perk":8451,"var1":185,"var2":0,"var3":0},{"perk":8473,"var1":856,"var2":0,"var3":0}],"style":8400}]},"physicalDamageDealt":7223,"physicalDamageDealtToChampions":705,"physicalDamageTaken":4096,"placement":0,"playerAugment1":0,"playerAugment2":0,"playerAugment3":0,"playerAugment4":0,"playerAugment5":0,"playerAugment6":0,"playerSubteamId":0,"profileIcon":3463,"pushPings":0,"puuid":"441ab9d1-1ce9-5225-9426-94108f65f662","quadraKills":0,"retreatPings":4,"riotIdGameName":"M8 Eika","riotIdTagline":"eProd","role":"SUPPORT","sightWardsBoughtInGame":0,"spell1Casts":51,"spell1Id":4,"spell2Casts":119,"spell2Id":12,"spell3Casts":13,"spell4Casts":6,"subteamPlacement":0,"summoner1Casts":4,"summoner2Casts":4,"summonerId":3372419579560992,"summonerLevel":30,"summonerName":"","teamEarlySurrendered":false,"teamId":100,"teamPosition":"UTILITY","timeCCingOthers":8,"timePlayed":1508,"totalAllyJungleMinionsKilled":0,"totalDamageDealt":135500,"totalDamageDealtToChampions":16128,"totalDamageShieldedOnTeammates":0,"totalDamageTaken":14668,"totalEnemyJungleMinionsKilled":0,"totalHeal":4511,"totalHealsOnTeammates":0,"totalMinionsKilled":212,"totalTimeCCDealt":118,"totalTimeSpentDead":47,"totalUnitsHealed":1,"tripleKills":0,"trueDamageDealt":3559,"trueDamageDealtToChampions":0,"trueDamageTaken":232,"turretKills":2,"turretTakedowns":2,"turretsLost":1,"unrealKills":0,"visionClearedPings":0,"visionScore":38,"visionWardsBoughtInGame":3,"wardsKilled":7,"wardsPlaced":8,"win":true},{"PlayerScore0":0.0,"PlayerScore1":0.0,"PlayerScore10":0.0,"PlayerScore11":0.0,"PlayerScore2":0.0,"PlayerScore3":0.0,"PlayerScore4":0.0,"PlayerScore5":0.0,"PlayerScore6":0.0,"PlayerScore7":0.0,"PlayerScore8":0.0,"PlayerScore9":0.0,"allInPings":0,"assistMePings":3,"assists":3,"baronKills":0,"basicPings":0,"bountyLevel":6,"challenges":{"12AssistStreakCount":0.0,"HealFromMapSources":930.0,"InfernalScalePickup":0.0,"SWARM_DefeatAatrox":0.0,"SWARM_DefeatBriar":0.0,"SWARM_DefeatMiniBosses":0.0,"SWARM_EvolveWeapon":0.0,"SWARM_Have3Passives":0.0,"SWARM_KillEnemy":0.0,"SWARM_PickupGold":0.0,"SWARM_ReachLevel50":0.0,"SWARM_Survive15Min":0.0,"SWARM_WinWith5EvolvedWeapons":0.0,"abilityUses":237.0,"acesBefore15Minutes":0.0,"alliedJungleMonsterKills":0.0,"baronTakedowns":0.0,"blastConeOppositeOpponentCount":0.0,"bountyGold":0.0,"buffsStolen":1.0,"completeSupportQuestInTime":0.0,"controlWardTimeCoverageInRiverOrEnemyHalf":0.14063353826162833,"controlWardsPlaced":1.0,"damagePerMinute":669.8857540644386,"damageTakenOnTeamPercentage":0.1462833122674988,"dancedWithRiftHerald":0.0,"deathsByEnemyChamps":0.0,"dodgeSkillShotsSmallWindow":0.0,"doubleAces":0.0,"dragonTakedowns":0.0,"earlyLaningPhaseGoldExpAdvantage":0.0,"effectiveHealAndShielding":0.0,"elderDragonKillsWithOpposingSoul":0.0,"elderDragonMultikills":0.0,"enemyChampionImmobilizations":3.0,"enemyJungleMonsterKills":3.0,"epicMonsterKillsNearEnemyJungler":0.0,"epicMonsterKillsWithin30SecondsOfSpawn":0.0,"epicMonsterSteals":0.0,"epicMonsterStolenWithoutSmite":0.0,"firstTurretKilled":1.0,"firstTurretKilledTime":901.8482614870001,"fistBumpParticipation":0.0,"flawlessAces":0.0,"fullTeamTakedown":2.0,"gameLength":1508.899957649,"getTakedownsInAllLanesEarlyJungleAsLaner":0.0,"goldPerMinute":442.8032988663347,"hadOpenNexus":0.0,"highestWardKills":1.0,"immobilizeAndKillWithAlly":0.0,"initialBuffCount":0.0,"initialCrabCount":0.0,"jungleCsBefore10Minutes":0.0,"junglerTakedownsNearDamagedEpicMonster":0.0,"kTurretsDestroyedBeforePlatesFall":0.0,"kda":9.0,"killAfterHiddenWithAlly":0.0,"killParticipation":0.45,"killedChampTookFullTeamDamageSurvived":0.0,"killingSprees":1.0,"killsNearEnemyTurret":1.0,"killsOnOtherLanesEarlyJungleAsLaner":1.0,"killsOnRecentlyHealedByAramPack":0.0,"killsUnderOwnTurret":0.0,"killsWithHelpFromEpicMonster":0.0,"knockEnemyIntoTeamAndKill":0.0,"landSkillShotsEarlyGame":4.0,"laneMinionsFirst10Minutes":70.0,"laningPhaseGoldExpAdvantage":0.0,"legendaryCount":0.0,"legendaryItemUsed":[3153.0,3124.0],"lostAnInhibitor":0.0,"maxCsAdvantageOnLaneOpponent":60.5,"maxKillDeficit":0.0,"maxLevelLeadLaneOpponent":1.0,"mejaisFullStackInTime":0.0,"moreEnemyJungleThanOpponent":0.0,"multiKillOneSpell":0.0,"multiTurretRiftHeraldCount":0.0,"multikills":2.0,"multikillsAfterAggressiveFlash":1.0,"outerTurretExecutesBefore10Minutes":0.0,"outnumberedKills":0.0,"outnumberedNexusKill":0.0,"perfectDragonSoulsTaken":0.0,"perfectGame":0.0,"pickKillWithAlly":7.0,"poroExplosions":0.0,"quickCleanse":0.0,"quickFirstTurret":0.0,"quickSoloKills":0.0,"riftHeraldTakedowns":0.0,"saveAllyFromDeath":0.0,"scuttleCrabKills":1.0,"skillshotsDodged":7.0,"skillshotsHit":21.0,"snowballsHit":0.0,"soloBaronKills":0.0,"soloKills":0.0,"stealthWardsPlaced":3.0,"survivedSingleDigitHpCount":0.0,"survivedThreeImmobilizesInFight":6.0,"takedownOnFirstTurret":0.0,"takedowns":9.0,"takedownsAfterGainingLevelAdvantage":1.0,"takedownsBeforeJungleMinionSpawn":0.0,"takedownsFirstXMinutes":2.0,"takedownsInAlcove":0.0,"takedownsInEnemyFountain":0.0,"teamBaronKills":0.0,"teamDamagePercentage":0.23063677395326634,"teamElderDragonKills":0.0,"teamRiftHeraldKills":1.0,"tookLargeDamageSurvived":0.0,"turretPlatesTaken":0.0,"turretTakedowns":2.0,"turretsTakenWithRiftHerald":5.0,"twentyMinionsIn3SecondsCount":0.0,"twoWardsOneSweeperCount":0.0,"unseenRecalls":0.0,"visionScoreAdvantageLaneOpponent":0.6205753087997437,"visionScorePerMinute":1.1809268554517645,"voidMonsterKill":0.0,"wardTakedowns":10.0,"wardTakedownsBefore20M":6.0,"wardsGuarded":2.0},"champExperience":12722,"champLevel":14,"championId":429,"championName":"Kalista","championTransform":0,"commandPings":2,"consumablesPurchased":3,"damageDealtToBuildings":4315,"damageDealtToObjectives":10815,"damageDealtToTurrets":4315,"damageSelfMitigated":7367,"dangerPings":0,"deaths":0,"detectorWardsPlaced":1,"doubleKills":2,"dragonKills":0,"eligibleForProgression":false,"enemyMissingPings":2,"enemyVisionPings":1,"firstBloodAssist":false,"firstBloodKill":false,"firstTowerAssist":false,"firstTowerKill":false,"gameEndedInEarlySurrender":false,"gameEndedInSurrender":true,"getBackPings":1,"goldEarned":11135,"goldSpent":9375,"holdPings":0,"individualPosition":"AFK","inhibitorKills":0,"inhibitorTakedowns":0,"inhibitorsLost":0,"item0":3006,"item1":3153,"item2":3124,"item3":3051,"item4":1042,"item5":1055,"item6":3364,"itemsPurchased":18,"killingSprees":1,"kills":6,"lane":"BOTTOM","largestCriticalStrike":0,"largestKillingSpree":6,"largestMultiKill":2,"longestTimeSpentLiving":0,"magicDamageDealt":6064,"magicDamageDealtToChampions":1727,"magicDamageTaken":5308,"missions":{"ActMission_S1_A2_ArenaRoundsWon":0,"ActMission_S1_A2_BloodyPetalsCollected":42,"ActMission_S1_A2_FeatsOfStrength":2,"DemonsHand_MissionPointsA":68,"DemonsHand_MissionPointsB":69,"DemonsHand_MissionPointsC":109,"DemonsHand_MissionPointsD":69,"DemonsHand_MissionPointsE":70,"DemonsHand_MissionPointsF":69,"Event_2025LR_StructuresEpicMonsters":3,"Event_S1_A1_AprilFools_Dragon":0,"Event_S1_A1_AprilFools_Snowball":0,"Event_S1_A2_AprilFools_Dragon":0,"Event_S1_A2_AprilFools_Garen_Play":0,"Event_S1_A2_AprilFools_Garen_Takedown":2,"Event_S1_A2_AprilFools_Snowball":0,"Event_S1_A2_Arena_BraveryChampions":0,"Event_S1_A2_Arena_NoxianChampions":0,"Event_S1_A2_Arena_ReviveAllies":0,"Event_S1_A2_Esports_TakedownEpicMonstersSingleGame":0,"Missions_CannonMinionsKilled":14,"Missions_ChampionTakedownsWhileGhosted":0,"Missions_ChampionTakedownsWithIgnite":2,"Missions_ChampionsHitWithAbilitiesEarlyGame":12,"Missions_ChampionsKilled":6,"Missions_CreepScore":248,"Missions_CreepScoreBy10Minutes":1,"Missions_Crepe_DamageDealtSpeedZone":0,"Missions_Crepe_SnowballLanded":0,"Missions_Crepe_TakedownsWithInhibBuff":0,"Missions_DamageToChampsWithItems":1846,"Missions_DamageToStructures":4315,"Missions_DestroyPlants":41,"Missions_DominationRune":0,"Missions_GoldFromStructuresDestroyed":495,"Missions_GoldFromTurretPlatesTaken":0,"Missions_GoldPerMinute":1,"Missions_HealingFromLevelObjects":83,"Missions_HexgatesUsed":0,"Missions_ImmobilizeChampions":3,"Missions_InspirationRune":0,"Missions_LegendaryItems":2,"Missions_MinionsKilled":215,"Missions_PeriodicDamage":32,"Missions_PlaceUsefulControlWards":1,"Missions_PlaceUsefulWards":4,"Missions_PorosFed":0,"Missions_PrecisionRune":1,"Missions_ResolveRune":0,"Missions_SnowballsHit":0,"Missions_SorceryRune":0,"Missions_TakedownBaronsElderDragons":0,"Missions_TakedownDragons":0,"Missions_TakedownEpicMonsters":2,"Missions_TakedownEpicMonstersSingleGame":2,"Missions_TakedownGold":1656,"Missions_TakedownStructures":2,"Missions_TakedownWards":10,"Missions_TakedownsAfterExhausting":3,"Missions_TakedownsAfterTeleporting":3,"Missions_TakedownsBefore15Min":2,"Missions_TakedownsUnderTurret":0,"Missions_TakedownsWithHelpFromMonsters":0,"Missions_TimeSpentActivelyPlaying":25,"Missions_TotalGold":0,"Missions_TrueDamageToStructures":2225,"Missions_TurretPlatesDestroyed":0,"Missions_TwoChampsKilledWithSameAbility":0,"Missions_VoidMitesSummoned":13,"PlayerScore0":0.0,"PlayerScore1":0.0,"PlayerScore10":0.0,"PlayerScore11":0.0,"PlayerScore2":0.0,"PlayerScore3":0.0,"PlayerScore4":0.0,"PlayerScore5":0.0,"PlayerScore6":0.0,"PlayerScore7":0.0,"PlayerScore8":0.0,"PlayerScore9":0.0,"SeasonalMissions_TakedownAtakhan":1},"needVisionPings":0,"neutralMinionsKilled":10,"nexusKills":0,"nexusLost":0,"nexusTakedowns":0,"objectivesStolen":0,"objectivesStolenAssists":0,"onMyWayPings":19,"participantId":4,"pentaKills":0,"perks":{"statPerks":{"defense":5011,"flex":5008,"offense":5005},"styles":[{"description":"primaryStyle","selections":[{"perk":8008,"var1":369,"var2":369,"var3":0},{"perk":9111,"var1":745,"var2":180,"var3":0},{"perk":9104,"var1":18,"var2":10,"var3":0},{"perk":8017,"var1":599,"var2":0,"var3":0}],"style":8000},{"description":"subStyle","selections":[{"perk":8345,"var1":3,"var2":0,"var3":187},{"perk":8347,"var1":0,"var2":0,"var3":0}],"style":8300}]},"physicalDamageDealt":135628,"physicalDamageDealtToChampions":15086,"physicalDamageTaken":7845,"placement":0,"playerAugment1":0,"playerAugment2":0,"playerAugment3":0,"playerAugment4":0,"playerAugment5":0,"playerAugment6":0,"playerSubteamId":0,"profileIcon":22,"pushPings":0,"puuid":"db7d6558-f73c-54aa-97a2-1ba186e8f94e","quadraKills":0,"retreatPings":0,"riotIdGameName":"M8 Comp","riotIdTagline":"eProd","role":"SUPPORT","sightWardsBoughtInGame":0,"spell1Casts":83,"spell1Id":4,"spell2Casts":5,"spell2Id":21,"spell3Casts":144,"spell4Casts":5,"subteamPlacement":0,"summoner1Casts":2,"summoner2Casts":2,"summonerId":3372424562607136,"summonerLevel":30,"summonerName":"","teamEarlySurrendered":false,"teamId":100,"teamPosition":"TOP","timeCCingOthers":13,"timePlayed":1508,"totalAllyJungleMinionsKilled":0,"totalDamageDealt":143952,"totalDamageDealtToChampions":16846,"totalDamageShieldedOnTeammates":0,"totalDamageTaken":13897,"totalEnemyJungleMinionsKilled":6,"totalHeal":8279,"totalHealsOnTeammates":0,"totalMinionsKilled":238,"totalTimeCCDealt":308,"totalTimeSpentDead":0,"totalUnitsHealed":1,"tripleKills":0,"trueDamageDealt":2259,"trueDamageDealtToChampions":32,"trueDamageTaken":743,"turretKills":1,"turretTakedowns":2,"turretsLost":1,"unrealKills":0,"visionClearedPings":0,"visionScore":29,"visionWardsBoughtInGame":1,"wardsKilled":10,"wardsPlaced":4,"win":true},{"PlayerScore0":0.0,"PlayerScore1":0.0,"PlayerScore10":0.0,"PlayerScore11":0.0,"PlayerScore2":0.0,"PlayerScore3":0.0,"PlayerScore4":0.0,"PlayerScore5":0.0,"PlayerScore6":0.0,"PlayerScore7":0.0,"PlayerScore8":0.0,"PlayerScore9":0.0,"allInPings":0,"assistMePings":0,"assists":14,"baronKills":0,"basicPings":0,"bountyLevel":0,"challenges":{"12AssistStreakCount":1.0,"HealFromMapSources":578.7667999267578,"InfernalScalePickup":0.0,"SWARM_DefeatAatrox":0.0,"SWARM_DefeatBriar":0.0,"SWARM_DefeatMiniBosses":0.0,"SWARM_EvolveWeapon":0.0,"SWARM_Have3Passives":0.0,"SWARM_KillEnemy":0.0,"SWARM_PickupGold":0.0,"SWARM_ReachLevel50":0.0,"SWARM_Survive15Min":0.0,"SWARM_WinWith5EvolvedWeapons":0.0,"abilityUses":136.0,"acesBefore15Minutes":0.0,"alliedJungleMonsterKills":0.0,"baronTakedowns":0.0,"blastConeOppositeOpponentCount":0.0,"bountyGold":0.0,"buffsStolen":0.0,"completeSupportQuestInTime":1.0,"controlWardTimeCoverageInRiverOrEnemyHalf":0.6421431303130781,"controlWardsPlaced":9.0,"damagePerMinute":369.1973690550254,"damageTakenOnTeamPercentage":0.11788022779430751,"dancedWithRiftHerald":0.0,"deathsByEnemyChamps":1.0,"dodgeSkillShotsSmallWindow":0.0,"doubleAces":0.0,"dragonTakedowns":0.0,"earlyLaningPhaseGoldExpAdvantage":1.0,"effectiveHealAndShielding":1345.8494873046875,"elderDragonKillsWithOpposingSoul":0.0,"elderDragonMultikills":0.0,"enemyChampionImmobilizations":96.0,"enemyJungleMonsterKills":0.0,"epicMonsterKillsNearEnemyJungler":0.0,"epicMonsterKillsWithin30SecondsOfSpawn":0.0,"epicMonsterSteals":0.0,"epicMonsterStolenWithoutSmite":0.0,"fasterSupportQuestCompletion":1.0,"firstTurretKilled":1.0,"firstTurretKilledTime":901.8482614870001,"fistBumpParticipation":0.0,"flawlessAces":0.0,"fullTeamTakedown":2.0,"gameLength":1508.899957649,"goldPerMinute":257.0145658843852,"hadOpenNexus":0.0,"highestCrowdControlScore":1.0,"immobilizeAndKillWithAlly":7.0,"initialBuffCount":0.0,"initialCrabCount":0.0,"jungleCsBefore10Minutes":0.0,"junglerKillsEarlyJungle":0.0,"junglerTakedownsNearDamagedEpicMonster":0.0,"kTurretsDestroyedBeforePlatesFall":0.0,"kda":14.0,"killAfterHiddenWithAlly":0.0,"killParticipation":0.7,"killedChampTookFullTeamDamageSurvived":0.0,"killingSprees":0.0,"killsNearEnemyTurret":0.0,"killsOnLanersEarlyJungleAsJungler":0.0,"killsOnRecentlyHealedByAramPack":0.0,"killsUnderOwnTurret":0.0,"killsWithHelpFromEpicMonster":0.0,"knockEnemyIntoTeamAndKill":3.0,"landSkillShotsEarlyGame":4.0,"laneMinionsFirst10Minutes":13.0,"laningPhaseGoldExpAdvantage":0.0,"legendaryCount":0.0,"legendaryItemUsed":[3877.0,3190.0],"lostAnInhibitor":0.0,"maxCsAdvantageOnLaneOpponent":9.0,"maxKillDeficit":0.0,"maxLevelLeadLaneOpponent":1.0,"mejaisFullStackInTime":0.0,"moreEnemyJungleThanOpponent":0.0,"multiKillOneSpell":0.0,"multiTurretRiftHeraldCount":0.0,"multikills":0.0,"multikillsAfterAggressiveFlash":0.0,"outerTurretExecutesBefore10Minutes":0.0,"outnumberedKills":0.0,"outnumberedNexusKill":0.0,"perfectDragonSoulsTaken":0.0,"perfectGame":0.0,"pickKillWithAlly":9.0,"poroExplosions":0.0,"quickCleanse":0.0,"quickFirstTurret":0.0,"quickSoloKills":0.0,"riftHeraldTakedowns":0.0,"saveAllyFromDeath":1.0,"scuttleCrabKills":0.0,"skillshotsDodged":6.0,"skillshotsHit":20.0,"snowballsHit":0.0,"soloBaronKills":0.0,"soloKills":0.0,"stealthWardsPlaced":32.0,"survivedSingleDigitHpCount":0.0,"survivedThreeImmobilizesInFight":4.0,"takedownOnFirstTurret":0.0,"takedowns":14.0,"takedownsAfterGainingLevelAdvantage":0.0,"takedownsBeforeJungleMinionSpawn":0.0,"takedownsFirstXMinutes":3.0,"takedownsInAlcove":0.0,"takedownsInEnemyFountain":0.0,"teamBaronKills":0.0,"teamDamagePercentage":0.12711195847089712,"teamElderDragonKills":0.0,"teamRiftHeraldKills":1.0,"tookLargeDamageSurvived":0.0,"turretPlatesTaken":0.0,"turretTakedowns":2.0,"turretsTakenWithRiftHerald":5.0,"twentyMinionsIn3SecondsCount":0.0,"twoWardsOneSweeperCount":0.0,"unseenRecalls":0.0,"visionScoreAdvantageLaneOpponent":0.032666563987731934,"visionScorePerMinute":2.8681602476573382,"voidMonsterKill":0.0,"wardTakedowns":5.0,"wardTakedownsBefore20M":3.0,"wardsGuarded":2.0},"champExperience":8118,"champLevel":11,"championId":111,"championName":"Nautilus","championTransform":0,"commandPings":22,"consumablesPurchased":11,"damageDealtToBuildings":756,"damageDealtToObjectives":856,"damageDealtToTurrets":756,"damageSelfMitigated":18966,"dangerPings":0,"deaths":1,"detectorWardsPlaced":9,"doubleKills":0,"dragonKills":0,"eligibleForProgression":false,"enemyMissingPings":2,"enemyVisionPings":5,"firstBloodAssist":false,"firstBloodKill":false,"firstTowerAssist":false,"firstTowerKill":false,"gameEndedInEarlySurrender":false,"gameEndedInSurrender":true,"getBackPings":0,"goldEarned":6463,"goldSpent":5775,"holdPings":0,"individualPosition":"AFK","inhibitorKills":0,"inhibitorTakedowns":0,"inhibitorsLost":0,"item0":3190,"item1":3877,"item2":3047,"item3":1028,"item4":1031,"item5":0,"item6":3364,"itemsPurchased":39,"killingSprees":0,"kills":0,"lane":"BOTTOM","largestCriticalStrike":0,"largestKillingSpree":0,"largestMultiKill":0,"longestTimeSpentLiving":1172,"magicDamageDealt":8962,"magicDamageDealtToChampions":5802,"magicDamageTaken":3988,"missions":{"ActMission_S1_A2_ArenaRoundsWon":0,"ActMission_S1_A2_BloodyPetalsCollected":42,"ActMission_S1_A2_FeatsOfStrength":2,"DemonsHand_MissionPointsA":98,"DemonsHand_MissionPointsB":73,"DemonsHand_MissionPointsC":69,"DemonsHand_MissionPointsD":77,"DemonsHand_MissionPointsE":69,"DemonsHand_MissionPointsF":68,"Event_2025LR_StructuresEpicMonsters":2,"Event_S1_A1_AprilFools_Dragon":0,"Event_S1_A1_AprilFools_Snowball":0,"Event_S1_A2_AprilFools_Dragon":0,"Event_S1_A2_AprilFools_Garen_Play":0,"Event_S1_A2_AprilFools_Garen_Takedown":2,"Event_S1_A2_AprilFools_Snowball":0,"Event_S1_A2_Arena_BraveryChampions":0,"Event_S1_A2_Arena_NoxianChampions":0,"Event_S1_A2_Arena_ReviveAllies":0,"Event_S1_A2_Esports_TakedownEpicMonstersSingleGame":0,"Missions_CannonMinionsKilled":3,"Missions_ChampionTakedownsWhileGhosted":0,"Missions_ChampionTakedownsWithIgnite":2,"Missions_ChampionsHitWithAbilitiesEarlyGame":20,"Missions_ChampionsKilled":0,"Missions_CreepScore":20,"Missions_CreepScoreBy10Minutes":0,"Missions_Crepe_DamageDealtSpeedZone":0,"Missions_Crepe_SnowballLanded":0,"Missions_Crepe_TakedownsWithInhibBuff":0,"Missions_DamageToChampsWithItems":1036,"Missions_DamageToStructures":756,"Missions_DestroyPlants":22,"Missions_DominationRune":0,"Missions_GoldFromStructuresDestroyed":495,"Missions_GoldFromTurretPlatesTaken":0,"Missions_GoldPerMinute":0,"Missions_HealingFromLevelObjects":578,"Missions_HexgatesUsed":0,"Missions_ImmobilizeChampions":69,"Missions_InspirationRune":0,"Missions_LegendaryItems":2,"Missions_MinionsKilled":15,"Missions_PeriodicDamage":746,"Missions_PlaceUsefulControlWards":8,"Missions_PlaceUsefulWards":38,"Missions_PorosFed":0,"Missions_PrecisionRune":0,"Missions_ResolveRune":1,"Missions_SnowballsHit":0,"Missions_SorceryRune":0,"Missions_TakedownBaronsElderDragons":0,"Missions_TakedownDragons":0,"Missions_TakedownEpicMonsters":0,"Missions_TakedownEpicMonstersSingleGame":0,"Missions_TakedownGold":1027,"Missions_TakedownStructures":2,"Missions_TakedownWards":5,"Missions_TakedownsAfterExhausting":14,"Missions_TakedownsAfterTeleporting":4,"Missions_TakedownsBefore15Min":3,"Missions_TakedownsUnderTurret":0,"Missions_TakedownsWithHelpFromMonsters":0,"Missions_TimeSpentActivelyPlaying":25,"Missions_TotalGold":0,"Missions_TrueDamageToStructures":330,"Missions_TurretPlatesDestroyed":0,"Missions_TwoChampsKilledWithSameAbility":0,"Missions_VoidMitesSummoned":2,"PlayerScore0":0.0,"PlayerScore1":0.0,"PlayerScore10":0.0,"PlayerScore11":0.0,"PlayerScore2":0.0,"PlayerScore3":0.0,"PlayerScore4":0.0,"PlayerScore5":0.0,"PlayerScore6":0.0,"PlayerScore7":0.0,"PlayerScore8":0.0,"PlayerScore9":0.0,"SeasonalMissions_TakedownAtakhan":0},"needVisionPings":0,"neutralMinionsKilled":0,"nexusKills":0,"nexusLost":0,"nexusTakedowns":0,"objectivesStolen":0,"objectivesStolenAssists":0,"onMyWayPings":32,"participantId":5,"pentaKills":0,"perks":{"statPerks":{"defense":5011,"flex":5010,"offense":5007},"styles":[{"description":"primaryStyle","selections":[{"perk":8439,"var1":477,"var2":1271,"var3":0},{"perk":8401,"var1":653,"var2":0,"var3":0},{"perk":8473,"var1":431,"var2":0,"var3":0},{"perk":8451,"var1":146,"var2":0,"var3":0}],"style":8400},{"description":"subStyle","selections":[{"perk":8143,"var1":562,"var2":0,"var3":0},{"perk":8106,"var1":5,"var2":31,"var3":0}],"style":8100}]},"physicalDamageDealt":5832,"physicalDamageDealtToChampions":2329,"physicalDamageTaken":6262,"placement":0,"playerAugment1":0,"playerAugment2":0,"playerAugment3":0,"playerAugment4":0,"playerAugment5":0,"playerAugment6":0,"playerSubteamId":0,"profileIcon":567,"pushPings":0,"puuid":"9219250b-bb29-5a96-bffb-77b9efea5187","quadraKills":0,"retreatPings":9,"riotIdGameName":"M8 Erdote","riotIdTagline":"eProd","role":"SUPPORT","sightWardsBoughtInGame":0,"spell1Casts":68,"spell1Id":14,"spell2Casts":35,"spell2Id":4,"spell3Casts":25,"spell4Casts":8,"subteamPlacement":0,"summoner1Casts":5,"summoner2Casts":4,"summonerId":3373249013810208,"summonerLevel":30,"summonerName":"","teamEarlySurrendered":false,"teamId":100,"teamPosition":"JUNGLE","timeCCingOthers":54,"timePlayed":1508,"totalAllyJungleMinionsKilled":0,"totalDamageDealt":19465,"totalDamageDealtToChampions":9284,"totalDamageShieldedOnTeammates":1345,"totalDamageTaken":11199,"totalEnemyJungleMinionsKilled":0,"totalHeal":2722,"totalHealsOnTeammates":0,"totalMinionsKilled":20,"totalTimeCCDealt":223,"totalTimeSpentDead":29,"totalUnitsHealed":1,"tripleKills":0,"trueDamageDealt":4671,"trueDamageDealtToChampions":1152,"trueDamageTaken":947,"turretKills":1,"turretTakedowns":2,"turretsLost":1,"unrealKills":0,"visionClearedPings":0,"visionScore":72,"visionWardsBoughtInGame":9,"wardsKilled":5,"wardsPlaced":42,"win":true},{"PlayerScore0":0.0,"PlayerScore1":0.0,"PlayerScore10":0.0,"PlayerScore11":0.0,"PlayerScore2":0.0,"PlayerScore3":0.0,"PlayerScore4":0.0,"PlayerScore5":0.0,"PlayerScore6":0.0,"PlayerScore7":0.0,"PlayerScore8":0.0,"PlayerScore9":0.0,"allInPings":2,"assistMePings":0,"assists":2,"baronKills":0,"basicPings":0,"bountyLevel":1,"challenges":{"12AssistStreakCount":0.0,"HealFromMapSources":818.6578521728516,"InfernalScalePickup":0.0,"SWARM_DefeatAatrox":0.0,"SWARM_DefeatBriar":0.0,"SWARM_DefeatMiniBosses":0.0,"SWARM_EvolveWeapon":0.0,"SWARM_Have3Passives":0.0,"SWARM_KillEnemy":0.0,"SWARM_PickupGold":0.0,"SWARM_ReachLevel50":0.0,"SWARM_Survive15Min":0.0,"SWARM_WinWith5EvolvedWeapons":0.0,"abilityUses":265.0,"acesBefore15Minutes":0.0,"alliedJungleMonsterKills":0.0,"baronTakedowns":0.0,"blastConeOppositeOpponentCount":0.0,"bountyGold":107.87519836425781,"buffsStolen":0.0,"completeSupportQuestInTime":0.0,"controlWardsPlaced":0.0,"damagePerMinute":686.5072120082623,"damageTakenOnTeamPercentage":0.2364056217776822,"dancedWithRiftHerald":0.0,"deathsByEnemyChamps":3.0,"dodgeSkillShotsSmallWindow":0.0,"doubleAces":0.0,"dragonTakedowns":0.0,"earlyLaningPhaseGoldExpAdvantage":0.0,"effectiveHealAndShielding":0.0,"elderDragonKillsWithOpposingSoul":0.0,"elderDragonMultikills":0.0,"enemyChampionImmobilizations":6.0,"enemyJungleMonsterKills":0.0,"epicMonsterKillsNearEnemyJungler":0.0,"epicMonsterKillsWithin30SecondsOfSpawn":0.0,"epicMonsterSteals":0.0,"epicMonsterStolenWithoutSmite":0.0,"firstTurretKilled":0.0,"fistBumpParticipation":0.0,"flawlessAces":0.0,"fullTeamTakedown":0.0,"gameLength":1508.899957649,"goldPerMinute":356.0923516839202,"hadOpenNexus":0.0,"immobilizeAndKillWithAlly":1.0,"initialBuffCount":0.0,"initialCrabCount":0.0,"jungleCsBefore10Minutes":0.0,"junglerTakedownsNearDamagedEpicMonster":1.0,"kTurretsDestroyedBeforePlatesFall":0.0,"kda":1.0,"killAfterHiddenWithAlly":0.0,"killParticipation":0.5,"killedChampTookFullTeamDamageSurvived":0.0,"killingSprees":0.0,"killsNearEnemyTurret":0.0,"killsOnRecentlyHealedByAramPack":0.0,"killsUnderOwnTurret":0.0,"killsWithHelpFromEpicMonster":1.0,"knockEnemyIntoTeamAndKill":0.0,"landSkillShotsEarlyGame":0.0,"laneMinionsFirst10Minutes":94.0,"laningPhaseGoldExpAdvantage":0.0,"legendaryCount":0.0,"legendaryItemUsed":[6692.0,6610.0],"lostAnInhibitor":0.0,"maxCsAdvantageOnLaneOpponent":13.0,"maxKillDeficit":0.0,"maxLevelLeadLaneOpponent":1.0,"mejaisFullStackInTime":0.0,"moreEnemyJungleThanOpponent":0.0,"multiKillOneSpell":0.0,"multiTurretRiftHeraldCount":0.0,"multikills":0.0,"multikillsAfterAggressiveFlash":0.0,"outerTurretExecutesBefore10Minutes":0.0,"outnumberedKills":0.0,"outnumberedNexusKill":0.0,"perfectDragonSoulsTaken":0.0,"perfectGame":0.0,"pickKillWithAlly":3.0,"poroExplosions":0.0,"quickCleanse":0.0,"quickFirstTurret":0.0,"quickSoloKills":0.0,"riftHeraldTakedowns":0.0,"saveAllyFromDeath":0.0,"scuttleCrabKills":0.0,"skillshotsDodged":10.0,"skillshotsHit":0.0,"snowballsHit":0.0,"soloBaronKills":0.0,"soloKills":0.0,"soloTurretsLategame":1.0,"stealthWardsPlaced":4.0,"survivedSingleDigitHpCount":0.0,"survivedThreeImmobilizesInFight":4.0,"takedownOnFirstTurret":0.0,"takedowns":3.0,"takedownsAfterGainingLevelAdvantage":0.0,"takedownsBeforeJungleMinionSpawn":0.0,"takedownsFirstXMinutes":1.0,"takedownsInAlcove":0.0,"takedownsInEnemyFountain":0.0,"teamBaronKills":0.0,"teamDamagePercentage":0.2587807174533006,"teamElderDragonKills":0.0,"teamRiftHeraldKills":0.0,"tookLargeDamageSurvived":0.0,"turretPlatesTaken":0.0,"turretTakedowns":2.0,"turretsTakenWithRiftHerald":0.0,"twentyMinionsIn3SecondsCount":0.0,"twoWardsOneSweeperCount":0.0,"unseenRecalls":0.0,"visionScoreAdvantageLaneOpponent":-0.4542311429977417,"visionScorePerMinute":0.6620719388123659,"voidMonsterKill":0.0,"wardTakedowns":5.0,"wardTakedownsBefore20M":2.0,"wardsGuarded":1.0},"champExperience":12921,"champLevel":14,"championId":799,"championName":"Ambessa","championTransform":0,"commandPings":1,"consumablesPurchased":1,"damageDealtToBuildings":4062,"damageDealtToObjectives":4062,"damageDealtToTurrets":4062,"damageSelfMitigated":26870,"dangerPings":0,"deaths":3,"detectorWardsPlaced":0,"doubleKills":0,"dragonKills":0,"eligibleForProgression":false,"enemyMissingPings":5,"enemyVisionPings":1,"firstBloodAssist":false,"firstBloodKill":false,"firstTowerAssist":false,"firstTowerKill":false,"gameEndedInEarlySurrender":false,"gameEndedInSurrender":true,"getBackPings":6,"goldEarned":8955,"goldSpent":8700,"holdPings":0,"individualPosition":"AFK","inhibitorKills":0,"inhibitorTakedowns":0,"inhibitorsLost":0,"item0":6692,"item1":2031,"item2":1054,"item3":3047,"item4":6610,"item5":2021,"item6":3364,"itemsPurchased":15,"killingSprees":0,"kills":1,"lane":"JUNGLE","largestCriticalStrike":246,"largestKillingSpree":0,"largestMultiKill":1,"longestTimeSpentLiving":892,"magicDamageDealt":885,"magicDamageDealtToChampions":885,"magicDamageTaken":10016,"missions":{"ActMission_S1_A2_ArenaRoundsWon":0,"ActMission_S1_A2_BloodyPetalsCollected":20,"ActMission_S1_A2_FeatsOfStrength":0,"DemonsHand_MissionPointsA":80,"DemonsHand_MissionPointsB":68,"DemonsHand_MissionPointsC":72,"DemonsHand_MissionPointsD":76,"DemonsHand_MissionPointsE":70,"DemonsHand_MissionPointsF":87,"Event_2025LR_StructuresEpicMonsters":1,"Event_S1_A1_AprilFools_Dragon":0,"Event_S1_A1_AprilFools_Snowball":0,"Event_S1_A2_AprilFools_Dragon":0,"Event_S1_A2_AprilFools_Garen_Play":0,"Event_S1_A2_AprilFools_Garen_Takedown":0,"Event_S1_A2_AprilFools_Snowball":0,"Event_S1_A2_Arena_BraveryChampions":0,"Event_S1_A2_Arena_NoxianChampions":0,"Event_S1_A2_Arena_ReviveAllies":0,"Event_S1_A2_Esports_TakedownEpicMonstersSingleGame":0,"Missions_CannonMinionsKilled":12,"Missions_ChampionTakedownsWhileGhosted":0,"Missions_ChampionTakedownsWithIgnite":0,"Missions_ChampionsHitWithAbilitiesEarlyGame":26,"Missions_ChampionsKilled":1,"Missions_CreepScore":224,"Missions_CreepScoreBy10Minutes":1,"Missions_Crepe_DamageDealtSpeedZone":0,"Missions_Crepe_SnowballLanded":0,"Missions_Crepe_TakedownsWithInhibBuff":0,"Missions_DamageToChampsWithItems":918,"Missions_DamageToStructures":4062,"Missions_DestroyPlants":15,"Missions_DominationRune":0,"Missions_GoldFromStructuresDestroyed":300,"Missions_GoldFromTurretPlatesTaken":0,"Missions_GoldPerMinute":0,"Missions_HealingFromLevelObjects":818,"Missions_HexgatesUsed":0,"Missions_ImmobilizeChampions":5,"Missions_InspirationRune":0,"Missions_LegendaryItems":2,"Missions_MinionsKilled":219,"Missions_PeriodicDamage":0,"Missions_PlaceUsefulControlWards":0,"Missions_PlaceUsefulWards":4,"Missions_PorosFed":0,"Missions_PrecisionRune":0,"Missions_ResolveRune":1,"Missions_SnowballsHit":0,"Missions_SorceryRune":0,"Missions_TakedownBaronsElderDragons":0,"Missions_TakedownDragons":0,"Missions_TakedownEpicMonsters":0,"Missions_TakedownEpicMonstersSingleGame":0,"Missions_TakedownGold":572,"Missions_TakedownStructures":1,"Missions_TakedownWards":4,"Missions_TakedownsAfterExhausting":2,"Missions_TakedownsAfterTeleporting":2,"Missions_TakedownsBefore15Min":1,"Missions_TakedownsUnderTurret":1,"Missions_TakedownsWithHelpFromMonsters":1,"Missions_TimeSpentActivelyPlaying":25,"Missions_TotalGold":0,"Missions_TrueDamageToStructures":168,"Missions_TurretPlatesDestroyed":0,"Missions_TwoChampsKilledWithSameAbility":0,"Missions_VoidMitesSummoned":0,"PlayerScore0":0.0,"PlayerScore1":0.0,"PlayerScore10":0.0,"PlayerScore11":0.0,"PlayerScore2":0.0,"PlayerScore3":0.0,"PlayerScore4":0.0,"PlayerScore5":0.0,"PlayerScore6":0.0,"PlayerScore7":0.0,"PlayerScore8":0.0,"PlayerScore9":0.0,"SeasonalMissions_TakedownAtakhan":0},"needVisionPings":0,"neutralMinionsKilled":0,"nexusKills":0,"nexusLost":1,"nexusTakedowns":0,"objectivesStolen":0,"objectivesStolenAssists":0,"onMyWayPings":5,"participantId":6,"pentaKills":0,"perks":{"statPerks":{"defense":5001,"flex":5008,"offense":5008},"styles":[{"description":"primaryStyle","selections":[{"perk":8437,"var1":885,"var2":586,"var3":0},{"perk":8401,"var1":877,"var2":0,"var3":0},{"perk":8473,"var1":806,"var2":0,"var3":0},{"perk":8451,"var1":206,"var2":0,"var3":0}],"style":8400},{"description":"subStyle","selections":[{"perk":8304,"var1":11,"var2":1,"var3":5},{"perk":8345,"var1":3,"var2":0,"var3":267}],"style":8300}]},"physicalDamageDealt":118847,"physicalDamageDealtToChampions":16378,"physicalDamageTaken":9917,"placement":0,"playerAugment1":0,"playerAugment2":0,"playerAugment3":0,"playerAugment4":0,"playerAugment5":0,"playerAugment6":0,"playerSubteamId":0,"profileIcon":4070,"pushPings":0,"puuid":"235cd3e9-ccfb-5d29-8724-8ed78b41fff7","quadraKills":0,"retreatPings":0,"riotIdGameName":"BKR Szygenda","riotIdTagline":"eProd","role":"NONE","sightWardsBoughtInGame":0,"spell1Casts":150,"spell1Id":12,"spell2Casts":44,"spell2Id":4,"spell3Casts":66,"spell4Casts":5,"subteamPlacement":0,"summoner1Casts":4,"summoner2Casts":3,"summonerId":3372422387786784,"summonerLevel":30,"summonerName":"","teamEarlySurrendered":false,"teamId":200,"teamPosition":"AFK","timeCCingOthers":6,"timePlayed":1508,"totalAllyJungleMinionsKilled":0,"totalDamageDealt":119906,"totalDamageDealtToChampions":17264,"totalDamageShieldedOnTeammates":0,"totalDamageTaken":20260,"totalEnemyJungleMinionsKilled":0,"totalHeal":5076,"totalHealsOnTeammates":0,"totalMinionsKilled":224,"totalTimeCCDealt":169,"totalTimeSpentDead":117,"totalUnitsHealed":1,"tripleKills":0,"trueDamageDealt":173,"trueDamageDealtToChampions":0,"trueDamageTaken":327,"turretKills":2,"turretTakedowns":2,"turretsLost":5,"unrealKills":0,"visionClearedPings":0,"visionScore":16,"visionWardsBoughtInGame":0,"wardsKilled":4,"wardsPlaced":4,"win":false},{"PlayerScore0":0.0,"PlayerScore1":0.0,"PlayerScore10":0.0,"PlayerScore11":0.0,"PlayerScore2":0.0,"PlayerScore3":0.0,"PlayerScore4":0.0,"PlayerScore5":0.0,"PlayerScore6":0.0,"PlayerScore7":0.0,"PlayerScore8":0.0,"PlayerScore9":0.0,"allInPings":0,"assistMePings":0,"assists":1,"baronKills":0,"basicPings":0,"bountyLevel":1,"challenges":{"12AssistStreakCount":0.0,"HealFromMapSources":492.0,"InfernalScalePickup":0.0,"SWARM_DefeatAatrox":0.0,"SWARM_DefeatBriar":0.0,"SWARM_DefeatMiniBosses":0.0,"SWARM_EvolveWeapon":0.0,"SWARM_Have3Passives":0.0,"SWARM_KillEnemy":0.0,"SWARM_PickupGold":0.0,"SWARM_ReachLevel50":0.0,"SWARM_Survive15Min":0.0,"SWARM_WinWith5EvolvedWeapons":0.0,"abilityUses":314.0,"acesBefore15Minutes":0.0,"alliedJungleMonsterKills":89.0,"baronTakedowns":0.0,"blastConeOppositeOpponentCount":0.0,"bountyGold":0.0,"buffsStolen":0.0,"completeSupportQuestInTime":0.0,"controlWardTimeCoverageInRiverOrEnemyHalf":0.7531126213003331,"controlWardsPlaced":6.0,"damagePerMinute":519.9674914191751,"damageTakenOnTeamPercentage":0.1616827110962014,"dancedWithRiftHerald":0.0,"deathsByEnemyChamps":2.0,"dodgeSkillShotsSmallWindow":0.0,"doubleAces":0.0,"dragonTakedowns":2.0,"earliestDragonTakedown":408.44302701400005,"earlyLaningPhaseGoldExpAdvantage":0.0,"effectiveHealAndShielding":0.0,"elderDragonKillsWithOpposingSoul":0.0,"elderDragonMultikills":0.0,"enemyChampionImmobilizations":17.0,"enemyJungleMonsterKills":0.0,"epicMonsterKillsNearEnemyJungler":2.0,"epicMonsterKillsWithin30SecondsOfSpawn":0.0,"epicMonsterSteals":0.0,"epicMonsterStolenWithoutSmite":0.0,"firstTurretKilled":0.0,"fistBumpParticipation":0.0,"flawlessAces":0.0,"fullTeamTakedown":0.0,"gameLength":1508.899957649,"getTakedownsInAllLanesEarlyJungleAsLaner":0.0,"goldPerMinute":318.8391674419495,"hadOpenNexus":0.0,"highestWardKills":1.0,"immobilizeAndKillWithAlly":1.0,"initialBuffCount":1.0,"initialCrabCount":2.0,"jungleCsBefore10Minutes":71.75000008940697,"junglerTakedownsNearDamagedEpicMonster":0.0,"kTurretsDestroyedBeforePlatesFall":0.0,"kda":1.0,"killAfterHiddenWithAlly":0.0,"killParticipation":0.3333333333333333,"killedChampTookFullTeamDamageSurvived":0.0,"killingSprees":0.0,"killsNearEnemyTurret":0.0,"killsOnOtherLanesEarlyJungleAsLaner":0.0,"killsOnRecentlyHealedByAramPack":0.0,"killsUnderOwnTurret":0.0,"killsWithHelpFromEpicMonster":0.0,"knockEnemyIntoTeamAndKill":0.0,"landSkillShotsEarlyGame":1.0,"laneMinionsFirst10Minutes":1.0,"laningPhaseGoldExpAdvantage":0.0,"legendaryCount":0.0,"legendaryItemUsed":[6653.0],"lostAnInhibitor":0.0,"maxCsAdvantageOnLaneOpponent":24.750000029802322,"maxKillDeficit":0.0,"maxLevelLeadLaneOpponent":1.0,"mejaisFullStackInTime":0.0,"moreEnemyJungleThanOpponent":0.0,"multiKillOneSpell":0.0,"multiTurretRiftHeraldCount":0.0,"multikills":0.0,"multikillsAfterAggressiveFlash":0.0,"outerTurretExecutesBefore10Minutes":0.0,"outnumberedKills":0.0,"outnumberedNexusKill":0.0,"perfectDragonSoulsTaken":0.0,"perfectGame":0.0,"pickKillWithAlly":2.0,"poroExplosions":0.0,"quickCleanse":0.0,"quickFirstTurret":0.0,"quickSoloKills":0.0,"riftHeraldTakedowns":0.0,"saveAllyFromDeath":0.0,"scuttleCrabKills":3.0,"skillshotsDodged":15.0,"skillshotsHit":12.0,"snowballsHit":0.0,"soloBaronKills":0.0,"soloKills":0.0,"stealthWardsPlaced":1.0,"survivedSingleDigitHpCount":0.0,"survivedThreeImmobilizesInFight":4.0,"takedownOnFirstTurret":0.0,"takedowns":2.0,"takedownsAfterGainingLevelAdvantage":0.0,"takedownsBeforeJungleMinionSpawn":0.0,"takedownsFirstXMinutes":1.0,"takedownsInAlcove":0.0,"takedownsInEnemyFountain":0.0,"teamBaronKills":0.0,"teamDamagePercentage":0.1960031273207187,"teamElderDragonKills":0.0,"teamRiftHeraldKills":0.0,"tookLargeDamageSurvived":0.0,"turretPlatesTaken":2.0,"turretTakedowns":0.0,"turretsTakenWithRiftHerald":0.0,"twentyMinionsIn3SecondsCount":0.0,"twoWardsOneSweeperCount":0.0,"unseenRecalls":0.0,"visionScoreAdvantageLaneOpponent":0.11942553520202637,"visionScorePerMinute":1.578112013293814,"voidMonsterKill":1.0,"wardTakedowns":10.0,"wardTakedownsBefore20M":6.0,"wardsGuarded":2.0},"champExperience":9910,"champLevel":12,"championId":143,"championName":"Zyra","championTransform":0,"commandPings":20,"consumablesPurchased":7,"damageDealtToBuildings":326,"damageDealtToObjectives":11278,"damageDealtToTurrets":326,"damageSelfMitigated":6229,"dangerPings":0,"deaths":2,"detectorWardsPlaced":6,"doubleKills":0,"dragonKills":2,"eligibleForProgression":false,"enemyMissingPings":6,"enemyVisionPings":20,"firstBloodAssist":false,"firstBloodKill":false,"firstTowerAssist":false,"firstTowerKill":false,"gameEndedInEarlySurrender":false,"gameEndedInSurrender":true,"getBackPings":2,"goldEarned":8018,"goldSpent":7875,"holdPings":0,"individualPosition":"AFK","inhibitorKills":0,"inhibitorTakedowns":0,"inhibitorsLost":0,"item0":2055,"item1":3020,"item2":2420,"item3":0,"item4":1058,"item5":6653,"item6":3364,"itemsPurchased":19,"killingSprees":0,"kills":1,"lane":"JUNGLE","largestCriticalStrike":0,"largestKillingSpree":0,"largestMultiKill":1,"longestTimeSpentLiving":1101,"magicDamageDealt":121473,"magicDamageDealtToChampions":10898,"magicDamageTaken":6721,"missions":{"ActMission_S1_A2_ArenaRoundsWon":0,"ActMission_S1_A2_BloodyPetalsCollected":20,"ActMission_S1_A2_FeatsOfStrength":0,"DemonsHand_MissionPointsA":71,"DemonsHand_MissionPointsB":82,"DemonsHand_MissionPointsC":71,"DemonsHand_MissionPointsD":70,"DemonsHand_MissionPointsE":83,"DemonsHand_MissionPointsF":76,"Event_2025LR_StructuresEpicMonsters":3,"Event_S1_A1_AprilFools_Dragon":0,"Event_S1_A1_AprilFools_Snowball":0,"Event_S1_A2_AprilFools_Dragon":0,"Event_S1_A2_AprilFools_Garen_Play":0,"Event_S1_A2_AprilFools_Garen_Takedown":0,"Event_S1_A2_AprilFools_Snowball":0,"Event_S1_A2_Arena_BraveryChampions":0,"Event_S1_A2_Arena_NoxianChampions":0,"Event_S1_A2_Arena_ReviveAllies":0,"Event_S1_A2_Esports_TakedownEpicMonstersSingleGame":0,"Missions_CannonMinionsKilled":0,"Missions_ChampionTakedownsWhileGhosted":0,"Missions_ChampionTakedownsWithIgnite":0,"Missions_ChampionsHitWithAbilitiesEarlyGame":8,"Missions_ChampionsKilled":1,"Missions_CreepScore":172,"Missions_CreepScoreBy10Minutes":1,"Missions_Crepe_DamageDealtSpeedZone":0,"Missions_Crepe_SnowballLanded":0,"Missions_Crepe_TakedownsWithInhibBuff":0,"Missions_DamageToChampsWithItems":2822,"Missions_DamageToStructures":326,"Missions_DestroyPlants":17,"Missions_DominationRune":1,"Missions_GoldFromStructuresDestroyed":133,"Missions_GoldFromTurretPlatesTaken":83,"Missions_GoldPerMinute":0,"Missions_HealingFromLevelObjects":492,"Missions_HexgatesUsed":0,"Missions_ImmobilizeChampions":17,"Missions_InspirationRune":0,"Missions_LegendaryItems":1,"Missions_MinionsKilled":11,"Missions_PeriodicDamage":4054,"Missions_PlaceUsefulControlWards":6,"Missions_PlaceUsefulWards":7,"Missions_PorosFed":0,"Missions_PrecisionRune":0,"Missions_ResolveRune":0,"Missions_SnowballsHit":0,"Missions_SorceryRune":0,"Missions_TakedownBaronsElderDragons":0,"Missions_TakedownDragons":2,"Missions_TakedownEpicMonsters":2,"Missions_TakedownEpicMonstersSingleGame":2,"Missions_TakedownGold":547,"Missions_TakedownStructures":0,"Missions_TakedownWards":10,"Missions_TakedownsAfterExhausting":2,"Missions_TakedownsAfterTeleporting":0,"Missions_TakedownsBefore15Min":1,"Missions_TakedownsUnderTurret":0,"Missions_TakedownsWithHelpFromMonsters":0,"Missions_TimeSpentActivelyPlaying":25,"Missions_TotalGold":0,"Missions_TrueDamageToStructures":0,"Missions_TurretPlatesDestroyed":2,"Missions_TwoChampsKilledWithSameAbility":0,"Missions_VoidMitesSummoned":0,"PlayerScore0":0.0,"PlayerScore1":0.0,"PlayerScore10":0.0,"PlayerScore11":0.0,"PlayerScore2":0.0,"PlayerScore3":0.0,"PlayerScore4":0.0,"PlayerScore5":0.0,"PlayerScore6":0.0,"PlayerScore7":0.0,"PlayerScore8":0.0,"PlayerScore9":0.0,"SeasonalMissions_TakedownAtakhan":0},"needVisionPings":3,"neutralMinionsKilled":151,"nexusKills":0,"nexusLost":1,"nexusTakedowns":0,"objectivesStolen":0,"objectivesStolenAssists":0,"onMyWayPings":38,"participantId":7,"pentaKills":0,"perks":{"statPerks":{"defense":5001,"flex":5008,"offense":5007},"styles":[{"description":"primaryStyle","selections":[{"perk":8112,"var1":983,"var2":0,"var3":0},{"perk":8126,"var1":208,"var2":0,"var3":0},{"perk":8140,"var1":2,"var2":0,"var3":0},{"perk":8135,"var1":50,"var2":1,"var3":0}],"style":8100},{"description":"subStyle","selections":[{"perk":9105,"var1":13,"var2":50,"var3":0},{"perk":8017,"var1":802,"var2":0,"var3":0}],"style":8000}]},"physicalDamageDealt":15053,"physicalDamageDealtToChampions":695,"physicalDamageTaken":6930,"placement":0,"playerAugment1":0,"playerAugment2":0,"playerAugment3":0,"playerAugment4":0,"playerAugment5":0,"playerAugment6":0,"playerSubteamId":0,"profileIcon":5180,"pushPings":0,"puuid":"eb170a7c-2508-5783-ab22-31e7fdfc0784","quadraKills":0,"retreatPings":6,"riotIdGameName":"BKR Rhilech","riotIdTagline":"eProd","role":"NONE","sightWardsBoughtInGame":0,"spell1Casts":126,"spell1Id":4,"spell2Casts":128,"spell2Id":11,"spell3Casts":54,"spell4Casts":6,"subteamPlacement":0,"summoner1Casts":4,"summoner2Casts":12,"summonerId":3372421564147040,"summonerLevel":30,"summonerName":"","teamEarlySurrendered":false,"teamId":200,"teamPosition":"BOTTOM","timeCCingOthers":32,"timePlayed":1508,"totalAllyJungleMinionsKilled":121,"totalDamageDealt":198065,"totalDamageDealtToChampions":13076,"totalDamageShieldedOnTeammates":0,"totalDamageTaken":13856,"totalEnemyJungleMinionsKilled":0,"totalHeal":6382,"totalHealsOnTeammates":0,"totalMinionsKilled":21,"totalTimeCCDealt":469,"totalTimeSpentDead":36,"totalUnitsHealed":1,"tripleKills":0,"trueDamageDealt":61538,"trueDamageDealtToChampions":1482,"trueDamageTaken":204,"turretKills":0,"turretTakedowns":0,"turretsLost":5,"unrealKills":0,"visionClearedPings":0,"visionScore":39,"visionWardsBoughtInGame":7,"wardsKilled":10,"wardsPlaced":7,"win":false},{"PlayerScore0":0.0,"PlayerScore1":0.0,"PlayerScore10":0.0,"PlayerScore11":0.0,"PlayerScore2":0.0,"PlayerScore3":0.0,"PlayerScore4":0.0,"PlayerScore5":0.0,"PlayerScore6":0.0,"PlayerScore7":0.0,"PlayerScore8":0.0,"PlayerScore9":0.0,"allInPings":1,"assistMePings":3,"assists":3,"baronKills":0,"basicPings":0,"bountyLevel":1,"challenges":{"12AssistStreakCount":0.0,"HealFromMapSources":360.0,"InfernalScalePickup":0.0,"SWARM_DefeatAatrox":0.0,"SWARM_DefeatBriar":0.0,"SWARM_DefeatMiniBosses":0.0,"SWARM_EvolveWeapon":0.0,"SWARM_Have3Passives":0.0,"SWARM_KillEnemy":0.0,"SWARM_PickupGold":0.0,"SWARM_ReachLevel50":0.0,"SWARM_Survive15Min":0.0,"SWARM_WinWith5EvolvedWeapons":0.0,"abilityUses":193.0,"acesBefore15Minutes":0.0,"alliedJungleMonsterKills":0.0,"baronTakedowns":0.0,"blastConeOppositeOpponentCount":0.0,"bountyGold":384.8218994140625,"buffsStolen":0.0,"completeSupportQuestInTime":0.0,"controlWardsPlaced":0.0,"damagePerMinute":681.0718833465274,"damageTakenOnTeamPercentage":0.221863909802717,"dancedWithRiftHerald":0.0,"deathsByEnemyChamps":8.0,"dodgeSkillShotsSmallWindow":0.0,"doubleAces":0.0,"dragonTakedowns":1.0,"earliestDragonTakedown":767.818515563,"earlyLaningPhaseGoldExpAdvantage":0.0,"effectiveHealAndShielding":0.0,"elderDragonKillsWithOpposingSoul":0.0,"elderDragonMultikills":0.0,"enemyChampionImmobilizations":6.0,"enemyJungleMonsterKills":0.0,"epicMonsterKillsNearEnemyJungler":0.0,"epicMonsterKillsWithin30SecondsOfSpawn":0.0,"epicMonsterSteals":0.0,"epicMonsterStolenWithoutSmite":0.0,"firstTurretKilled":0.0,"fistBumpParticipation":0.0,"flawlessAces":0.0,"fullTeamTakedown":0.0,"gameLength":1508.899957649,"getTakedownsInAllLanesEarlyJungleAsLaner":0.0,"goldPerMinute":325.9788368550134,"hadOpenNexus":0.0,"immobilizeAndKillWithAlly":1.0,"initialBuffCount":0.0,"initialCrabCount":0.0,"jungleCsBefore10Minutes":0.0,"junglerTakedownsNearDamagedEpicMonster":0.0,"kTurretsDestroyedBeforePlatesFall":0.0,"kda":0.5,"killAfterHiddenWithAlly":0.0,"killParticipation":0.6666666666666666,"killedChampTookFullTeamDamageSurvived":0.0,"killingSprees":0.0,"killsNearEnemyTurret":0.0,"killsOnOtherLanesEarlyJungleAsLaner":0.0,"killsOnRecentlyHealedByAramPack":0.0,"killsUnderOwnTurret":1.0,"killsWithHelpFromEpicMonster":0.0,"knockEnemyIntoTeamAndKill":0.0,"landSkillShotsEarlyGame":13.0,"laneMinionsFirst10Minutes":60.0,"laningPhaseGoldExpAdvantage":0.0,"legendaryCount":0.0,"legendaryItemUsed":[6655.0,3100.0],"lostAnInhibitor":0.0,"maxCsAdvantageOnLaneOpponent":7.0,"maxKillDeficit":0.0,"maxLevelLeadLaneOpponent":2.0,"mejaisFullStackInTime":0.0,"moreEnemyJungleThanOpponent":0.0,"multiKillOneSpell":0.0,"multiTurretRiftHeraldCount":0.0,"multikills":0.0,"multikillsAfterAggressiveFlash":0.0,"outerTurretExecutesBefore10Minutes":0.0,"outnumberedKills":0.0,"outnumberedNexusKill":0.0,"perfectDragonSoulsTaken":0.0,"perfectGame":0.0,"pickKillWithAlly":3.0,"poroExplosions":0.0,"quickCleanse":0.0,"quickFirstTurret":0.0,"quickSoloKills":0.0,"riftHeraldTakedowns":0.0,"saveAllyFromDeath":0.0,"scuttleCrabKills":0.0,"skillshotsDodged":18.0,"skillshotsHit":49.0,"snowballsHit":0.0,"soloBaronKills":0.0,"soloKills":1.0,"stealthWardsPlaced":6.0,"survivedSingleDigitHpCount":0.0,"survivedThreeImmobilizesInFight":0.0,"takedownOnFirstTurret":0.0,"takedowns":4.0,"takedownsAfterGainingLevelAdvantage":0.0,"takedownsBeforeJungleMinionSpawn":0.0,"takedownsFirstXMinutes":2.0,"takedownsInAlcove":0.0,"takedownsInEnemyFountain":0.0,"teamBaronKills":0.0,"teamDamagePercentage":0.256731855873881,"teamElderDragonKills":0.0,"teamRiftHeraldKills":0.0,"tookLargeDamageSurvived":0.0,"turretPlatesTaken":2.0,"turretTakedowns":0.0,"turretsTakenWithRiftHerald":0.0,"twentyMinionsIn3SecondsCount":0.0,"twoWardsOneSweeperCount":0.0,"unseenRecalls":0.0,"visionScoreAdvantageLaneOpponent":-0.38293516635894775,"visionScorePerMinute":0.7287084245632213,"voidMonsterKill":0.0,"wardTakedowns":3.0,"wardTakedownsBefore20M":2.0,"wardsGuarded":1.0},"champExperience":11548,"champLevel":14,"championId":112,"championName":"Viktor","championTransform":0,"commandPings":24,"consumablesPurchased":4,"damageDealtToBuildings":647,"damageDealtToObjectives":856,"damageDealtToTurrets":647,"damageSelfMitigated":12295,"dangerPings":0,"deaths":8,"detectorWardsPlaced":0,"doubleKills":0,"dragonKills":0,"eligibleForProgression":false,"enemyMissingPings":1,"enemyVisionPings":0,"firstBloodAssist":false,"firstBloodKill":false,"firstTowerAssist":false,"firstTowerKill":false,"gameEndedInEarlySurrender":false,"gameEndedInSurrender":true,"getBackPings":2,"goldEarned":8197,"goldSpent":7850,"holdPings":0,"individualPosition":"AFK","inhibitorKills":0,"inhibitorTakedowns":0,"inhibitorsLost":0,"item0":1056,"item1":6655,"item2":1001,"item3":1082,"item4":3100,"item5":1052,"item6":3363,"itemsPurchased":21,"killingSprees":0,"kills":1,"lane":"JUNGLE","largestCriticalStrike":0,"largestKillingSpree":0,"largestMultiKill":1,"longestTimeSpentLiving":422,"magicDamageDealt":90820,"magicDamageDealtToChampions":16555,"magicDamageTaken":14320,"missions":{"ActMission_S1_A2_ArenaRoundsWon":0,"ActMission_S1_A2_BloodyPetalsCollected":20,"ActMission_S1_A2_FeatsOfStrength":0,"DemonsHand_MissionPointsA":71,"DemonsHand_MissionPointsB":78,"DemonsHand_MissionPointsC":69,"DemonsHand_MissionPointsD":94,"DemonsHand_MissionPointsE":72,"DemonsHand_MissionPointsF":69,"Event_2025LR_StructuresEpicMonsters":1,"Event_S1_A1_AprilFools_Dragon":0,"Event_S1_A1_AprilFools_Snowball":0,"Event_S1_A2_AprilFools_Dragon":0,"Event_S1_A2_AprilFools_Garen_Play":0,"Event_S1_A2_AprilFools_Garen_Takedown":0,"Event_S1_A2_AprilFools_Snowball":0,"Event_S1_A2_Arena_BraveryChampions":0,"Event_S1_A2_Arena_NoxianChampions":0,"Event_S1_A2_Arena_ReviveAllies":0,"Event_S1_A2_Esports_TakedownEpicMonstersSingleGame":0,"Missions_CannonMinionsKilled":10,"Missions_ChampionTakedownsWhileGhosted":0,"Missions_ChampionTakedownsWithIgnite":0,"Missions_ChampionsHitWithAbilitiesEarlyGame":30,"Missions_ChampionsKilled":1,"Missions_CreepScore":177,"Missions_CreepScoreBy10Minutes":0,"Missions_Crepe_DamageDealtSpeedZone":0,"Missions_Crepe_SnowballLanded":0,"Missions_Crepe_TakedownsWithInhibBuff":0,"Missions_DamageToChampsWithItems":728,"Missions_DamageToStructures":647,"Missions_DestroyPlants":10,"Missions_DominationRune":0,"Missions_GoldFromStructuresDestroyed":133,"Missions_GoldFromTurretPlatesTaken":83,"Missions_GoldPerMinute":0,"Missions_HealingFromLevelObjects":116,"Missions_HexgatesUsed":0,"Missions_ImmobilizeChampions":6,"Missions_InspirationRune":0,"Missions_LegendaryItems":2,"Missions_MinionsKilled":172,"Missions_PeriodicDamage":4196,"Missions_PlaceUsefulControlWards":0,"Missions_PlaceUsefulWards":7,"Missions_PorosFed":0,"Missions_PrecisionRune":0,"Missions_ResolveRune":0,"Missions_SnowballsHit":0,"Missions_SorceryRune":1,"Missions_TakedownBaronsElderDragons":0,"Missions_TakedownDragons":1,"Missions_TakedownEpicMonsters":1,"Missions_TakedownEpicMonstersSingleGame":1,"Missions_TakedownGold":974,"Missions_TakedownStructures":0,"Missions_TakedownWards":3,"Missions_TakedownsAfterExhausting":3,"Missions_TakedownsAfterTeleporting":0,"Missions_TakedownsBefore15Min":2,"Missions_TakedownsUnderTurret":0,"Missions_TakedownsWithHelpFromMonsters":1,"Missions_TimeSpentActivelyPlaying":25,"Missions_TotalGold":0,"Missions_TrueDamageToStructures":0,"Missions_TurretPlatesDestroyed":0,"Missions_TwoChampsKilledWithSameAbility":0,"Missions_VoidMitesSummoned":0,"PlayerScore0":0.0,"PlayerScore1":0.0,"PlayerScore10":0.0,"PlayerScore11":0.0,"PlayerScore2":0.0,"PlayerScore3":0.0,"PlayerScore4":0.0,"PlayerScore5":0.0,"PlayerScore6":0.0,"PlayerScore7":0.0,"PlayerScore8":0.0,"PlayerScore9":0.0,"SeasonalMissions_TakedownAtakhan":0},"needVisionPings":1,"neutralMinionsKilled":0,"nexusKills":0,"nexusLost":1,"nexusTakedowns":0,"objectivesStolen":0,"objectivesStolenAssists":0,"onMyWayPings":20,"participantId":8,"pentaKills":0,"perks":{"statPerks":{"defense":5011,"flex":5008,"offense":5005},"styles":[{"description":"primaryStyle","selections":[{"perk":8229,"var1":1442,"var2":0,"var3":0},{"perk":8226,"var1":250,"var2":596,"var3":0},{"perk":8210,"var1":3,"var2":0,"var3":0},{"perk":8237,"var1":515,"var2":0,"var3":0}],"style":8200},{"description":"subStyle","selections":[{"perk":9105,"var1":21,"var2":0,"var3":0},{"perk":8017,"var1":754,"var2":0,"var3":0}],"style":8000}]},"physicalDamageDealt":11874,"physicalDamageDealtToChampions":572,"physicalDamageTaken":4544,"placement":0,"playerAugment1":0,"playerAugment2":0,"playerAugment3":0,"playerAugment4":0,"playerAugment5":0,"playerAugment6":0,"playerSubteamId":0,"profileIcon":29,"pushPings":0,"puuid":"75099c11-fb6b-5fbe-ab36-e7601095851a","quadraKills":0,"retreatPings":0,"riotIdGameName":"BKR OMON","riotIdTagline":"eProd","role":"NONE","sightWardsBoughtInGame":0,"spell1Casts":67,"spell1Id":4,"spell2Casts":20,"spell2Id":12,"spell3Casts":76,"spell4Casts":30,"subteamPlacement":0,"summoner1Casts":4,"summoner2Casts":4,"summonerId":3373306980541472,"summonerLevel":30,"summonerName":"","teamEarlySurrendered":false,"teamId":200,"teamPosition":"TOP","timeCCingOthers":18,"timePlayed":1508,"totalAllyJungleMinionsKilled":0,"totalDamageDealt":107275,"totalDamageDealtToChampions":17127,"totalDamageShieldedOnTeammates":0,"totalDamageTaken":19014,"totalEnemyJungleMinionsKilled":0,"totalHeal":1495,"totalHealsOnTeammates":0,"totalMinionsKilled":177,"totalTimeCCDealt":590,"totalTimeSpentDead":177,"totalUnitsHealed":1,"tripleKills":0,"trueDamageDealt":4581,"trueDamageDealtToChampions":0,"trueDamageTaken":149,"turretKills":0,"turretTakedowns":0,"turretsLost":5,"unrealKills":0,"visionClearedPings":0,"visionScore":18,"visionWardsBoughtInGame":0,"wardsKilled":3,"wardsPlaced":7,"win":false},{"PlayerScore0":0.0,"PlayerScore1":0.0,"PlayerScore10":0.0,"PlayerScore11":0.0,"PlayerScore2":0.0,"PlayerScore3":0.0,"PlayerScore4":0.0,"PlayerScore5":0.0,"PlayerScore6":0.0,"PlayerScore7":0.0,"PlayerScore8":0.0,"PlayerScore9":0.0,"allInPings":0,"assistMePings":1,"assists":0,"baronKills":0,"basicPings":0,"bountyLevel":3,"challenges":{"12AssistStreakCount":0.0,"HealFromMapSources":320.0,"InfernalScalePickup":0.0,"SWARM_DefeatAatrox":0.0,"SWARM_DefeatBriar":0.0,"SWARM_DefeatMiniBosses":0.0,"SWARM_EvolveWeapon":0.0,"SWARM_Have3Passives":0.0,"SWARM_KillEnemy":0.0,"SWARM_PickupGold":0.0,"SWARM_ReachLevel50":0.0,"SWARM_Survive15Min":0.0,"SWARM_WinWith5EvolvedWeapons":0.0,"abilityUses":194.0,"acesBefore15Minutes":0.0,"alliedJungleMonsterKills":0.0,"baronTakedowns":0.0,"blastConeOppositeOpponentCount":0.0,"bountyGold":524.7191467285156,"buffsStolen":0.0,"completeSupportQuestInTime":0.0,"controlWardTimeCoverageInRiverOrEnemyHalf":0.23185961766219534,"controlWardsPlaced":2.0,"damagePerMinute":676.8710270585624,"damageTakenOnTeamPercentage":0.15901175719938043,"dancedWithRiftHerald":0.0,"deathsByEnemyChamps":3.0,"dodgeSkillShotsSmallWindow":0.0,"doubleAces":0.0,"dragonTakedowns":1.0,"earliestDragonTakedown":767.818515563,"earlyLaningPhaseGoldExpAdvantage":0.0,"effectiveHealAndShielding":0.0,"elderDragonKillsWithOpposingSoul":0.0,"elderDragonMultikills":0.0,"enemyChampionImmobilizations":0.0,"enemyJungleMonsterKills":0.0,"epicMonsterKillsNearEnemyJungler":0.0,"epicMonsterKillsWithin30SecondsOfSpawn":0.0,"epicMonsterSteals":0.0,"epicMonsterStolenWithoutSmite":0.0,"firstTurretKilled":0.0,"fistBumpParticipation":0.0,"flawlessAces":0.0,"fullTeamTakedown":0.0,"gameLength":1508.899957649,"getTakedownsInAllLanesEarlyJungleAsLaner":0.0,"goldPerMinute":390.93254823058805,"hadOpenNexus":0.0,"immobilizeAndKillWithAlly":0.0,"initialBuffCount":0.0,"initialCrabCount":0.0,"jungleCsBefore10Minutes":0.0,"junglerTakedownsNearDamagedEpicMonster":1.0,"kTurretsDestroyedBeforePlatesFall":0.0,"kda":1.0,"killAfterHiddenWithAlly":0.0,"killParticipation":0.5,"killedChampTookFullTeamDamageSurvived":0.0,"killingSprees":1.0,"killsNearEnemyTurret":1.0,"killsOnOtherLanesEarlyJungleAsLaner":0.0,"killsOnRecentlyHealedByAramPack":0.0,"killsUnderOwnTurret":1.0,"killsWithHelpFromEpicMonster":0.0,"knockEnemyIntoTeamAndKill":0.0,"landSkillShotsEarlyGame":2.0,"laneMinionsFirst10Minutes":70.0,"laningPhaseGoldExpAdvantage":0.0,"legendaryCount":0.0,"legendaryItemUsed":[3078.0,3004.0,3042.0],"lostAnInhibitor":0.0,"maxCsAdvantageOnLaneOpponent":8.0,"maxKillDeficit":0.0,"maxLevelLeadLaneOpponent":0.0,"mejaisFullStackInTime":0.0,"moreEnemyJungleThanOpponent":0.0,"multiKillOneSpell":0.0,"multiTurretRiftHeraldCount":0.0,"multikills":0.0,"multikillsAfterAggressiveFlash":0.0,"outerTurretExecutesBefore10Minutes":0.0,"outnumberedKills":1.0,"outnumberedNexusKill":0.0,"perfectDragonSoulsTaken":0.0,"perfectGame":0.0,"pickKillWithAlly":3.0,"poroExplosions":0.0,"quickCleanse":0.0,"quickFirstTurret":0.0,"quickSoloKills":0.0,"riftHeraldTakedowns":0.0,"saveAllyFromDeath":0.0,"scuttleCrabKills":0.0,"skillshotsDodged":5.0,"skillshotsHit":33.0,"snowballsHit":0.0,"soloBaronKills":0.0,"soloKills":0.0,"stealthWardsPlaced":5.0,"survivedSingleDigitHpCount":0.0,"survivedThreeImmobilizesInFight":12.0,"takedownOnFirstTurret":0.0,"takedowns":3.0,"takedownsAfterGainingLevelAdvantage":0.0,"takedownsBeforeJungleMinionSpawn":0.0,"takedownsFirstXMinutes":0.0,"takedownsInAlcove":0.0,"takedownsInEnemyFountain":0.0,"teamBaronKills":0.0,"teamDamagePercentage":0.2551483319354541,"teamElderDragonKills":0.0,"teamRiftHeraldKills":0.0,"tookLargeDamageSurvived":0.0,"turretPlatesTaken":1.0,"turretTakedowns":0.0,"turretsTakenWithRiftHerald":0.0,"twentyMinionsIn3SecondsCount":0.0,"twoWardsOneSweeperCount":0.0,"unseenRecalls":0.0,"visionScoreAdvantageLaneOpponent":-0.4504320025444031,"visionScorePerMinute":0.839038831723734,"voidMonsterKill":0.0,"wardTakedowns":6.0,"wardTakedownsBefore20M":4.0,"wardsGuarded":2.0},"champExperience":10439,"champLevel":13,"championId":42,"championName":"Corki","championTransform":0,"commandPings":5,"consumablesPurchased":3,"damageDealtToBuildings":823,"damageDealtToObjectives":1992,"damageDealtToTurrets":823,"damageSelfMitigated":8287,"dangerPings":0,"deaths":3,"detectorWardsPlaced":2,"doubleKills":0,"dragonKills":0,"eligibleForProgression":false,"enemyMissingPings":2,"enemyVisionPings":4,"firstBloodAssist":false,"firstBloodKill":false,"firstTowerAssist":false,"firstTowerKill":false,"gameEndedInEarlySurrender":false,"gameEndedInSurrender":true,"getBackPings":0,"goldEarned":9831,"goldSpent":8883,"holdPings":0,"individualPosition":"AFK","inhibitorKills":0,"inhibitorTakedowns":0,"inhibitorsLost":0,"item0":1055,"item1":1001,"item2":3078,"item3":3042,"item4":1042,"item5":3035,"item6":3363,"itemsPurchased":20,"killingSprees":1,"kills":3,"lane":"BOTTOM","largestCriticalStrike":0,"largestKillingSpree":3,"largestMultiKill":1,"longestTimeSpentLiving":865,"magicDamageDealt":37197,"magicDamageDealtToChampions":2640,"magicDamageTaken":6192,"missions":{"ActMission_S1_A2_ArenaRoundsWon":0,"ActMission_S1_A2_BloodyPetalsCollected":20,"ActMission_S1_A2_FeatsOfStrength":0,"DemonsHand_MissionPointsA":74,"DemonsHand_MissionPointsB":69,"DemonsHand_MissionPointsC":73,"DemonsHand_MissionPointsD":70,"DemonsHand_MissionPointsE":84,"DemonsHand_MissionPointsF":83,"Event_2025LR_StructuresEpicMonsters":1,"Event_S1_A1_AprilFools_Dragon":0,"Event_S1_A1_AprilFools_Snowball":0,"Event_S1_A2_AprilFools_Dragon":0,"Event_S1_A2_AprilFools_Garen_Play":0,"Event_S1_A2_AprilFools_Garen_Takedown":0,"Event_S1_A2_AprilFools_Snowball":0,"Event_S1_A2_Arena_BraveryChampions":0,"Event_S1_A2_Arena_NoxianChampions":0,"Event_S1_A2_Arena_ReviveAllies":0,"Event_S1_A2_Esports_TakedownEpicMonstersSingleGame":0,"Missions_CannonMinionsKilled":15,"Missions_ChampionTakedownsWhileGhosted":0,"Missions_ChampionTakedownsWithIgnite":0,"Missions_ChampionsHitWithAbilitiesEarlyGame":11,"Missions_ChampionsKilled":3,"Missions_CreepScore":216,"Missions_CreepScoreBy10Minutes":1,"Missions_Crepe_DamageDealtSpeedZone":0,"Missions_Crepe_SnowballLanded":0,"Missions_Crepe_TakedownsWithInhibBuff":0,"Missions_DamageToChampsWithItems":2015,"Missions_DamageToStructures":823,"Missions_DestroyPlants":8,"Missions_DominationRune":0,"Missions_GoldFromStructuresDestroyed":112,"Missions_GoldFromTurretPlatesTaken":62,"Missions_GoldPerMinute":0,"Missions_HealingFromLevelObjects":242,"Missions_HexgatesUsed":0,"Missions_ImmobilizeChampions":0,"Missions_InspirationRune":0,"Missions_LegendaryItems":2,"Missions_MinionsKilled":202,"Missions_PeriodicDamage":2342,"Missions_PlaceUsefulControlWards":2,"Missions_PlaceUsefulWards":9,"Missions_PorosFed":0,"Missions_PrecisionRune":1,"Missions_ResolveRune":0,"Missions_SnowballsHit":0,"Missions_SorceryRune":0,"Missions_TakedownBaronsElderDragons":0,"Missions_TakedownDragons":1,"Missions_TakedownEpicMonsters":1,"Missions_TakedownEpicMonstersSingleGame":1,"Missions_TakedownGold":1545,"Missions_TakedownStructures":0,"Missions_TakedownWards":6,"Missions_TakedownsAfterExhausting":0,"Missions_TakedownsAfterTeleporting":0,"Missions_TakedownsBefore15Min":0,"Missions_TakedownsUnderTurret":1,"Missions_TakedownsWithHelpFromMonsters":0,"Missions_TimeSpentActivelyPlaying":25,"Missions_TotalGold":0,"Missions_TrueDamageToStructures":207,"Missions_TurretPlatesDestroyed":0,"Missions_TwoChampsKilledWithSameAbility":0,"Missions_VoidMitesSummoned":0,"PlayerScore0":0.0,"PlayerScore1":0.0,"PlayerScore10":0.0,"PlayerScore11":0.0,"PlayerScore2":0.0,"PlayerScore3":0.0,"PlayerScore4":0.0,"PlayerScore5":0.0,"PlayerScore6":0.0,"PlayerScore7":0.0,"PlayerScore8":0.0,"PlayerScore9":0.0,"SeasonalMissions_TakedownAtakhan":0},"needVisionPings":0,"neutralMinionsKilled":0,"nexusKills":0,"nexusLost":1,"nexusTakedowns":0,"objectivesStolen":0,"objectivesStolenAssists":0,"onMyWayPings":19,"participantId":9,"pentaKills":0,"perks":{"statPerks":{"defense":5011,"flex":5008,"offense":5005},"styles":[{"description":"primaryStyle","selections":[{"perk":8010,"var1":156,"var2":0,"var3":0},{"perk":8009,"var1":967,"var2":0,"var3":0},{"perk":9103,"var1":0,"var2":0,"var3":0},{"perk":8017,"var1":697,"var2":0,"var3":0}],"style":8000},{"description":"subStyle","selections":[{"perk":8345,"var1":3,"var2":0,"var3":206},{"perk":8316,"var1":8,"var2":10,"var3":0}],"style":8300}]},"physicalDamageDealt":82570,"physicalDamageDealtToChampions":12132,"physicalDamageTaken":6857,"placement":0,"playerAugment1":0,"playerAugment2":0,"playerAugment3":0,"playerAugment4":0,"playerAugment5":0,"playerAugment6":0,"playerSubteamId":0,"profileIcon":29,"pushPings":0,"puuid":"d6bd841f-1ae8-5e3c-8434-813e0531dcf3","quadraKills":0,"retreatPings":0,"riotIdGameName":"BKR BOOSHI","riotIdTagline":"eProd","role":"SOLO","sightWardsBoughtInGame":0,"spell1Casts":50,"spell1Id":21,"spell2Casts":20,"spell2Id":4,"spell3Casts":48,"spell4Casts":76,"subteamPlacement":0,"summoner1Casts":5,"summoner2Casts":2,"summonerId":3394942411228448,"summonerLevel":30,"summonerName":"","teamEarlySurrendered":false,"teamId":200,"teamPosition":"UTILITY","timeCCingOthers":0,"timePlayed":1508,"totalAllyJungleMinionsKilled":0,"totalDamageDealt":131977,"totalDamageDealtToChampions":17022,"totalDamageShieldedOnTeammates":0,"totalDamageTaken":13627,"totalEnemyJungleMinionsKilled":0,"totalHeal":3464,"totalHealsOnTeammates":0,"totalMinionsKilled":216,"totalTimeCCDealt":0,"totalTimeSpentDead":53,"totalUnitsHealed":1,"tripleKills":0,"trueDamageDealt":12209,"trueDamageDealtToChampions":2249,"trueDamageTaken":578,"turretKills":0,"turretTakedowns":0,"turretsLost":5,"unrealKills":0,"visionClearedPings":0,"visionScore":21,"visionWardsBoughtInGame":2,"wardsKilled":6,"wardsPlaced":9,"win":false},{"PlayerScore0":0.0,"PlayerScore1":0.0,"PlayerScore10":0.0,"PlayerScore11":0.0,"PlayerScore2":0.0,"PlayerScore3":0.0,"PlayerScore4":0.0,"PlayerScore5":0.0,"PlayerScore6":0.0,"PlayerScore7":0.0,"PlayerScore8":0.0,"PlayerScore9":0.0,"allInPings":1,"assistMePings":7,"assists":3,"baronKills":0,"basicPings":0,"bountyLevel":0,"challenges":{"12AssistStreakCount":0.0,"HealFromMapSources":0.0,"InfernalScalePickup":0.0,"SWARM_DefeatAatrox":0.0,"SWARM_DefeatBriar":0.0,"SWARM_DefeatMiniBosses":0.0,"SWARM_EvolveWeapon":0.0,"SWARM_Have3Passives":0.0,"SWARM_KillEnemy":0.0,"SWARM_PickupGold":0.0,"SWARM_ReachLevel50":0.0,"SWARM_Survive15Min":0.0,"SWARM_WinWith5EvolvedWeapons":0.0,"abilityUses":43.0,"acesBefore15Minutes":0.0,"alliedJungleMonsterKills":0.0,"baronTakedowns":0.0,"blastConeOppositeOpponentCount":1.0,"bountyGold":0.0,"buffsStolen":0.0,"completeSupportQuestInTime":1.0,"controlWardTimeCoverageInRiverOrEnemyHalf":0.565910675057249,"controlWardsPlaced":7.0,"damagePerMinute":88.43542237620358,"damageTakenOnTeamPercentage":0.22103600012401894,"dancedWithRiftHerald":0.0,"deathsByEnemyChamps":4.0,"dodgeSkillShotsSmallWindow":0.0,"doubleAces":0.0,"dragonTakedowns":1.0,"earliestDragonTakedown":767.818515563,"earlyLaningPhaseGoldExpAdvantage":0.0,"effectiveHealAndShielding":2157.59423828125,"elderDragonKillsWithOpposingSoul":0.0,"elderDragonMultikills":0.0,"enemyChampionImmobilizations":44.0,"enemyJungleMonsterKills":0.0,"epicMonsterKillsNearEnemyJungler":0.0,"epicMonsterKillsWithin30SecondsOfSpawn":0.0,"epicMonsterSteals":0.0,"epicMonsterStolenWithoutSmite":0.0,"firstTurretKilled":0.0,"fistBumpParticipation":0.0,"flawlessAces":0.0,"fullTeamTakedown":0.0,"gameLength":1508.899957649,"goldPerMinute":208.21667677368245,"hadOpenNexus":0.0,"immobilizeAndKillWithAlly":1.0,"initialBuffCount":0.0,"initialCrabCount":0.0,"jungleCsBefore10Minutes":0.0,"junglerKillsEarlyJungle":0.0,"junglerTakedownsNearDamagedEpicMonster":0.0,"kTurretsDestroyedBeforePlatesFall":0.0,"kda":0.75,"killAfterHiddenWithAlly":0.0,"killParticipation":0.5,"killedChampTookFullTeamDamageSurvived":0.0,"killingSprees":0.0,"killsNearEnemyTurret":0.0,"killsOnLanersEarlyJungleAsJungler":0.0,"killsOnRecentlyHealedByAramPack":0.0,"killsUnderOwnTurret":0.0,"killsWithHelpFromEpicMonster":0.0,"knockEnemyIntoTeamAndKill":1.0,"landSkillShotsEarlyGame":0.0,"laneMinionsFirst10Minutes":6.0,"laningPhaseGoldExpAdvantage":0.0,"legendaryCount":0.0,"legendaryItemUsed":[3869.0,3190.0],"lostAnInhibitor":0.0,"maxCsAdvantageOnLaneOpponent":0.0,"maxKillDeficit":0.0,"maxLevelLeadLaneOpponent":1.0,"mejaisFullStackInTime":0.0,"moreEnemyJungleThanOpponent":0.0,"multiKillOneSpell":0.0,"multiTurretRiftHeraldCount":0.0,"multikills":0.0,"multikillsAfterAggressiveFlash":0.0,"outerTurretExecutesBefore10Minutes":0.0,"outnumberedKills":0.0,"outnumberedNexusKill":0.0,"perfectDragonSoulsTaken":0.0,"perfectGame":0.0,"pickKillWithAlly":3.0,"poroExplosions":0.0,"quickCleanse":0.0,"quickFirstTurret":0.0,"quickSoloKills":0.0,"riftHeraldTakedowns":0.0,"saveAllyFromDeath":0.0,"scuttleCrabKills":0.0,"skillshotsDodged":25.0,"skillshotsHit":0.0,"snowballsHit":0.0,"soloBaronKills":0.0,"soloKills":0.0,"stealthWardsPlaced":35.0,"survivedSingleDigitHpCount":0.0,"survivedThreeImmobilizesInFight":12.0,"takedownOnFirstTurret":0.0,"takedowns":3.0,"takedownsAfterGainingLevelAdvantage":0.0,"takedownsBeforeJungleMinionSpawn":0.0,"takedownsFirstXMinutes":2.0,"takedownsInAlcove":0.0,"takedownsInEnemyFountain":0.0,"teamBaronKills":0.0,"teamDamagePercentage":0.03333596741664559,"teamElderDragonKills":0.0,"teamRiftHeraldKills":0.0,"tookLargeDamageSurvived":0.0,"turretPlatesTaken":3.0,"turretTakedowns":0.0,"turretsTakenWithRiftHerald":0.0,"twentyMinionsIn3SecondsCount":0.0,"twoWardsOneSweeperCount":0.0,"unseenRecalls":0.0,"visionScoreAdvantageLaneOpponent":-0.031633198261260986,"visionScorePerMinute":2.7774311759019112,"voidMonsterKill":0.0,"wardTakedowns":4.0,"wardTakedownsBefore20M":4.0,"wardsGuarded":4.0},"champExperience":7138,"champLevel":10,"championId":12,"championName":"Alistar","championTransform":0,"commandPings":36,"consumablesPurchased":9,"damageDealtToBuildings":455,"damageDealtToObjectives":691,"damageDealtToTurrets":455,"damageSelfMitigated":23491,"dangerPings":0,"deaths":4,"detectorWardsPlaced":7,"doubleKills":0,"dragonKills":0,"eligibleForProgression":false,"enemyMissingPings":8,"enemyVisionPings":0,"firstBloodAssist":false,"firstBloodKill":false,"firstTowerAssist":false,"firstTowerKill":false,"gameEndedInEarlySurrender":false,"gameEndedInSurrender":true,"getBackPings":5,"goldEarned":5236,"goldSpent":5075,"holdPings":0,"individualPosition":"AFK","inhibitorKills":0,"inhibitorTakedowns":0,"inhibitorsLost":0,"item0":3869,"item1":3067,"item2":3190,"item3":3158,"item4":0,"item5":0,"item6":3364,"itemsPurchased":22,"killingSprees":0,"kills":0,"lane":"JUNGLE","largestCriticalStrike":0,"largestKillingSpree":0,"largestMultiKill":0,"longestTimeSpentLiving":700,"magicDamageDealt":2877,"magicDamageDealtToChampions":2016,"magicDamageTaken":10559,"missions":{"ActMission_S1_A2_ArenaRoundsWon":0,"ActMission_S1_A2_BloodyPetalsCollected":20,"ActMission_S1_A2_FeatsOfStrength":0,"DemonsHand_MissionPointsA":68,"DemonsHand_MissionPointsB":69,"DemonsHand_MissionPointsC":69,"DemonsHand_MissionPointsD":113,"DemonsHand_MissionPointsE":69,"DemonsHand_MissionPointsF":69,"Event_2025LR_StructuresEpicMonsters":1,"Event_S1_A1_AprilFools_Dragon":0,"Event_S1_A1_AprilFools_Snowball":0,"Event_S1_A2_AprilFools_Dragon":0,"Event_S1_A2_AprilFools_Garen_Play":0,"Event_S1_A2_AprilFools_Garen_Takedown":0,"Event_S1_A2_AprilFools_Snowball":0,"Event_S1_A2_Arena_BraveryChampions":0,"Event_S1_A2_Arena_NoxianChampions":0,"Event_S1_A2_Arena_ReviveAllies":0,"Event_S1_A2_Esports_TakedownEpicMonstersSingleGame":0,"Missions_CannonMinionsKilled":3,"Missions_ChampionTakedownsWhileGhosted":0,"Missions_ChampionTakedownsWithIgnite":0,"Missions_ChampionsHitWithAbilitiesEarlyGame":12,"Missions_ChampionsKilled":0,"Missions_CreepScore":14,"Missions_CreepScoreBy10Minutes":0,"Missions_Crepe_DamageDealtSpeedZone":0,"Missions_Crepe_SnowballLanded":0,"Missions_Crepe_TakedownsWithInhibBuff":0,"Missions_DamageToChampsWithItems":0,"Missions_DamageToStructures":455,"Missions_DestroyPlants":13,"Missions_DominationRune":0,"Missions_GoldFromStructuresDestroyed":195,"Missions_GoldFromTurretPlatesTaken":145,"Missions_GoldPerMinute":0,"Missions_HealingFromLevelObjects":0,"Missions_HexgatesUsed":0,"Missions_ImmobilizeChampions":39,"Missions_InspirationRune":0,"Missions_LegendaryItems":2,"Missions_MinionsKilled":10,"Missions_PeriodicDamage":187,"Missions_PlaceUsefulControlWards":7,"Missions_PlaceUsefulWards":41,"Missions_PorosFed":0,"Missions_PrecisionRune":0,"Missions_ResolveRune":1,"Missions_SnowballsHit":0,"Missions_SorceryRune":0,"Missions_TakedownBaronsElderDragons":0,"Missions_TakedownDragons":1,"Missions_TakedownEpicMonsters":1,"Missions_TakedownEpicMonstersSingleGame":1,"Missions_TakedownGold":259,"Missions_TakedownStructures":0,"Missions_TakedownWards":4,"Missions_TakedownsAfterExhausting":3,"Missions_TakedownsAfterTeleporting":1,"Missions_TakedownsBefore15Min":2,"Missions_TakedownsUnderTurret":1,"Missions_TakedownsWithHelpFromMonsters":1,"Missions_TimeSpentActivelyPlaying":25,"Missions_TotalGold":0,"Missions_TrueDamageToStructures":0,"Missions_TurretPlatesDestroyed":1,"Missions_TwoChampsKilledWithSameAbility":0,"Missions_VoidMitesSummoned":0,"PlayerScore0":0.0,"PlayerScore1":0.0,"PlayerScore10":0.0,"PlayerScore11":0.0,"PlayerScore2":0.0,"PlayerScore3":0.0,"PlayerScore4":0.0,"PlayerScore5":0.0,"PlayerScore6":0.0,"PlayerScore7":0.0,"PlayerScore8":0.0,"PlayerScore9":0.0,"SeasonalMissions_TakedownAtakhan":0},"needVisionPings":0,"neutralMinionsKilled":0,"nexusKills":0,"nexusLost":1,"nexusTakedowns":0,"objectivesStolen":0,"objectivesStolenAssists":0,"onMyWayPings":125,"participantId":10,"pentaKills":0,"perks":{"statPerks":{"defense":5011,"flex":5001,"offense":5007},"styles":[{"description":"primaryStyle","selections":[{"perk":8439,"var1":142,"var2":659,"var3":0},{"perk":8463,"var1":566,"var2":0,"var3":0},{"perk":8473,"var1":688,"var2":0,"var3":0},{"perk":8453,"var1":685,"var2":159,"var3":0}],"style":8400},{"description":"subStyle","selections":[{"perk":8347,"var1":0,"var2":0,"var3":0},{"perk":8306,"var1":4,"var2":0,"var3":0}],"style":8300}]},"physicalDamageDealt":2400,"physicalDamageDealtToChampions":207,"physicalDamageTaken":8035,"placement":0,"playerAugment1":0,"playerAugment2":0,"playerAugment3":0,"playerAugment4":0,"playerAugment5":0,"playerAugment6":0,"playerSubteamId":0,"profileIcon":29,"pushPings":0,"puuid":"655f6c44-d126-53cd-a5e7-5e32394c1834","quadraKills":0,"retreatPings":0,"riotIdGameName":"BKR Doss","riotIdTagline":"eProd","role":"NONE","sightWardsBoughtInGame":0,"spell1Casts":14,"spell1Id":4,"spell2Casts":13,"spell2Id":3,"spell3Casts":12,"spell4Casts":4,"subteamPlacement":0,"summoner1Casts":8,"summoner2Casts":5,"summonerId":3372424908956704,"summonerLevel":30,"summonerName":"","teamEarlySurrendered":false,"teamId":200,"teamPosition":"JUNGLE","timeCCingOthers":31,"timePlayed":1508,"totalAllyJungleMinionsKilled":0,"totalDamageDealt":7168,"totalDamageDealtToChampions":2224,"totalDamageShieldedOnTeammates":77,"totalDamageTaken":18943,"totalEnemyJungleMinionsKilled":0,"totalHeal":6812,"totalHealsOnTeammates":2080,"totalMinionsKilled":14,"totalTimeCCDealt":64,"totalTimeSpentDead":67,"totalUnitsHealed":5,"tripleKills":0,"trueDamageDealt":1890,"trueDamageDealtToChampions":0,"trueDamageTaken":348,"turretKills":0,"turretTakedowns":0,"turretsLost":5,"unrealKills":0,"visionClearedPings":0,"visionScore":69,"visionWardsBoughtInGame":7,"wardsKilled":4,"wardsPlaced":42,"win":false}],"platformId":"LOLTMNT99","queueId":0,"seasonId":0,"teams":[{"bans":[{"championId":78,"pickTurn":1},{"championId":201,"pickTurn":3},{"championId":1,"pickTurn":5},{"championId":163,"pickTurn":2},{"championId":516,"pickTurn":4}],"feats":{"EPIC_MONSTER_KILL":{"featState":1},"FIRST_BLOOD":{"featState":3},"FIRST_TURRET":{"featState":1}},"objectives":{"atakhan":{"first":true,"kills":1},"baron":{"first":false,"kills":0},"champion":{"first":true,"kills":20},"dragon":{"first":false,"kills":2},"horde":{"first":true,"kills":5},"inhibitor":{"first":false,"kills":0},"riftHerald":{"first":true,"kills":1},"tower":{"first":true,"kills":5}},"teamId":100,"win":true},{"bans":[{"championId":950,"pickTurn":2},{"championId":57,"pickTurn":4},{"championId":68,"pickTurn":6},{"championId":58,"pickTurn":1},{"championId":18,"pickTurn":3}],"feats":{"EPIC_MONSTER_KILL":{"featState":2},"FIRST_BLOOD":{"featState":1001},"FIRST_TURRET":{"featState":1001}},"objectives":{"atakhan":{"first":false,"kills":0},"baron":{"first":false,"kills":0},"champion":{"first":false,"kills":6},"dragon":{"first":true,"kills":2},"horde":{"first":false,"kills":1},"inhibitor":{"first":false,"kills":0},"riftHerald":{"first":false,"kills":0},"tower":{"first":false,"kills":1}},"teamId":200,"win":false}],"tournamentCode":""}